Workbook

Sheet Landing Sheet
A1: YOUR COMPANY NAME | D1: Flowerama
R2: =AF9/7 -> 142.85714
AE5: 3000 | AF5: 1000 | AG5: 300 | AH5: 300 | AI5: 100 | AJ5: 480 | AK5: 83 | AL5: 1000
V6: KPI | AE6: 1 | AF6: Sunday | AG6: 15 | AH6: 10 | AI6: 20 | AJ6: 12 | AK6: 25 | AL6: 5
A7: Date | B7: Dayo Month | C7: Dayo Year | D7: Dayo Week # | E7: Dayo Week Name | F7: Weeko Year | G7: Month # | H7: Month Name | I7: Quarter | J7: Foot Traffic (customers per day) | K7: Spend per Customer | L7: Total Revenue | M7: Daily COGS | N7: COGS | O7: Gross Margin | P7: buy online | Q7: Stems discard | R7: Wages paied by day | S7: Online Orders | T7: Delvery Total rev | U7: Delevry orders | V7: Peps in door | W7: Online delevery | X7: Conversion Rate | Y7: Avg Delevry cost % | Z7: Delevery percentage | AA7: percent of wage per hr | AB7: Average Delevery value per Order | AC7: Dollar wasted oer stem discarded | AD7: online order % | AE7: Rent / Lease | AF7: Wages and Salaries | AG7: Insurance | AH7: Electric | AI7: Water | AJ7: Phone | AK7: Internet | AL7: Delivery | AM7: Total Expenses | AN7: Profit
A8: 44562 | B8: 1 | C8: 1 | D8: 7 | E8: Saturday | F8: 1 | G8: 1 | H8: January | I8: 1 | J8: 18.248423 | K8: 63.210073 | L8: =J8*K8 -> 1153.4842 | M8: 0.38876823 | N8: =L8*M8 -> 448.43799 | O8: =L8-N8 -> 705.04617 | P8: 43.748147 | Q8: 6.6793627 | R8: =IF(E8=$AF$6,$R$2/5,$R$2/11) -> 12.987013 | S8: 28.155118 | T8: =L8*0.7 -> 807.43891 | U8: =T8/J8 -> 44.247051 | V8: 26.334351 | W8: =P8/U8 -> 0.98872459 | X8: =J8/V8 -> 0.69295131 | Y8: =N8/T8 -> 0.55538318 | Z8: =J8/U8 -> 0.41242123 | AA8: =R8/L8 -> 0.011258944 | AB8: =T8/J8 -> 44.247051 | AC8: =Q8/K8 -> 0.10566928 | AD8: =P8/L8 -> 0.03792696 | AE8: =IF(B8=$AE$6,$AE$5, ) -> 3000 | AF8: =IF(E8=$AF$6,$AF$5,"") | AG8: =IF(B8=$AG$6,$AG$5,"") | AH8: =IF($B$8=AH6,AH5,"") | AI8: =IF($B8=$AI$6,$AI$5,"") | AJ8: =IF($B8=$AJ$6,$AJ$5,"") | AK8: =IF($B8=$AK$6,$AK$5,"") | AL8: =IF($B8=$AL$6,$AL$5,"") | AM8: =SUM(AE8:AL8) -> 3000 | AN8: =O8-AM8 -> -2294.9538
A9: 44563 | B9: 2 | C9: 2 | D9: 1 | E9: Sunday | F9: 1 | G9: 1 | H9: January | I9: 1 | J9: 5.6481892 | K9: 37.00637 | L9: =J9*K9 -> 209.01898 | M9: 0.21121235 | N9: =L9*M9 -> 44.14739 | O9: =L9-N9 -> 164.87159 | P9: 15.607485 | Q9: 7.0101524 | R9: =IF(E9=$AF$6,$R$2/5,$R$2/11) -> 28.571429 | S9: 13.589794 | T9: =L9*0.7 -> 146.31329 | U9: =T9/J9 -> 25.904459 | V9: 13.883588 | W9: =P9/U9 -> 0.60250188 | X9: =J9/V9 -> 0.40682489 | Y9: =N9/T9 -> 0.30173193 | Z9: =J9/U9 -> 0.21803926 | AA9: =R9/L9 -> 0.13669299 | AB9: =T9/J9 -> 25.904459 | AC9: =Q9/K9 -> 0.18943096 | AD9: =P9/L9 -> 0.074670182 | AE9: =IF(B9=$AE$6,$AE$5, "") | AF9: =IF(E9=$AF$6,$AF$5,"") -> 1000 | AG9: =IF(B9=$AG$6,$AG$5,"") | AH9: =IF(B9=$AH$6,$AH$5,"") | AI9: =IF($B9=$AI$6,$AI$5,"") | AJ9: =IF($B9=$AJ$6,$AJ$5,"") | AK9: =IF($B9=$AK$6,$AK$5,"") | AL9: =IF($B9=$AL$6,$AL$5,"") | AM9: =SUM(AE9:AL9) -> 1000 | AN9: =O9-AM9 -> -835.12841
A10: 44564 | B10: 3 | C10: 3 | D10: 2 | E10: Monday | F10: 1 | G10: 1 | H10: January | I10: 1 | J10: 10.949241 | K10: 8.9188617 | L10: =J10*K10 -> 97.654762 | M10: 0.50933335 | N10: =L10*M10 -> 49.738827 | O10: =L10-N10 -> 47.915935 | P10: 36.952446 | Q10: 7.7018362 | R10: =IF(E10=$AF$6,$R$2/5,$R$2/11) -> 12.987013 | S10: 30.385295 | T10: =L10*0.7 -> 68.358333 | U10: =T10/J10 -> 6.2432032 | V10: 25.259286 | W10: =P10/U10 -> 5.918828 | X10: =J10/V10 -> 0.43347387 | Y10: =N10/T10 -> 0.72761907 | Z10: =J10/U10 -> 1.7537857 | AA10: =R10/L10 -> 0.13298904 | AB10: =T10/J10 -> 6.2432032 | AC10: =Q10/K10 -> 0.86354475 | AD10: =P10/L10 -> 0.37839881 | AE10: =IF(B10=$AE$6,$AE$5, "") | AF10: =IF(E10=$AF$6,$AF$5,"") | AG10: =IF(B10=$AG$6,$AG$5,"") | AH10: =IF(B10=$AH$6,$AH$5,"") | AI10: =IF($B10=$AI$6,$AI$5,"") | AJ10: =IF($B10=$AJ$6,$AJ$5,"") | AK10: =IF($B10=$AK$6,$AK$5,"") | AL10: =IF($B10=$AL$6,$AL$5,"") | AM10: =SUM(AE10:AL10) -> 0 | AN10: =O10-AM10 -> 47.915935
A11: 44565 | B11: 4 | C11: 4 | D11: 3 | E11: Tuesday | F11: 1 | G11: 1 | H11: January | I11: 1 | J11: 12.174664 | K11: 27.250856 | L11: =J11*K11 -> 331.77002 | M11: 0.36085715 | N11: =L11*M11 -> 119.72158 | O11: =L11-N11 -> 212.04843 | P11: 26.314823 | Q11: 5.9731019 | R11: =IF(E11=$AF$6,$R$2/5,$R$2/11) -> 12.987013 | S11: 25.204278 | T11: =L11*0.7 -> 232.23901 | U11: =T11/J11 -> 19.075599 | V11: 35.670771 | W11: =P11/U11 -> 1.3795018 | X11: =J11/V11 -> 0.34130645 | Y11: =N11/T11 -> 0.51551022 | Z11: =J11/U11 -> 0.63823233 | AA11: =R11/L11 -> 0.039144625 | AB11: =T11/J11 -> 19.075599 | AC11: =Q11/K11 -> 0.21918952 | AD11: =P11/L11 -> 0.07931646 | AE11: =IF(B11=$AE$6,$AE$5, "") | AF11: =IF(E11=$AF$6,$AF$5,"") | AG11: =IF(B11=$AG$6,$AG$5,"") | AH11: =IF(B11=$AH$6,$AH$5,"") | AI11: =IF($B11=$AI$6,$AI$5,"") | AJ11: =IF($B11=$AJ$6,$AJ$5,"") | AK11: =IF($B11=$AK$6,$AK$5,"") | AL11: =IF($B11=$AL$6,$AL$5,"") | AM11: =SUM(AE11:AL11) -> 0 | AN11: =O11-AM11 -> 212.04843
A12: 44566 | B12: 5 | C12: 5 | D12: 4 | E12: Wednesday | F12: 1 | G12: 1 | H12: January | I12: 1 | J12: 7.8061021 | K12: 38.12985 | L12: =J12*K12 -> 297.64551 | M12: 0.34623885 | N12: =L12*M12 -> 103.05644 | O12: =L12-N12 -> 194.58907 | P12: 32.519419 | Q12: 1.4195718 | R12: =IF(E12=$AF$6,$R$2/5,$R$2/11) -> 12.987013 | S12: 27.172086 | T12: =L12*0.7 -> 208.35185 | U12: =T12/J12 -> 26.690895 | V12: 24.852601 | W12: =P12/U12 -> 1.2183712 | X12: =J12/V12 -> 0.31409598 | Y12: =N12/T12 -> 0.49462693 | Z12: =J12/U12 -> 0.29246311 | AA12: =R12/L12 -> 0.043632485 | AB12: =T12/J12 -> 26.690895 | AC12: =Q12/K12 -> 0.037229934 | AD12: =P12/L12 -> 0.10925553 | AE12: =IF(B12=$AE$6,$AE$5, "") | AF12: =IF(E12=$AF$6,$AF$5,"") | AG12: =IF(B12=$AG$6,$AG$5,"") | AH12: =IF(B12=$AH$6,$AH$5,"") | AI12: =IF($B12=$AI$6,$AI$5,"") | AJ12: =IF($B12=$AJ$6,$AJ$5,"") | AK12: =IF($B12=$AK$6,$AK$5,"") | AL12: =IF($B12=$AL$6,$AL$5,"") -> 1000 | AM12: =SUM(AE12:AL12) -> 1000 | AN12: =O12-AM12 -> -805.41093
A13: 44567 | B13: 6 | C13: 6 | D13: 5 | E13: Thursday | F13: 1 | G13: 1 | H13: January | I13: 1 | J13: 9.2683237 | K13: 29.780468 | L13: =J13*K13 -> 276.01501 | M13: 0.40558507 | N13: =L13*M13 -> 111.94757 | O13: =L13-N13 -> 164.06745 | P13: 38.666184 | Q13: 8.9853593 | R13: =IF(E13=$AF$6,$R$2/5,$R$2/11) -> 12.987013 | S13: 34.524216 | T13: =L13*0.7 -> 193.21051 | U13: =T13/J13 -> 20.846327 | V13: 34.428736 | W13: =P13/U13 -> 1.85482 | X13: =J13/V13 -> 0.26920314 | Y13: =N13/T13 -> 0.57940724 | Z13: =J13/U13 -> 0.44460223 | AA13: =R13/L13 -> 0.047051835 | AB13: =T13/J13 -> 20.846327 | AC13: =Q13/K13 -> 0.30171989 | AD13: =P13/L13 -> 0.14008725 | AE13: =IF(B13=$AE$6,$AE$5, "") | AF13: =IF(E13=$AF$6,$AF$5,"") | AG13: =IF(B13=$AG$6,$AG$5,"") | AH13: =IF(B13=$AH$6,$AH$5,"") | AI13: =IF($B13=$AI$6,$AI$5,"") | AJ13: =IF($B13=$AJ$6,$AJ$5,"") | AK13: =IF($B13=$AK$6,$AK$5,"") | AL13: =IF($B13=$AL$6,$AL$5,"") | AM13: =SUM(AE13:AL13) -> 0 | AN13: =O13-AM13 -> 164.06745
A14: 44568 | B14: 7 | C14: 7 | D14: 6 | E14: Friday | F14: 1 | G14: 1 | H14: January | I14: 1 | J14: 5.7375578 | K14: 43.485501 | L14: =J14*K14 -> 249.50058 | M14: 0.39389748 | N14: =L14*M14 -> 98.277649 | O14: =L14-N14 -> 151.22293 | P14: 29.232184 | Q14: 7.0897059 | R14: =IF(E14=$AF$6,$R$2/5,$R$2/11) -> 12.987013 | S14: 31.126457 | T14: =L14*0.7 -> 174.6504 | U14: =T14/J14 -> 30.439851 | V14: 35.188495 | W14: =P14/U14 -> 0.96032612 | X14: =J14/V14 -> 0.16305209 | Y14: =N14/T14 -> 0.56271069 | Z14: =J14/U14 -> 0.18848837 | AA14: =R14/L14 -> 0.052052036 | AB14: =T14/J14 -> 30.439851 | AC14: =Q14/K14 -> 0.16303609 | AD14: =P14/L14 -> 0.11716279 | AE14: =IF(B14=$AE$6,$AE$5, "") | AF14: =IF(E14=$AF$6,$AF$5,"") | AG14: =IF(B14=$AG$6,$AG$5,"") | AH14: =IF(B14=$AH$6,$AH$5,"") | AI14: =IF($B14=$AI$6,$AI$5,"") | AJ14: =IF($B14=$AJ$6,$AJ$5,"") | AK14: =IF($B14=$AK$6,$AK$5,"") | AL14: =IF($B14=$AL$6,$AL$5,"") | AM14: =SUM(AE14:AL14) -> 0 | AN14: =O14-AM14 -> 151.22293
A15: 44569 | B15: 8 | C15: 8 | D15: 7 | E15: Saturday | F15: 1 | G15: 1 | H15: January | I15: 1 | J15: 9.6976877 | K15: 30.347755 | L15: =J15*K15 -> 294.30305 | M15: 0.33384866 | N15: =L15*M15 -> 98.252679 | O15: =L15-N15 -> 196.05037 | P15: 23.267168 | Q15: 2.1453246 | R15: =IF(E15=$AF$6,$R$2/5,$R$2/11) -> 12.987013 | S15: 30.204552 | T15: =L15*0.7 -> 206.01213 | U15: =T15/J15 -> 21.243428 | V15: 28.435653 | W15: =P15/U15 -> 1.0952643 | X15: =J15/V15 -> 0.34103973 | Y15: =N15/T15 -> 0.47692666 | Z15: =J15/U15 -> 0.45650295 | AA15: =R15/L15 -> 0.044128027 | AB15: =T15/J15 -> 21.243428 | AC15: =Q15/K15 -> 0.070691378 | AD15: =P15/L15 -> 0.079058535 | AE15: =IF(B15=$AE$6,$AE$5, "") | AF15: =IF(E15=$AF$6,$AF$5,"") | AG15: =IF(B15=$AG$6,$AG$5,"") | AH15: =IF(B15=$AH$6,$AH$5,"") | AI15: =IF($B15=$AI$6,$AI$5,"") | AJ15: =IF($B15=$AJ$6,$AJ$5,"") | AK15: =IF($B15=$AK$6,$AK$5,"") | AL15: =IF($B15=$AL$6,$AL$5,"") | AM15: =SUM(AE15:AL15) -> 0 | AN15: =O15-AM15 -> 196.05037
A16: 44570 | B16: 9 | C16: 9 | D16: 1 | E16: Sunday | F16: 2 | G16: 1 | H16: January | I16: 1 | J16: 5.5871449 | K16: 21.60263 | L16: =J16*K16 -> 120.69702 | M16: 0.27132475 | N16: =L16*M16 -> 32.748089 | O16: =L16-N16 -> 87.948933 | P16: 16.590911 | Q16: 3.6238352 | R16: =IF(E16=$AF$6,$R$2/5,$R$2/11) -> 28.571429 | S16: 14.680302 | T16: =L16*0.7 -> 84.487915 | U16: =T16/J16 -> 15.121841 | V16: 12.701462 | W16: =P16/U16 -> 1.0971489 | X16: =J16/V16 -> 0.43988203 | Y16: =N16/T16 -> 0.38760678 | Z16: =J16/U16 -> 0.36947519 | AA16: =R16/L16 -> 0.23672025 | AB16: =T16/J16 -> 15.121841 | AC16: =Q16/K16 -> 0.16774973 | AD16: =P16/L16 -> 0.13745916 | AE16: =IF(B16=$AE$6,$AE$5, "") | AF16: =IF(E16=$AF$6,$AF$5,"") -> 1000 | AG16: =IF(B16=$AG$6,$AG$5,"") | AH16: =IF(B16=$AH$6,$AH$5,"") | AI16: =IF($B16=$AI$6,$AI$5,"") | AJ16: =IF($B16=$AJ$6,$AJ$5,"") | AK16: =IF($B16=$AK$6,$AK$5,"") | AL16: =IF($B16=$AL$6,$AL$5,"") | AM16: =SUM(AE16:AL16) -> 1000 | AN16: =O16-AM16 -> -912.05107
A17: 44571 | B17: 10 | C17: 10 | D17: 2 | E17: Monday | F17: 2 | G17: 1 | H17: January | I17: 1 | J17: 8.7214496 | K17: 50.462988 | L17: =J17*K17 -> 440.11041 | M17: 0.29690507 | N17: =L17*M17 -> 130.67101 | O17: =L17-N17 -> 309.4394 | P17: 37.40443 | Q17: 7.6271942 | R17: =IF(E17=$AF$6,$R$2/5,$R$2/11) -> 12.987013 | S17: 25.73566 | T17: =L17*0.7 -> 308.07729 | U17: =T17/J17 -> 35.324092 | V17: 34.111474 | W17: =P17/U17 -> 1.0588929 | X17: =J17/V17 -> 0.25567496 | Y17: =N17/T17 -> 0.4241501 | Z17: =J17/U17 -> 0.24689806 | AA17: =R17/L17 -> 0.029508534 | AB17: =T17/J17 -> 35.324092 | AC17: =Q17/K17 -> 0.15114432 | AD17: =P17/L17 -> 0.084988743 | AE17: =IF(B17=$AE$6,$AE$5, "") | AF17: =IF(E17=$AF$6,$AF$5,"") | AG17: =IF(B17=$AG$6,$AG$5,"") | AH17: =IF(B17=$AH$6,$AH$5,"") -> 300 | AI17: =IF($B17=$AI$6,$AI$5,"") | AJ17: =IF($B17=$AJ$6,$AJ$5,"") | AK17: =IF($B17=$AK$6,$AK$5,"") | AL17: =IF($B17=$AL$6,$AL$5,"") | AM17: =SUM(AE17:AL17) -> 300 | AN17: =O17-AM17 -> 9.4393969
A18: 44572 | B18: 11 | C18: 11 | D18: 3 | E18: Tuesday | F18: 2 | G18: 1 | H18: January | I18: 1 | J18: 18.144643 | K18: 43.016572 | L18: =J18*K18 -> 780.52036 | M18: 0.52230161 | N18: =L18*M18 -> 407.66703 | O18: =L18-N18 -> 372.85332 | P18: 46.794366 | Q18: 9.3260607 | R18: =IF(E18=$AF$6,$R$2/5,$R$2/11) -> 12.987013 | S18: 31.99161 | T18: =L18*0.7 -> 546.36425 | U18: =T18/J18 -> 30.1116 | V18: 30.81582 | W18: =P18/U18 -> 1.5540312 | X18: =J18/V18 -> 0.58880936 | Y18: =N18/T18 -> 0.74614515 | Z18: =J18/U18 -> 0.60257984 | AA18: =R18/L18 -> 0.016638916 | AB18: =T18/J18 -> 30.1116 | AC18: =Q18/K18 -> 0.21680158 | AD18: =P18/L18 -> 0.059952782 | AE18: =IF(B18=$AE$6,$AE$5, "") | AF18: =IF(E18=$AF$6,$AF$5,"") | AG18: =IF(B18=$AG$6,$AG$5,"") | AH18: =IF(B18=$AH$6,$AH$5,"") | AI18: =IF($B18=$AI$6,$AI$5,"") | AJ18: =IF($B18=$AJ$6,$AJ$5,"") | AK18: =IF($B18=$AK$6,$AK$5,"") | AL18: =IF($B18=$AL$6,$AL$5,"") | AM18: =SUM(AE18:AL18) -> 0 | AN18: =O18-AM18 -> 372.85332
A19: 44573 | B19: 12 | C19: 12 | D19: 4 | E19: Wednesday | F19: 2 | G19: 1 | H19: January | I19: 1 | J19: 2.6356184 | K19: 23.051269 | L19: =J19*K19 -> 60.754349 | M19: 0.52234832 | N19: =L19*M19 -> 31.734932 | O19: =L19-N19 -> 29.019417 | P19: 29.957514 | Q19: 3.9756458 | R19: =IF(E19=$AF$6,$R$2/5,$R$2/11) -> 12.987013 | S19: 28.772989 | T19: =L19*0.7 -> 42.528045 | U19: =T19/J19 -> 16.135889 | V19: 27.099146 | W19: =P19/U19 -> 1.8565766 | X19: =J19/V19 -> 0.097258354 | Y19: =N19/T19 -> 0.74621188 | Z19: =J19/U19 -> 0.1633389 | AA19: =R19/L19 -> 0.21376269 | AB19: =T19/J19 -> 16.135889 | AC19: =Q19/K19 -> 0.17246971 | AD19: =P19/L19 -> 0.4930925 | AE19: =IF(B19=$AE$6,$AE$5, "") | AF19: =IF(E19=$AF$6,$AF$5,"") | AG19: =IF(B19=$AG$6,$AG$5,"") | AH19: =IF(B19=$AH$6,$AH$5,"") | AI19: =IF($B19=$AI$6,$AI$5,"") | AJ19: =IF($B19=$AJ$6,$AJ$5,"") -> 480 | AK19: =IF($B19=$AK$6,$AK$5,"") | AL19: =IF($B19=$AL$6,$AL$5,"") | AM19: =SUM(AE19:AL19) -> 480 | AN19: =O19-AM19 -> -450.98058
A20: 44574 | B20: 13 | C20: 13 | D20: 5 | E20: Thursday | F20: 2 | G20: 1 | H20: January | I20: 1 | J20: 13.689948 | K20: 52.886584 | L20: =J20*K20 -> 724.0146 | M20: 0.45813765 | N20: =L20*M20 -> 331.69835 | O20: =L20-N20 -> 392.31625 | P20: 30.053337 | Q20: 9.9404558 | R20: =IF(E20=$AF$6,$R$2/5,$R$2/11) -> 12.987013 | S20: 25.193107 | T20: =L20*0.7 -> 506.81022 | U20: =T20/J20 -> 37.020609 | V20: 26.834492 | W20: =P20/U20 -> 0.81180018 | X20: =J20/V20 -> 0.51016239 | Y20: =N20/T20 -> 0.65448236 | Z20: =J20/U20 -> 0.36979263 | AA20: =R20/L20 -> 0.017937501 | AB20: =T20/J20 -> 37.020609 | AC20: =Q20/K20 -> 0.18795799 | AD20: =P20/L20 -> 0.041509297 | AE20: =IF(B20=$AE$6,$AE$5, "") | AF20: =IF(E20=$AF$6,$AF$5,"") | AG20: =IF(B20=$AG$6,$AG$5,"") | AH20: =IF(B20=$AH$6,$AH$5,"") | AI20: =IF($B20=$AI$6,$AI$5,"") | AJ20: =IF($B20=$AJ$6,$AJ$5,"") | AK20: =IF($B20=$AK$6,$AK$5,"") | AL20: =IF($B20=$AL$6,$AL$5,"") | AM20: =SUM(AE20:AL20) -> 0 | AN20: =O20-AM20 -> 392.31625
... A360: 44914 | B360: 19 | C360: 353 | D360: 2 | E360: Monday | F360: 51 | G360: 12 | H360: December | I360: 4 | J360: 6.8184141 | K360: 28.518699 | L360: =J360*K360 -> 194.4523 | M360: 0.48413577 | N360: =L360*M360 -> 94.141316 | O360: =L360-N360 -> 100.31099 | P360: 35.067245 | Q360: 22.482861 | R360: =IF(E360=$AF$6,$R$2/5,$R$2/11) -> 12.987013 | S360: 46.152846 | T360: =L360*0.7 -> 136.11661 | U360: =T360/J360 -> 19.96309 | V360: 45.832731 | W360: =P360/U360 -> 1.7566041 | X360: =J360/V360 -> 0.14876735 | Y360: =N360/T360 -> 0.69162253 | Z360: =J360/U360 -> 0.34155104 | AA360: =R360/L360 -> 0.066787653 | AB360: =T360/J360 -> 19.96309 | AC360: =Q360/K360 -> 0.78835504 | AD360: =P360/L360 -> 0.18033854 | AE360: =IF(B360=$AE$6,$AE$5, "") | AF360: =IF(E360=$AF$6,$AF$5,"") | AG360: =IF(B360=$AG$6,$AG$5,"") | AH360: =IF(B360=$AH$6,$AH$5,"") | AI360: =IF($B360=$AI$6,$AI$5,"") | AJ360: =IF($B360=$AJ$6,$AJ$5,"") | AK360: =IF($B360=$AK$6,$AK$5,"") | AL360: =IF($B360=$AL$6,$AL$5,"") | AM360: =SUM(AE360:AL360) -> 0 | AN360: =O360-AM360 -> 100.31099
A361: 44915 | B361: 20 | C361: 354 | D361: 3 | E361: Tuesday | F361: 51 | G361: 12 | H361: December | I361: 4 | J361: 34.729872 | K361: 87.633024 | L361: 2700 | M361: 0.38146445 | N361: =L361*M361 -> 1029.954 | O361: =L361-N361 -> 1670.046 | P361: 61.378809 | Q361: 9.6321764 | R361: =IF(E361=$AF$6,$R$2/5,$R$2/11) -> 12.987013 | S361: 37.333048 | T361: =L361*0.7 -> 1890 | U361: =T361/J361 -> 54.420011 | V361: 52.870811 | W361: =P361/U361 -> 1.1278721 | X361: =J361/V361 -> 0.65688177 | Y361: =N361/T361 -> 0.54494921 | Z361: =J361/U361 -> 0.63818201 | AA361: =R361/L361 -> 0.0048100048 | AB361: =T361/J361 -> 54.420011 | AC361: =Q361/K361 -> 0.10991491 | AD361: =P361/L361 -> 0.022732892 | AE361: =IF(B361=$AE$6,$AE$5, "") | AF361: =IF(E361=$AF$6,$AF$5,"") | AG361: =IF(B361=$AG$6,$AG$5,"") | AH361: =IF(B361=$AH$6,$AH$5,"") | AI361: =IF($B361=$AI$6,$AI$5,"") -> 100 | AJ361: =IF($B361=$AJ$6,$AJ$5,"") | AK361: =IF($B361=$AK$6,$AK$5,"") | AL361: =IF($B361=$AL$6,$AL$5,"") | AM361: =SUM(AE361:AL361) -> 100 | AN361: =O361-AM361 -> 1570.046
A362: 44916 | B362: 21 | C362: 355 | D362: 4 | E362: Wednesday | F362: 51 | G362: 12 | H362: December | I362: 4 | J362: 10.265542 | K362: 95.818001 | L362: =J362*K362 -> 983.6237 | M362: 0.71915437 | N362: =L362*M362 -> 707.37729 | O362: =L362-N362 -> 276.24641 | P362: 30.361883 | Q362: 24.584828 | R362: =IF(E362=$AF$6,$R$2/5,$R$2/11) -> 12.987013 | S362: 41.685307 | T362: =L362*0.7 -> 688.53659 | U362: =T362/J362 -> 67.072601 | V362: 38.255351 | W362: =P362/U362 -> 0.45267192 | X362: =J362/V362 -> 0.26834264 | Y362: =N362/T362 -> 1.0273634 | Z362: =J362/U362 -> 0.1530512 | AA362: =R362/L362 -> 0.013203233 | AB362: =T362/J362 -> 67.072601 | AC362: =Q362/K362 -> 0.25657838 | AD362: =P362/L362 -> 0.030867376 | AE362: =IF(B362=$AE$6,$AE$5, "") | AF362: =IF(E362=$AF$6,$AF$5,"") | AG362: =IF(B362=$AG$6,$AG$5,"") | AH362: =IF(B362=$AH$6,$AH$5,"") | AI362: =IF($B362=$AI$6,$AI$5,"") | AJ362: =IF($B362=$AJ$6,$AJ$5,"") | AK362: =IF($B362=$AK$6,$AK$5,"") | AL362: =IF($B362=$AL$6,$AL$5,"") | AM362: =SUM(AE362:AL362) -> 0 | AN362: =O362-AM362 -> 276.24641
A363: 44917 | B363: 22 | C363: 356 | D363: 5 | E363: Thursday | F363: 51 | G363: 12 | H363: December | I363: 4 | J363: 20.317871 | K363: 8.5887738 | L363: =J363*K363 -> 174.5056 | M363: 0.34541969 | N363: =L363*M363 -> 60.27767 | O363: =L363-N363 -> 114.22793 | P363: 52.821631 | Q363: 18.605359 | R363: =IF(E363=$AF$6,$R$2/5,$R$2/11) -> 12.987013 | S363: 43.516424 | T363: =L363*0.7 -> 122.15392 | U363: =T363/J363 -> 6.0121417 | V363: 42.098056 | W363: =P363/U363 -> 8.7858261 | X363: =J363/V363 -> 0.48263205 | Y363: =N363/T363 -> 0.4934567 | Z363: =J363/U363 -> 3.3794731 | AA363: =R363/L363 -> 0.074421756 | AB363: =T363/J363 -> 6.0121417 | AC363: =Q363/K363 -> 2.1662416 | AD363: =P363/L363 -> 0.30269305 | AE363: =IF(B363=$AE$6,$AE$5, "") | AF363: =IF(E363=$AF$6,$AF$5,"") | AG363: =IF(B363=$AG$6,$AG$5,"") | AH363: =IF(B363=$AH$6,$AH$5,"") | AI363: =IF($B363=$AI$6,$AI$5,"") | AJ363: =IF($B363=$AJ$6,$AJ$5,"") | AK363: =IF($B363=$AK$6,$AK$5,"") | AL363: =IF($B363=$AL$6,$AL$5,"") | AM363: =SUM(AE363:AL363) -> 0 | AN363: =O363-AM363 -> 114.22793
A364: 44918 | B364: 23 | C364: 357 | D364: 6 | E364: Friday | F364: 51 | G364: 12 | H364: December | I364: 4 | J364: 27.072355 | K364: 53.693965 | L364: =J364*K364 -> 1453.6221 | M364: 0.62520535 | N364: =L364*M364 -> 908.81233 | O364: =L364-N364 -> 544.80979 | P364: 56.296011 | Q364: 21.532837 | R364: =IF(E364=$AF$6,$R$2/5,$R$2/11) -> 12.987013 | S364: 35.255251 | T364: =L364*0.7 -> 1017.5355 | U364: =T364/J364 -> 37.585776 | V364: 42.97565 | W364: =P364/U364 -> 1.497801 | X364: =J364/V364 -> 0.62994638 | Y364: =N364/T364 -> 0.8931505 | Z364: =J364/U364 -> 0.72028194 | AA364: =R364/L364 -> 0.0089342429 | AB364: =T364/J364 -> 37.585776 | AC364: =Q364/K364 -> 0.401029 | AD364: =P364/L364 -> 0.038728092 | AE364: =IF(B364=$AE$6,$AE$5, "") | AF364: =IF(E364=$AF$6,$AF$5,"") | AG364: =IF(B364=$AG$6,$AG$5,"") | AH364: =IF(B364=$AH$6,$AH$5,"") | AI364: =IF($B364=$AI$6,$AI$5,"") | AJ364: =IF($B364=$AJ$6,$AJ$5,"") | AK364: =IF($B364=$AK$6,$AK$5,"") | AL364: =IF($B364=$AL$6,$AL$5,"") | AM364: =SUM(AE364:AL364) -> 0 | AN364: =O364-AM364 -> 544.80979
A365: 44919 | B365: 24 | C365: 358 | D365: 7 | E365: Saturday | F365: 51 | G365: 12 | H365: December | I365: 4 | J365: 23.923233 | K365: 85.222041 | L365: =J365*K365 -> 2038.7867 | M365: 0.54986695 | N365: =L365*M365 -> 1121.0614 | O365: =L365-N365 -> 917.72529 | P365: 42.834192 | Q365: 26.151715 | R365: =IF(E365=$AF$6,$R$2/5,$R$2/11) -> 12.987013 | S365: 41.956361 | T365: =L365*0.7 -> 1427.1507 | U365: =T365/J365 -> 59.655428 | V365: 39.370492 | W365: =P365/U365 -> 0.71802672 | X365: =J365/V365 -> 0.60764373 | Y365: =N365/T365 -> 0.78552421 | Z365: =J365/U365 -> 0.40102357 | AA365: =R365/L365 -> 0.0063699714 | AB365: =T365/J365 -> 59.655428 | AC365: =Q365/K365 -> 0.30686562 | AD365: =P365/L365 -> 0.021009648 | AE365: =IF(B365=$AE$6,$AE$5, "") | AF365: =IF(E365=$AF$6,$AF$5,"") | AG365: =IF(B365=$AG$6,$AG$5,"") | AH365: =IF(B365=$AH$6,$AH$5,"") | AI365: =IF($B365=$AI$6,$AI$5,"") | AJ365: =IF($B365=$AJ$6,$AJ$5,"") | AK365: =IF($B365=$AK$6,$AK$5,"") | AL365: =IF($B365=$AL$6,$AL$5,"") | AM365: =SUM(AE365:AL365) -> 0 | AN365: =O365-AM365 -> 917.72529
A366: 44920 | B366: 25 | C366: 359 | D366: 1 | E366: Sunday | F366: 52 | G366: 12 | H366: December | I366: 4 | J366: 1.5888531 | K366: 12.699583 | L366: =J366*K366 -> 20.177772 | M366: 0.29650658 | N366: =L366*M366 -> 5.9828422 | O366: =L366-N366 -> 14.19493 | P366: 15.206224 | Q366: 3.7851211 | R366: =IF(E366=$AF$6,$R$2/5,$R$2/11) -> 28.571429 | S366: 16.194881 | T366: =L366*0.7 -> 14.124441 | U366: =T366/J366 -> 8.8897084 | V366: 15.691891 | W366: =P366/U366 -> 1.7105425 | X366: =J366/V366 -> 0.10125313 | Y366: =N366/T366 -> 0.42358082 | Z366: =J366/U366 -> 0.17872949 | AA366: =R366/L366 -> 1.4159853 | AB366: =T366/J366 -> 8.8897084 | AC366: =Q366/K366 -> 0.29805081 | AD366: =P366/L366 -> 0.75361263 | AE366: =IF(B366=$AE$6,$AE$5, "") | AF366: =IF(E366=$AF$6,$AF$5,"") -> 1000 | AG366: =IF(B366=$AG$6,$AG$5,"") | AH366: =IF(B366=$AH$6,$AH$5,"") | AI366: =IF($B366=$AI$6,$AI$5,"") | AJ366: =IF($B366=$AJ$6,$AJ$5,"") | AK366: =IF($B366=$AK$6,$AK$5,"") -> 83 | AL366: =IF($B366=$AL$6,$AL$5,"") | AM366: =SUM(AE366:AL366) -> 1083 | AN366: =O366-AM366 -> -1068.8051
A367: 44921 | B367: 26 | C367: 360 | D367: 2 | E367: Monday | F367: 52 | G367: 12 | H367: December | I367: 4 | J367: 4.6741504 | K367: 111.60408 | L367: =J367*K367 -> 521.65425 | M367: 0.48601576 | N367: =L367*M367 -> 253.53219 | O367: =L367-N367 -> 268.12206 | P367: 44.340542 | Q367: 14.151808 | R367: =IF(E367=$AF$6,$R$2/5,$R$2/11) -> 12.987013 | S367: 39.521039 | T367: =L367*0.7 -> 365.15798 | U367: =T367/J367 -> 78.122855 | V367: 29.957688 | W367: =P367/U367 -> 0.56757452 | X367: =J367/V367 -> 0.15602507 | Y367: =N367/T367 -> 0.69430823 | Z367: =J367/U367 -> 0.059830769 | AA367: =R367/L367 -> 0.024895825 | AB367: =T367/J367 -> 78.122855 | AC367: =Q367/K367 -> 0.12680368 | AD367: =P367/L367 -> 0.084999867 | AE367: =IF(B367=$AE$6,$AE$5, "") | AF367: =IF(E367=$AF$6,$AF$5,"") | AG367: =IF(B367=$AG$6,$AG$5,"") | AH367: =IF(B367=$AH$6,$AH$5,"") | AI367: =IF($B367=$AI$6,$AI$5,"") | AJ367: =IF($B367=$AJ$6,$AJ$5,"") | AK367: =IF($B367=$AK$6,$AK$5,"") | AL367: =IF($B367=$AL$6,$AL$5,"") | AM367: =SUM(AE367:AL367) -> 0 | AN367: =O367-AM367 -> 268.12206
A368: 44922 | B368: 27 | C368: 361 | D368: 3 | E368: Tuesday | F368: 52 | G368: 12 | H368: December | I368: 4 | J368: 12.657227 | K368: 79.692877 | L368: =J368*K368 -> 1008.6909 | M368: 0.75585499 | N368: =L368*M368 -> 762.42402 | O368: =L368-N368 -> 246.26684 | P368: 42.809633 | Q368: 21.087758 | R368: =IF(E368=$AF$6,$R$2/5,$R$2/11) -> 12.987013 | S368: 34.115318 | T368: =L368*0.7 -> 706.0836 | U368: =T368/J368 -> 55.785014 | V368: 36.796045 | W368: =P368/U368 -> 0.76740382 | X368: =J368/V368 -> 0.34398336 | Y368: =N368/T368 -> 1.0797928 | Z368: =J368/U368 -> 0.22689297 | AA368: =R368/L368 -> 0.012875117 | AB368: =T368/J368 -> 55.785014 | AC368: =Q368/K368 -> 0.26461283 | AD368: =P368/L368 -> 0.042440786 | AE368: =IF(B368=$AE$6,$AE$5, "") | AF368: =IF(E368=$AF$6,$AF$5,"") | AG368: =IF(B368=$AG$6,$AG$5,"") | AH368: =IF(B368=$AH$6,$AH$5,"") | AI368: =IF($B368=$AI$6,$AI$5,"") | AJ368: =IF($B368=$AJ$6,$AJ$5,"") | AK368: =IF($B368=$AK$6,$AK$5,"") | AL368: =IF($B368=$AL$6,$AL$5,"") | AM368: =SUM(AE368:AL368) -> 0 | AN368: =O368-AM368 -> 246.26684
A369: 44923 | B369: 28 | C369: 362 | D369: 4 | E369: Wednesday | F369: 52 | G369: 12 | H369: December | I369: 4 | J369: 17.054586 | K369: 45.871309 | L369: =J369*K369 -> 782.3162 | M369: 0.83468092 | N369: =L369*M369 -> 652.98441 | O369: =L369-N369 -> 129.33179 | P369: 32.750516 | Q369: 16.653138 | R369: =IF(E369=$AF$6,$R$2/5,$R$2/11) -> 12.987013 | S369: 35.290841 | T369: =L369*0.7 -> 547.62134 | U369: =T369/J369 -> 32.109916 | V369: 38.493287 | W369: =P369/U369 -> 1.0199502 | X369: =J369/V369 -> 0.44305352 | Y369: =N369/T369 -> 1.1924013 | Z369: =J369/U369 -> 0.53113144 | AA369: =R369/L369 -> 0.016600721 | AB369: =T369/J369 -> 32.109916 | AC369: =Q369/K369 -> 0.36304039 | AD369: =P369/L369 -> 0.041863528 | AE369: =IF(B369=$AE$6,$AE$5, "") | AF369: =IF(E369=$AF$6,$AF$5,"") | AG369: =IF(B369=$AG$6,$AG$5,"") | AH369: =IF(B369=$AH$6,$AH$5,"") | AI369: =IF($B369=$AI$6,$AI$5,"") | AJ369: =IF($B369=$AJ$6,$AJ$5,"") | AK369: =IF($B369=$AK$6,$AK$5,"") | AL369: =IF($B369=$AL$6,$AL$5,"") | AM369: =SUM(AE369:AL369) -> 0 | AN369: =O369-AM369 -> 129.33179
A370: 44924 | B370: 29 | C370: 363 | D370: 5 | E370: Thursday | F370: 52 | G370: 12 | H370: December | I370: 4 | J370: 20.391537 | K370: 56.738478 | L370: =J370*K370 -> 1156.9848 | M370: 0.5123357 | N370: =L370*M370 -> 592.7646 | O370: =L370-N370 -> 564.22016 | P370: 38.522717 | Q370: 17.296552 | R370: =IF(E370=$AF$6,$R$2/5,$R$2/11) -> 12.987013 | S370: 40.762155 | T370: =L370*0.7 -> 809.88933 | U370: =T370/J370 -> 39.716934 | V370: 36.646902 | W370: =P370/U370 -> 0.96993179 | X370: =J370/V370 -> 0.55643276 | Y370: =N370/T370 -> 0.73190815 | Z370: =J370/U370 -> 0.51342172 | AA370: =R370/L370 -> 0.011224878 | AB370: =T370/J370 -> 39.716934 | AC370: =Q370/K370 -> 0.30484696 | AD370: =P370/L370 -> 0.033295786 | AE370: =IF(B370=$AE$6,$AE$5, "") | AF370: =IF(E370=$AF$6,$AF$5,"") | AG370: =IF(B370=$AG$6,$AG$5,"") | AH370: =IF(B370=$AH$6,$AH$5,"") | AI370: =IF($B370=$AI$6,$AI$5,"") | AJ370: =IF($B370=$AJ$6,$AJ$5,"") | AK370: =IF($B370=$AK$6,$AK$5,"") | AL370: =IF($B370=$AL$6,$AL$5,"") | AM370: =SUM(AE370:AL370) -> 0 | AN370: =O370-AM370 -> 564.22016
A371: 44925 | B371: 30 | C371: 364 | D371: 6 | E371: Friday | F371: 52 | G371: 12 | H371: December | I371: 4 | J371: 21.387381 | K371: 33.597033 | L371: =J371*K371 -> 718.55254 | M371: 0.65940319 | N371: =L371*M371 -> 473.81584 | O371: =L371-N371 -> 244.7367 | P371: 47.393266 | Q371: 11.196263 | R371: =IF(E371=$AF$6,$R$2/5,$R$2/11) -> 12.987013 | S371: 48.075287 | T371: =L371*0.7 -> 502.98678 | U371: =T371/J371 -> 23.517923 | V371: 46.816452 | W371: =P371/U371 -> 2.0151977 | X371: =J371/V371 -> 0.45683472 | Y371: =N371/T371 -> 0.94200456 | Z371: =J371/U371 -> 0.9094077 | AA371: =R371/L371 -> 0.018073853 | AB371: =T371/J371 -> 23.517923 | AC371: =Q371/K371 -> 0.33325155 | AD371: =P371/L371 -> 0.065956577 | AE371: =IF(B371=$AE$6,$AE$5, "") | AF371: =IF(E371=$AF$6,$AF$5,"") | AG371: =IF(B371=$AG$6,$AG$5,"") | AH371: =IF(B371=$AH$6,$AH$5,"") | AI371: =IF($B371=$AI$6,$AI$5,"") | AJ371: =IF($B371=$AJ$6,$AJ$5,"") | AK371: =IF($B371=$AK$6,$AK$5,"") | AL371: =IF($B371=$AL$6,$AL$5,"") | AM371: =SUM(AE371:AL371) -> 0 | AN371: =O371-AM371 -> 244.7367
A372: 44926 | B372: 31 | C372: 365 | D372: 7 | E372: Saturday | F372: 52 | G372: 12 | H372: December | I372: 4 | J372: 6.403807 | K372: 55.163928 | L372: =J372*K372 -> 353.25915 | M372: 0.73075665 | N372: =L372*M372 -> 258.14647 | O372: =L372-N372 -> 95.112676 | P372: 43.641932 | Q372: 10.292481 | R372: =IF(E372=$AF$6,$R$2/5,$R$2/11) -> 12.987013 | S372: 40.949616 | T372: =L372*0.7 -> 247.2814 | U372: =T372/J372 -> 38.61475 | V372: 38.734059 | W372: =P372/U372 -> 1.1301881 | X372: =J372/V372 -> 0.16532755 | Y372: =N372/T372 -> 1.0439381 | Z372: =J372/U372 -> 0.16583837 | AA372: =R372/L372 -> 0.036763416 | AB372: =T372/J372 -> 38.61475 | AC372: =Q372/K372 -> 0.18657992 | AD372: =P372/L372 -> 0.12354084 | AE372: =IF(B372=$AE$6,$AE$5, "") | AF372: =IF(E372=$AF$6,$AF$5,"") | AG372: =IF(B372=$AG$6,$AG$5,"") | AH372: =IF(B372=$AH$6,$AH$5,"") | AI372: =IF($B372=$AI$6,$AI$5,"") | AJ372: =IF($B372=$AJ$6,$AJ$5,"") | AK372: =IF($B372=$AK$6,$AK$5,"") | AL372: =IF($B372=$AL$6,$AL$5,"") | AM372: =SUM(AE372:AL372) -> 0 | AN372: =O372-AM372 -> 95.112676
A373: 44927 | B373: 1 | C373: 366 | D373: 1 | E373: Sunday | F373: 52 | G373: 1 | H373: January | I373: 4 | J373: 13.608697 | K373: 28.088597 | L373: =J373*K373 -> 382.24921 | M373: 0.17156509 | N373: =L373*M373 -> 65.58062 | O373: =L373-N373 -> 316.66859 | P373: 28.984362 | Q373: 5.6991993 | R373: =IF(E373=$AF$6,$R$2/5,$R$2/11) -> 28.571429 | S373: 15.912487 | T373: =L373*0.7 -> 267.57445 | U373: =T373/J373 -> 19.662018 | V373: 19.553897 | W373: =P373/U373 -> 1.4741296 | X373: =J373/V373 -> 0.69595831 | Y373: =N373/T373 -> 0.24509299 | Z373: =J373/U373 -> 0.69213126 | AA373: =R373/L373 -> 0.074745553 | AB373: =T373/J373 -> 19.662018 | AC373: =Q373/K373 -> 0.20290082 | AD373: =P373/L373 -> 0.075825825 | AE373: =IF(B373=$AE$6,$AE$5, "") -> 3000 | AF373: =IF(E373=$AF$6,$AF$5,"") -> 1000 | AG373: =IF(B373=$AG$6,$AG$5,"") | AH373: =IF(B373=$AH$6,$AH$5,"") | AI373: =IF($B373=$AI$6,$AI$5,"") | AJ373: =IF($B373=$AJ$6,$AJ$5,"") | AK373: =IF($B373=$AK$6,$AK$5,"") | AL373: =IF($B373=$AL$6,$AL$5,"") | AM373: =SUM(AE373:AL373) -> 4000 | AN373: =O373-AM373 -> -3683.3314

Sheet flatfeet
A1: Date | B1: Dayo Month | C1: Dayo Year | D1: Dayo Week # | E1: Dayo Week Name | F1: Weeko Year | G1: Month # | H1: Month Name | I1: Quarter | J1: Foot Traffic (customers per day) | K1: Spend per Customer | L1: Total Revenue | M1: Daily COGS | N1: COGS | O1: Gross Margin | P1: Online delevery | Q1: Conversion Rate | R1: Avg Delevry cost % | S1: Delevery percentage | T1: percent of wage per hr | U1: Average Delevery value per Order | V1: Dollar wasted oer stem discarded | W1: online order % | X1: Online order # | Y1: Delevery orders | Z1: In store | AA1: Rent / Lease | AB1: Wages and Salaries | AC1: Insurance | AD1: Electric | AE1: Water | AF1: Phone | AG1: Internet | AH1: Delivery | AI1: Total Expenses | AJ1: Profit | AK1: Order Method | AL1: Order amount
A2: 44562 | B2: 1 | C2: 1 | D2: 7 | E2: Saturday | F2: 1 | G2: 1 | H2: January | I2: 1 | J2: 18 | K2: 63 | L2: 1153 | M2: 0.39 | N2: 448 | O2: 705 | P2: 0.99 | Q2: 0.69 | R2: 0.56 | S2: 0.41 | T2: 0.01 | U2: 44 | V2: 0.11 | W2: 0.04 | X2: =L2*W2 -> 46.12 | Y2: =S2*L2 -> 472.73 | Z2: =L2-(X2+Y2) -> 634.15 | AA2: 3000 | AI2: 3000 | AJ2: -2295 | AK2: In Store
A3: 44563 | B3: 2 | C3: 2 | D3: 1 | E3: Sunday | F3: 1 | G3: 1 | H3: January | I3: 1 | J3: 6 | K3: 37 | L3: 209 | M3: 0.21 | N3: 44 | O3: 165 | P3: 0.6 | Q3: 0.41 | R3: 0.3 | S3: 0.22 | T3: 0.14 | U3: 26 | V3: 0.19 | W3: 0.07 | X3: =L3*W3 -> 14.63 | Y3: =S3*L3 -> 45.98 | Z3: =L3-(X3+Y3) -> 148.39 | AB3: 1000 | AI3: 1000 | AJ3: -835 | AK3: Delevry
A4: 44564 | B4: 3 | C4: 3 | D4: 2 | E4: Monday | F4: 1 | G4: 1 | H4: January | I4: 1 | J4: 11 | K4: 9 | L4: 98 | M4: 0.51 | N4: 50 | O4: 48 | P4: 5.92 | Q4: 0.43 | R4: 0.73 | S4: 1.75 | T4: 0.13 | U4: 6 | V4: 0.86 | W4: 0.38 | X4: =L4*W4 -> 37.24 | Y4: =S4*L4 -> 171.5 | Z4: =L4-(X4+Y4) -> -110.74 | AI4: 0 | AJ4: 48 | AK4: Online
A5: 44565 | B5: 4 | C5: 4 | D5: 3 | E5: Tuesday | F5: 1 | G5: 1 | H5: January | I5: 1 | J5: 12 | K5: 27 | L5: 332 | M5: 0.36 | N5: 120 | O5: 212 | P5: 1.38 | Q5: 0.34 | R5: 0.52 | S5: 0.64 | T5: 0.04 | U5: 19 | V5: 0.22 | W5: 0.08 | X5: =L5*W5 -> 26.56 | Y5: =S5*L5 -> 212.48 | Z5: =L5-(X5+Y5) -> 92.96 | AI5: 0 | AJ5: 212
A6: 44566 | B6: 5 | C6: 5 | D6: 4 | E6: Wednesday | F6: 1 | G6: 1 | H6: January | I6: 1 | J6: 8 | K6: 38 | L6: 298 | M6: 0.35 | N6: 103 | O6: 195 | P6: 1.22 | Q6: 0.31 | R6: 0.49 | S6: 0.29 | T6: 0.04 | U6: 27 | V6: 0.04 | W6: 0.11 | X6: =L6*W6 -> 32.78 | Y6: =S6*L6 -> 86.42 | Z6: =L6-(X6+Y6) -> 178.8 | AH6: 1000 | AI6: 1000 | AJ6: -805
A7: 44567 | B7: 6 | C7: 6 | D7: 5 | E7: Thursday | F7: 1 | G7: 1 | H7: January | I7: 1 | J7: 9 | K7: 30 | L7: 276 | M7: 0.41 | N7: 112 | O7: 164 | P7: 1.85 | Q7: 0.27 | R7: 0.58 | S7: 0.44 | T7: 0.05 | U7: 21 | V7: 0.3 | W7: 0.14 | X7: =L7*W7 -> 38.64 | Y7: =S7*L7 -> 121.44 | Z7: =L7-(X7+Y7) -> 115.92 | AI7: 0 | AJ7: 164
A8: 44568 | B8: 7 | C8: 7 | D8: 6 | E8: Friday | F8: 1 | G8: 1 | H8: January | I8: 1 | J8: 6 | K8: 43 | L8: 250 | M8: 0.39 | N8: 98 | O8: 151 | P8: 0.96 | Q8: 0.16 | R8: 0.56 | S8: 0.19 | T8: 0.05 | U8: 30 | V8: 0.16 | W8: 0.12 | X8: =L8*W8 -> 30 | Y8: =S8*L8 -> 47.5 | Z8: =L8-(X8+Y8) -> 172.5 | AI8: 0 | AJ8: 151
A9: 44569 | B9: 8 | C9: 8 | D9: 7 | E9: Saturday | F9: 1 | G9: 1 | H9: January | I9: 1 | J9: 10 | K9: 30 | L9: 294 | M9: 0.33 | N9: 98 | O9: 196 | P9: 1.1 | Q9: 0.34 | R9: 0.48 | S9: 0.46 | T9: 0.04 | U9: 21 | V9: 0.07 | W9: 0.08 | X9: =L9*W9 -> 23.52 | Y9: =S9*L9 -> 135.24 | Z9: =L9-(X9+Y9) -> 135.24 | AI9: 0 | AJ9: 196
A10: 44570 | B10: 9 | C10: 9 | D10: 1 | E10: Sunday | F10: 2 | G10: 1 | H10: January | I10: 1 | J10: 6 | K10: 22 | L10: 121 | M10: 0.27 | N10: 33 | O10: 88 | P10: 1.1 | Q10: 0.44 | R10: 0.39 | S10: 0.37 | T10: 0.24 | U10: 15 | V10: 0.17 | W10: 0.14 | X10: =L10*W10 -> 16.94 | Y10: =S10*L10 -> 44.77 | Z10: =L10-(X10+Y10) -> 59.29 | AB10: 1000 | AI10: 1000 | AJ10: -912
A11: 44571 | B11: 10 | C11: 10 | D11: 2 | E11: Monday | F11: 2 | G11: 1 | H11: January | I11: 1 | J11: 9 | K11: 50 | L11: 440 | M11: 0.3 | N11: 131 | O11: 309 | P11: 1.06 | Q11: 0.26 | R11: 0.42 | S11: 0.25 | T11: 0.03 | U11: 35 | V11: 0.15 | W11: 0.08 | X11: =L11*W11 -> 35.2 | Y11: =S11*L11 -> 110 | Z11: =L11-(X11+Y11) -> 294.8 | AD11: 300 | AI11: 300 | AJ11: 9
A12: 44572 | B12: 11 | C12: 11 | D12: 3 | E12: Tuesday | F12: 2 | G12: 1 | H12: January | I12: 1 | J12: 18 | K12: 43 | L12: 781 | M12: 0.52 | N12: 408 | O12: 373 | P12: 1.55 | Q12: 0.59 | R12: 0.75 | S12: 0.6 | T12: 0.02 | U12: 30 | V12: 0.22 | W12: 0.06 | X12: =L12*W12 -> 46.86 | Y12: =S12*L12 -> 468.6 | Z12: =L12-(X12+Y12) -> 265.54 | AI12: 0 | AJ12: 373
A13: 44573 | B13: 12 | C13: 12 | D13: 4 | E13: Wednesday | F13: 2 | G13: 1 | H13: January | I13: 1 | J13: 3 | K13: 23 | L13: 61 | M13: 0.52 | N13: 32 | O13: 29 | P13: 1.86 | Q13: 0.1 | R13: 0.75 | S13: 0.16 | T13: 0.21 | U13: 16 | V13: 0.17 | W13: 0.49 | X13: =L13*W13 -> 29.89 | Y13: =S13*L13 -> 9.76 | Z13: =L13-(X13+Y13) -> 21.35 | AF13: 480 | AI13: 480 | AJ13: -451
A14: 44574 | B14: 13 | C14: 13 | D14: 5 | E14: Thursday | F14: 2 | G14: 1 | H14: January | I14: 1 | J14: 14 | K14: 53 | L14: 724 | M14: 0.46 | N14: 332 | O14: 392 | P14: 0.81 | Q14: 0.51 | R14: 0.65 | S14: 0.37 | T14: 0.02 | U14: 37 | V14: 0.19 | W14: 0.04 | X14: =L14*W14 -> 28.96 | Y14: =S14*L14 -> 267.88 | Z14: =L14-(X14+Y14) -> 427.16 | AI14: 0 | AJ14: 392
A15: 44575 | B15: 14 | C15: 14 | D15: 6 | E15: Friday | F15: 2 | G15: 1 | H15: January | I15: 1 | J15: 11 | K15: 38 | L15: 427 | M15: 0.52 | N15: 221 | O15: 206 | P15: 1.75 | Q15: 0.43 | R15: 0.74 | S15: 0.42 | T15: 0.03 | U15: 27 | V15: 0.36 | W15: 0.11 | X15: =L15*W15 -> 46.97 | Y15: =S15*L15 -> 179.34 | Z15: =L15-(X15+Y15) -> 200.69 | AI15: 0 | AJ15: 206
A16: 44576 | B16: 15 | C16: 15 | D16: 7 | E16: Saturday | F16: 2 | G16: 1 | H16: January | I16: 1 | J16: 13 | K16: 50 | L16: 643 | M16: 0.32 | N16: 204 | O16: 439 | P16: 0.92 | Q16: 0.58 | R16: 0.45 | S16: 0.36 | T16: 0.02 | U16: 35 | V16: 0.25 | W16: 0.05 | X16: =L16*W16 -> 32.15 | Y16: =S16*L16 -> 231.48 | Z16: =L16-(X16+Y16) -> 379.37 | AC16: 300 | AI16: 300 | AJ16: 139
A17: 44577 | B17: 16 | C17: 16 | D17: 1 | E17: Sunday | F17: 3 | G17: 1 | H17: January | I17: 1 | J17: 4 | K17: 7 | L17: 28 | M17: 0.12 | N17: 3 | O17: 24 | P17: 4.54 | Q17: 0.23 | R17: 0.18 | S17: 0.9 | T17: 1.03 | U17: 5 | V17: 0.46 | W17: 0.76 | X17: =L17*W17 -> 21.28 | Y17: =S17*L17 -> 25.2 | Z17: =L17-(X17+Y17) -> -18.48 | AB17: 1000 | AI17: 1000 | AJ17: -976
A18: 44578 | B18: 17 | C18: 17 | D18: 2 | E18: Monday | F18: 3 | G18: 1 | H18: January | I18: 1 | J18: 9 | K18: 19 | L18: 170 | M18: 0.36 | N18: 62 | O18: 108 | P18: 3.02 | Q18: 0.25 | R18: 0.52 | S18: 0.67 | T18: 0.08 | U18: 13 | V18: 0.35 | W18: 0.24 | X18: =L18*W18 -> 40.8 | Y18: =S18*L18 -> 113.9 | Z18: =L18-(X18+Y18) -> 15.3 | AI18: 0 | AJ18: 108
A19: 44579 | B19: 18 | C19: 18 | D19: 3 | E19: Tuesday | F19: 3 | G19: 1 | H19: January | I19: 1 | J19: 11 | K19: 41 | L19: 452 | M19: 0.37 | N19: 169 | O19: 284 | P19: 0.38 | Q19: 0.36 | R19: 0.53 | S19: 0.38 | T19: 0.03 | U19: 29 | V19: 0.2 | W19: 0.02 | X19: =L19*W19 -> 9.04 | Y19: =S19*L19 -> 171.76 | Z19: =L19-(X19+Y19) -> 271.2 | AI19: 0 | AJ19: 284
A20: 44580 | B20: 19 | C20: 19 | D20: 4 | E20: Wednesday | F20: 3 | G20: 1 | H20: January | I20: 1 | J20: 8 | K20: 28 | L20: 232 | M20: 0.27 | N20: 62 | O20: 170 | P20: 2.12 | Q20: 0.31 | R20: 0.38 | S20: 0.42 | T20: 0.06 | U20: 20 | V20: 0.23 | W20: 0.18 | X20: =L20*W20 -> 41.76 | Y20: =S20*L20 -> 97.44 | Z20: =L20-(X20+Y20) -> 92.8 | AI20: 0 | AJ20: 170
A21: 44581 | B21: 20 | C21: 20 | D21: 5 | E21: Thursday | F21: 3 | G21: 1 | H21: January | I21: 1 | J21: 15 | K21: 56 | L21: 822 | M21: 0.32 | N21: 266 | O21: 556 | P21: 1.15 | Q21: 0.51 | R21: 0.46 | S21: 0.37 | T21: 0.02 | U21: 39 | V21: 0.15 | W21: 0.06 | X21: =L21*W21 -> 49.32 | Y21: =S21*L21 -> 304.14 | Z21: =L21-(X21+Y21) -> 468.54 | AE21: 100 | AI21: 100 | AJ21: 456
A22: 44582 | B22: 21 | C22: 21 | D22: 6 | E22: Friday | F22: 3 | G22: 1 | H22: January | I22: 1 | J22: 16 | K22: 72 | L22: 1169 | M22: 0.31 | N22: 362 | O22: 807 | P22: 0.36 | Q22: 0.62 | R22: 0.44 | S22: 0.33 | T22: 0.01 | U22: 50 | V22: 0.1 | W22: 0.02 | X22: =L22*W22 -> 23.38 | Y22: =S22*L22 -> 385.77 | Z22: =L22-(X22+Y22) -> 759.85 | AI22: 0 | AJ22: 807
A23: 44583 | B23: 22 | C23: 22 | D23: 7 | E23: Saturday | F23: 3 | G23: 1 | H23: January | I23: 1 | J23: 14 | K23: 50 | L23: 697 | M23: 0.51 | N23: 356 | O23: 340 | P23: 0.97 | Q23: 0.54 | R23: 0.73 | S23: 0.4 | T23: 0.02 | U23: 35 | V23: 0.2 | W23: 0.05 | X23: =L23*W23 -> 34.85 | Y23: =S23*L23 -> 278.8 | Z23: =L23-(X23+Y23) -> 383.35 | AI23: 0 | AJ23: 340
A24: 44584 | B24: 23 | C24: 23 | D24: 1 | E24: Sunday | F24: 4 | G24: 1 | H24: January | I24: 1 | J24: 8 | K24: 29 | L24: 229 | M24: 0.19 | N24: 45 | O24: 185 | P24: 1.51 | Q24: 0.41 | R24: 0.28 | S24: 0.39 | T24: 0.12 | U24: 20 | V24: 0.1 | W24: 0.13 | X24: =L24*W24 -> 29.77 | Y24: =S24*L24 -> 89.31 | Z24: =L24-(X24+Y24) -> 109.92 | AB24: 1000 | AI24: 1000 | AJ24: -815
A25: 44585 | B25: 24 | C25: 24 | D25: 2 | E25: Monday | F25: 4 | G25: 1 | H25: January | I25: 1 | J25: 11 | K25: 49 | L25: 555 | M25: 0.3 | N25: 166 | O25: 389 | P25: 2.13 | Q25: 0.19 | R25: 0.43 | S25: 0.33 | T25: 0.02 | U25: 34 | V25: 0.29 | W25: 0.13 | X25: =L25*W25 -> 72.15 | Y25: =S25*L25 -> 183.15 | Z25: =L25-(X25+Y25) -> 299.7 | AI25: 0 | AJ25: 389
A26: 44586 | B26: 25 | C26: 25 | D26: 3 | E26: Tuesday | F26: 4 | G26: 1 | H26: January | I26: 1 | J26: 13 | K26: 118 | L26: 1563 | M26: 0.15 | N26: 239 | O26: 1324 | P26: 0.54 | Q26: 0.3 | R26: 0.22 | S26: 0.16 | T26: 0.01 | U26: 82 | V26: 0.08 | W26: 0.03 | X26: =L26*W26 -> 46.89 | Y26: =S26*L26 -> 250.08 | Z26: =L26-(X26+Y26) -> 1266.03 | AG26: 83 | AI26: 83 | AJ26: 1241
A27: 44587 | B27: 26 | C27: 26 | D27: 4 | E27: Wednesday | F27: 4 | G27: 1 | H27: January | I27: 1 | J27: 16 | K27: 70 | L27: 1091 | M27: 0.55 | N27: 598 | O27: 493 | P27: 1.03 | Q27: 0.35 | R27: 0.78 | S27: 0.32 | T27: 0.01 | U27: 49 | V27: 0.21 | W27: 0.05 | X27: =L27*W27 -> 54.55 | Y27: =S27*L27 -> 349.12 | Z27: =L27-(X27+Y27) -> 687.33 | AI27: 0 | AJ27: 493
A28: 44588 | B28: 27 | C28: 27 | D28: 5 | E28: Thursday | F28: 4 | G28: 1 | H28: January | I28: 1 | J28: 8 | K28: 50 | L28: 411 | M28: 0.65 | N28: 268 | O28: 143 | P28: 1.09 | Q28: 0.15 | R28: 0.93 | S28: 0.24 | T28: 0.03 | U28: 35 | V28: 0.31 | W28: 0.09 | X28: =L28*W28 -> 36.99 | Y28: =S28*L28 -> 98.64 | Z28: =L28-(X28+Y28) -> 275.37 | AI28: 0 | AJ28: 143
A29: 44589 | B29: 28 | C29: 28 | D29: 6 | E29: Friday | F29: 4 | G29: 1 | H29: January | I29: 1 | J29: 17 | K29: 51 | L29: 841 | M29: 0.48 | N29: 407 | O29: 434 | P29: 1.96 | Q29: 0.32 | R29: 0.69 | S29: 0.46 | T29: 0.02 | U29: 36 | V29: 0.31 | W29: 0.08 | X29: =L29*W29 -> 67.28 | Y29: =S29*L29 -> 386.86 | Z29: =L29-(X29+Y29) -> 386.86 | AI29: 0 | AJ29: 434
A30: 44590 | B30: 29 | C30: 29 | D30: 7 | E30: Saturday | F30: 4 | G30: 1 | H30: January | I30: 1 | J30: 11 | K30: 94 | L30: 1034 | M30: 0.25 | N30: 258 | O30: 776 | P30: 0.74 | Q30: 0.19 | R30: 0.36 | S30: 0.17 | T30: 0.01 | U30: 66 | V30: 0.16 | W30: 0.05 | X30: =L30*W30 -> 51.7 | Y30: =S30*L30 -> 175.78 | Z30: =L30-(X30+Y30) -> 806.52 | AI30: 0 | AJ30: 776
A31: 44591 | B31: 30 | C31: 30 | D31: 1 | E31: Sunday | F31: 5 | G31: 1 | H31: January | I31: 1 | J31: 7 | K31: 25 | L31: 184 | M31: 0.23 | N31: 43 | O31: 141 | P31: 2.07 | Q31: 0.25 | R31: 0.33 | S31: 0.42 | T31: 0.15 | U31: 18 | V31: 0.15 | W31: 0.2 | X31: =L31*W31 -> 36.8 | Y31: =S31*L31 -> 77.28 | Z31: =L31-(X31+Y31) -> 69.92 | AB31: 1000 | AI31: 1000 | AJ31: -859
A32: 44592 | B32: 31 | C32: 31 | D32: 2 | E32: Monday | F32: 5 | G32: 1 | H32: January | I32: 1 | J32: 9 | K32: 32 | L32: 282 | M32: 0.52 | N32: 147 | O32: 135 | P32: 3.18 | Q32: 0.13 | R32: 0.75 | S32: 0.39 | T32: 0.05 | U32: 23 | V32: 0.24 | W32: 0.25 | X32: =L32*W32 -> 70.5 | Y32: =S32*L32 -> 109.98 | Z32: =L32-(X32+Y32) -> 101.52 | AI32: 0 | AJ32: 135
A33: 44593 | B33: 1 | C33: 32 | D33: 3 | E33: Tuesday | F33: 5 | G33: 2 | H33: February | I33: 1 | J33: 15 | K33: 51 | L33: 740 | M33: 0.44 | N33: 328 | O33: 412 | P33: 1.74 | Q33: 0.24 | R33: 0.63 | S33: 0.41 | T33: 0.02 | U33: 36 | V33: 0.27 | W33: 0.08 | X33: =L33*W33 -> 59.2 | Y33: =S33*L33 -> 303.4 | Z33: =L33-(X33+Y33) -> 377.4 | AA33: 3000 | AI33: 3000 | AJ33: -2588
A34: 44594 | B34: 2 | C34: 33 | D34: 4 | E34: Wednesday | F34: 5 | G34: 2 | H34: February | I34: 1 | J34: 28 | K34: 61 | L34: 1684 | M34: 0.54 | N34: 908 | O34: 776 | P34: 1.69 | Q34: 0.55 | R34: 0.77 | S34: 0.65 | T34: 0.01 | U34: 43 | V34: 0.46 | W34: 0.04 | X34: =L34*W34 -> 67.36 | Y34: =S34*L34 -> 1094.6 | Z34: =L34-(X34+Y34) -> 522.04 | AI34: 0 | AJ34: 776
A35: 44595 | B35: 3 | C35: 34 | D35: 5 | E35: Thursday | F35: 5 | G35: 2 | H35: February | I35: 1 | J35: 12 | K35: 32 | L35: 387 | M35: 0.38 | N35: 147 | O35: 240 | P35: 3.85 | Q35: 0.31 | R35: 0.54 | S35: 0.55 | T35: 0.03 | U35: 22 | V35: 0.37 | W35: 0.22 | X35: =L35*W35 -> 85.14 | Y35: =S35*L35 -> 212.85 | Z35: =L35-(X35+Y35) -> 89.01 | AI35: 0 | AJ35: 240
A36: 44596 | B36: 4 | C36: 35 | D36: 6 | E36: Friday | F36: 5 | G36: 2 | H36: February | I36: 1 | J36: 11 | K36: 75 | L36: 824 | M36: 0.34 | N36: 283 | O36: 541 | P36: 1.3 | Q36: 0.18 | R36: 0.49 | S36: 0.21 | T36: 0.02 | U36: 52 | V36: 0.21 | W36: 0.08 | X36: =L36*W36 -> 65.92 | Y36: =S36*L36 -> 173.04 | Z36: =L36-(X36+Y36) -> 585.04 | AI36: 0 | AJ36: 541
A37: 44597 | B37: 5 | C37: 36 | D37: 7 | E37: Saturday | F37: 5 | G37: 2 | H37: February | I37: 1 | J37: 5 | K37: 30 | L37: 143 | M37: 0.32 | N37: 46 | O37: 97 | P37: 3.85 | Q37: 0.08 | R37: 0.46 | S37: 0.23 | T37: 0.09 | U37: 21 | V37: 0.74 | W37: 0.56 | X37: =L37*W37 -> 80.08 | Y37: =S37*L37 -> 32.89 | Z37: =L37-(X37+Y37) -> 30.03 | AH37: 1000 | AI37: 1000 | AJ37: -903
A38: 44598 | B38: 6 | C38: 37 | D38: 1 | E38: Sunday | F38: 6 | G38: 2 | H38: February | I38: 1 | J38: 13 | K38: 41 | L38: 536 | M38: 0.26 | N38: 139 | O38: 398 | P38: 0.74 | Q38: 0.64 | R38: 0.37 | S38: 0.46 | T38: 0.05 | U38: 28 | V38: 0.04 | W38: 0.04 | X38: =L38*W38 -> 21.44 | Y38: =S38*L38 -> 246.56 | Z38: =L38-(X38+Y38) -> 268 | AB38: 1000 | AI38: 1000 | AJ38: -602
A39: 44599 | B39: 7 | C39: 38 | D39: 2 | E39: Monday | F39: 6 | G39: 2 | H39: February | I39: 1 | J39: 11 | K39: 56 | L39: 616 | M39: 0.82 | N39: 503 | O39: 113 | P39: 1.09 | Q39: 0.16 | R39: 1.17 | S39: 0.28 | T39: 0.02 | U39: 39 | V39: 0.09 | W39: 0.07 | X39: =L39*W39 -> 43.12 | Y39: =S39*L39 -> 172.48 | Z39: =L39-(X39+Y39) -> 400.4 | AI39: 0 | AJ39: 113
A40: 44600 | B40: 8 | C40: 39 | D40: 3 | E40: Tuesday | F40: 6 | G40: 2 | H40: February | I40: 1 | J40: 12 | K40: 143 | L40: 1721 | M40: 0.63 | N40: 1092 | O40: 629 | P40: 0.83 | Q40: 0.18 | R40: 0.91 | S40: 0.12 | T40: 0.01 | U40: 100 | V40: 0.08 | W40: 0.05 | X40: =L40*W40 -> 86.05 | Y40: =S40*L40 -> 206.52 | Z40: =L40-(X40+Y40) -> 1428.43 | AI40: 0 | AJ40: 629
A41: 44601 | B41: 9 | C41: 40 | D41: 4 | E41: Wednesday | F41: 6 | G41: 2 | H41: February | I41: 1 | J41: 24 | K41: 87 | L41: 2081 | M41: 1.12 | N41: 2323 | O41: -242 | P41: 1.38 | Q41: 0.36 | R41: 1.59 | S41: 0.39 | T41: 0.01 | U41: 61 | V41: 0.17 | W41: 0.04 | X41: =L41*W41 -> 83.24 | Y41: =S41*L41 -> 811.59 | Z41: =L41-(X41+Y41) -> 1186.17 | AI41: 0 | AJ41: -242
A42: 44602 | B42: 10 | C42: 41 | D42: 5 | E42: Thursday | F42: 6 | G42: 2 | H42: February | I42: 1 | J42: 27 | K42: 72 | L42: 1930 | M42: 0.53 | N42: 1031 | O42: 899 | P42: 1.76 | Q42: 0.44 | R42: 0.76 | S42: 0.54 | T42: 0.01 | U42: 50 | V42: 0.13 | W42: 0.05 | X42: =L42*W42 -> 96.5 | Y42: =S42*L42 -> 1042.2 | Z42: =L42-(X42+Y42) -> 791.3 | AD42: 300 | AI42: 300 | AJ42: 599
A43: 44603 | B43: 11 | C43: 42 | D43: 6 | E43: Friday | F43: 6 | G43: 2 | H43: February | I43: 1 | J43: 25 | K43: 82 | L43: 2093 | M43: 0.86 | N43: 1806 | O43: 287 | P43: 0.94 | Q43: 0.43 | R43: 1.23 | S43: 0.44 | T43: 0.01 | U43: 58 | V43: 0.12 | W43: 0.03 | X43: =L43*W43 -> 62.79 | Y43: =S43*L43 -> 920.92 | Z43: =L43-(X43+Y43) -> 1109.29 | AI43: 0 | AJ43: 287
A44: 44604 | B44: 12 | C44: 43 | D44: 7 | E44: Saturday | F44: 6 | G44: 2 | H44: February | I44: 1 | J44: 16 | K44: 111 | L44: 1738 | M44: 0.76 | N44: 1324 | O44: 414 | P44: 1.03 | Q44: 0.21 | R44: 1.09 | S44: 0.2 | T44: 0.01 | U44: 78 | V44: 0.18 | W44: 0.05 | X44: =L44*W44 -> 86.9 | Y44: =S44*L44 -> 347.6 | Z44: =L44-(X44+Y44) -> 1303.5 | AF44: 480 | AI44: 480 | AJ44: -66
A45: 44605 | B45: 13 | C45: 44 | D45: 1 | E45: Sunday | F45: 7 | G45: 2 | H45: February | I45: 1 | J45: 10 | K45: 62 | L45: 630 | M45: 0.32 | N45: 202 | O45: 428 | P45: 0.94 | Q45: 0.28 | R45: 0.46 | S45: 0.24 | T45: 0.05 | U45: 43 | V45: 0.2 | W45: 0.06 | X45: =L45*W45 -> 37.8 | Y45: =S45*L45 -> 151.2 | Z45: =L45-(X45+Y45) -> 441 | AB45: 1000 | AI45: 1000 | AJ45: -572
A46: 44606 | B46: 14 | C46: 45 | D46: 2 | E46: Monday | F46: 7 | G46: 2 | H46: February | I46: 1 | J46: 32 | K46: 25 | L46: 790 | M46: 0.85 | N46: 672 | O46: 118 | P46: 4.31 | Q46: 0.54 | R46: 1.22 | S46: 1.82 | T46: 0.02 | U46: 17 | V46: 1.46 | W46: 0.09 | X46: =L46*W46 -> 71.1 | Y46: =S46*L46 -> 1437.8 | Z46: =L46-(X46+Y46) -> -718.9 | AI46: 0 | AJ46: 118
A47: 44607 | B47: 15 | C47: 46 | D47: 3 | E47: Tuesday | F47: 7 | G47: 2 | H47: February | I47: 1 | J47: 6 | K47: 120 | L47: 685 | M47: 0.88 | N47: 600 | O47: 85 | P47: 0.65 | Q47: 0.07 | R47: 1.25 | S47: 0.07 | T47: 0.02 | U47: 84 | V47: 0.17 | W47: 0.08 | X47: =L47*W47 -> 54.8 | Y47: =S47*L47 -> 47.95 | Z47: =L47-(X47+Y47) -> 582.25 | AC47: 300 | AI47: 300 | AJ47: -215
A48: 44608 | B48: 16 | C48: 47 | D48: 4 | E48: Wednesday | F48: 7 | G48: 2 | H48: February | I48: 1 | J48: 24 | K48: 79 | L48: 1913 | M48: 0.81 | N48: 1547 | O48: 366 | P48: 1.2 | Q48: 0.29 | R48: 1.16 | S48: 0.44 | T48: 0.01 | U48: 55 | V48: 0.35 | W48: 0.03 | X48: =L48*W48 -> 57.39 | Y48: =S48*L48 -> 841.72 | Z48: =L48-(X48+Y48) -> 1013.89 | AI48: 0 | AJ48: 366
A49: 44609 | B49: 17 | C49: 48 | D49: 5 | E49: Thursday | F49: 7 | G49: 2 | H49: February | I49: 1 | J49: 21 | K49: 176 | L49: 3666 | M49: 0.94 | N49: 3446 | O49: 220 | P49: 0.66 | Q49: 0.31 | R49: 1.34 | S49: 0.17 | T49: 0 | U49: 123 | V49: 0.09 | W49: 0.02 | X49: =L49*W49 -> 73.32 | Y49: =S49*L49 -> 623.22 | Z49: =L49-(X49+Y49) -> 2969.46 | AI49: 0 | AJ49: 220
A50: 44610 | B50: 18 | C50: 49 | D50: 6 | E50: Friday | F50: 7 | G50: 2 | H50: February | I50: 1 | J50: 34 | K50: 130 | L50: 4486 | M50: 1.06 | N50: 4766 | O50: -280 | P50: 1.1 | Q50: 0.64 | R50: 1.52 | S50: 0.38 | T50: 0 | U50: 91 | V50: 0.19 | W50: 0.02 | X50: =L50*W50 -> 89.72 | Y50: =S50*L50 -> 1704.68 | Z50: =L50-(X50+Y50) -> 2691.6 | AI50: 0 | AJ50: -280
A51: 44611 | B51: 19 | C51: 50 | D51: 7 | E51: Saturday | F51: 7 | G51: 2 | H51: February | I51: 1 | J51: 22 | K51: 69 | L51: 1529 | M51: 0.53 | N51: 812 | O51: 718 | P51: 2.78 | Q51: 0.4 | R51: 0.76 | S51: 0.46 | T51: 0.01 | U51: 48 | V51: 0.25 | W51: 0.09 | X51: =L51*W51 -> 137.61 | Y51: =S51*L51 -> 703.34 | Z51: =L51-(X51+Y51) -> 688.05 | AI51: 0 | AJ51: 718
A52: 44612 | B52: 20 | C52: 51 | D52: 1 | E52: Sunday | F52: 8 | G52: 2 | H52: February | I52: 1 | J52: 6 | K52: 66 | L52: 406 | M52: 0.31 | N52: 126 | O52: 280 | P52: 1.02 | Q52: 0.16 | R52: 0.44 | S52: 0.13 | T52: 0.07 | U52: 47 | V52: 0.21 | W52: 0.12 | X52: =L52*W52 -> 48.72 | Y52: =S52*L52 -> 52.78 | Z52: =L52-(X52+Y52) -> 304.5 | AB52: 1000 | AE52: 100 | AI52: 1100 | AJ52: -820
A53: 44613 | B53: 21 | C53: 52 | D53: 2 | E53: Monday | F53: 8 | G53: 2 | H53: February | I53: 1 | J53: 20 | K53: 128 | L53: 2540 | M53: 0.85 | N53: 2170 | O53: 370 | P53: 0.99 | Q53: 0.27 | R53: 1.22 | S53: 0.22 | T53: 0.01 | U53: 90 | V53: 0.18 | W53: 0.04 | X53: =L53*W53 -> 101.6 | Y53: =S53*L53 -> 558.8 | Z53: =L53-(X53+Y53) -> 1879.6 | AI53: 0 | AJ53: 370
A54: 44614 | B54: 22 | C54: 53 | D54: 3 | E54: Tuesday | F54: 8 | G54: 2 | H54: February | I54: 1 | J54: 10 | K54: 130 | L54: 1323 | M54: 0.99 | N54: 1310 | O54: 12 | P54: 0.84 | Q54: 0.13 | R54: 1.42 | S54: 0.11 | T54: 0.01 | U54: 91 | V54: 0.03 | W54: 0.06 | X54: =L54*W54 -> 79.38 | Y54: =S54*L54 -> 145.53 | Z54: =L54-(X54+Y54) -> 1098.09 | AI54: 0 | AJ54: 12
A55: 44615 | B55: 23 | C55: 54 | D55: 4 | E55: Wednesday | F55: 8 | G55: 2 | H55: February | I55: 1 | J55: 27 | K55: 105 | L55: 2865 | M55: 0.85 | N55: 2425 | O55: 440 | P55: 1.34 | Q55: 0.36 | R55: 1.21 | S55: 0.37 | T55: 0 | U55: 73 | V55: 0.38 | W55: 0.03 | X55: =L55*W55 -> 85.95 | Y55: =S55*L55 -> 1060.05 | Z55: =L55-(X55+Y55) -> 1719 | AI55: 0 | AJ55: 440
A56: 44616 | B56: 24 | C56: 55 | D56: 5 | E56: Thursday | F56: 8 | G56: 2 | H56: February | I56: 1 | J56: 37 | K56: 91 | L56: 3324 | M56: 0.88 | N56: 2939 | O56: 385 | P56: 0.41 | Q56: 0.39 | R56: 1.26 | S56: 0.58 | T56: 0 | U56: 63 | V56: 0.35 | W56: 0.01 | X56: =L56*W56 -> 33.24 | Y56: =S56*L56 -> 1927.92 | Z56: =L56-(X56+Y56) -> 1362.84 | AI56: 0 | AJ56: 385
A57: 44617 | B57: 25 | C57: 56 | D57: 6 | E57: Friday | F57: 8 | G57: 2 | H57: February | I57: 1 | J57: 7 | K57: 151 | L57: 1039 | M57: 0.96 | N57: 995 | O57: 44 | P57: 1.13 | Q57: 0.08 | R57: 1.37 | S57: 0.07 | T57: 0.01 | U57: 106 | V57: 0.22 | W57: 0.11 | X57: =L57*W57 -> 114.29 | Y57: =S57*L57 -> 72.73 | Z57: =L57-(X57+Y57) -> 851.98 | AG57: 83 | AI57: 83 | AJ57: -39
A58: 44618 | B58: 26 | C58: 57 | D58: 7 | E58: Saturday | F58: 8 | G58: 2 | H58: February | I58: 1 | J58: 20 | K58: 92 | L58: 1848 | M58: 1.02 | N58: 1877 | O58: -29 | P58: 0.82 | Q58: 0.22 | R58: 1.45 | S58: 0.31 | T58: 0.01 | U58: 64 | V58: 0.29 | W58: 0.03 | X58: =L58*W58 -> 55.44 | Y58: =S58*L58 -> 572.88 | Z58: =L58-(X58+Y58) -> 1219.68 | AI58: 0 | AJ58: -29
A59: 44619 | B59: 27 | C59: 58 | D59: 1 | E59: Sunday | F59: 9 | G59: 2 | H59: February | I59: 1 | J59: 12 | K59: 40 | L59: 493 | M59: 0.42 | N59: 209 | O59: 284 | P59: 1.25 | Q59: 0.42 | R59: 0.61 | S59: 0.43 | T59: 0.06 | U59: 28 | V59: 0.36 | W59: 0.07 | X59: =L59*W59 -> 34.51 | Y59: =S59*L59 -> 211.99 | Z59: =L59-(X59+Y59) -> 246.5 | AB59: 1000 | AI59: 1000 | AJ59: -716
A60: 44620 | B60: 28 | C60: 59 | D60: 2 | E60: Monday | F60: 9 | G60: 2 | H60: February | I60: 1 | J60: 29 | K60: 61 | L60: 1807 | M60: 0.81 | N60: 1463 | O60: 343 | P60: 1.58 | Q60: 0.36 | R60: 1.16 | S60: 0.68 | T60: 0.01 | U60: 43 | V60: 0.23 | W60: 0.04 | X60: =L60*W60 -> 72.28 | Y60: =S60*L60 -> 1228.76 | Z60: =L60-(X60+Y60) -> 505.96 | AI60: 0 | AJ60: 343
A61: 44621 | B61: 1 | C61: 60 | D61: 3 | E61: Tuesday | F61: 9 | G61: 3 | H61: March | I61: 1 | J61: 36 | K61: 75 | L61: 2722 | M61: 1.23 | N61: 3352 | O61: -630 | P61: 1.52 | Q61: 0.51 | R61: 1.76 | S61: 0.68 | T61: 0 | U61: 53 | V61: 0.31 | W61: 0.03 | X61: =L61*W61 -> 81.66 | Y61: =S61*L61 -> 1850.96 | Z61: =L61-(X61+Y61) -> 789.38 | AA61: 3000 | AI61: 3000 | AJ61: -3630
A62: 44622 | B62: 2 | C62: 61 | D62: 4 | E62: Wednesday | F62: 9 | G62: 3 | H62: March | I62: 1 | J62: 17 | K62: 94 | L62: 1595 | M62: 0.63 | N62: 1013 | O62: 582 | P62: 1.36 | Q62: 0.24 | R62: 0.91 | S62: 0.26 | T62: 0.01 | U62: 66 | V62: 0.17 | W62: 0.06 | X62: =L62*W62 -> 95.7 | Y62: =S62*L62 -> 414.7 | Z62: =L62-(X62+Y62) -> 1084.6 | AI62: 0 | AJ62: 582
A63: 44623 | B63: 3 | C63: 62 | D63: 5 | E63: Thursday | F63: 9 | G63: 3 | H63: March | I63: 1 | J63: 14 | K63: 120 | L63: 1680 | M63: 0.75 | N63: 1254 | O63: 426 | P63: 1.17 | Q63: 0.18 | R63: 1.07 | S63: 0.17 | T63: 0.01 | U63: 84 | V63: 0.15 | W63: 0.06 | X63: =L63*W63 -> 100.8 | Y63: =S63*L63 -> 285.6 | Z63: =L63-(X63+Y63) -> 1293.6 | AI63: 0 | AJ63: 426
A64: 44624 | B64: 4 | C64: 63 | D64: 6 | E64: Friday | F64: 9 | G64: 3 | H64: March | I64: 1 | J64: 26 | K64: 42 | L64: 1064 | M64: 1.1 | N64: 1170 | O64: -105 | P64: 2.85 | Q64: 0.35 | R64: 1.57 | S64: 0.88 | T64: 0.01 | U64: 29 | V64: 0.51 | W64: 0.08 | X64: =L64*W64 -> 85.12 | Y64: =S64*L64 -> 936.32 | Z64: =L64-(X64+Y64) -> 42.56 | AI64: 0 | AJ64: -105
A65: 44625 | B65: 5 | C65: 64 | D65: 7 | E65: Saturday | F65: 9 | G65: 3 | H65: March | I65: 1 | J65: 20 | K65: 17 | L65: 352 | M65: 0.66 | N65: 232 | O65: 120 | P65: 6.8 | Q65: 0.27 | R65: 0.94 | S65: 1.66 | T65: 0.04 | U65: 12 | V65: 0.55 | W65: 0.24 | X65: =L65*W65 -> 84.48 | Y65: =S65*L65 -> 584.32 | Z65: =L65-(X65+Y65) -> -316.8 | AH65: 1000 | AI65: 1000 | AJ65: -880
A66: 44626 | B66: 6 | C66: 65 | D66: 1 | E66: Sunday | F66: 10 | G66: 3 | H66: March | I66: 1 | J66: 7 | K66: 26 | L66: 180 | M66: 0.37 | N66: 67 | O66: 113 | P66: 0.88 | Q66: 0.59 | R66: 0.53 | S66: 0.39 | T66: 0.16 | U66: 18 | V66: 0.21 | W66: 0.09 | X66: =L66*W66 -> 16.2 | Y66: =S66*L66 -> 70.2 | Z66: =L66-(X66+Y66) -> 93.6 | AB66: 1000 | AI66: 1000 | AJ66: -887
A67: 44627 | B67: 7 | C67: 66 | D67: 2 | E67: Monday | F67: 10 | G67: 3 | H67: March | I67: 1 | J67: 17 | K67: 68 | L67: 1127 | M67: 0.46 | N67: 521 | O67: 606 | P67: 0.81 | Q67: 0.56 | R67: 0.66 | S67: 0.35 | T67: 0.01 | U67: 47 | V67: 0.1 | W67: 0.03 | X67: =L67*W67 -> 33.81 | Y67: =S67*L67 -> 394.45 | Z67: =L67-(X67+Y67) -> 698.74 | AI67: 0 | AJ67: 606
A68: 44628 | B68: 8 | C68: 67 | D68: 3 | E68: Tuesday | F68: 10 | G68: 3 | H68: March | I68: 1 | J68: 35 | K68: 65 | L68: 2279 | M68: 0.87 | N68: 1991 | O68: 287 | P68: 0.68 | Q68: 1.22 | R68: 1.25 | S68: 0.78 | T68: 0.01 | U68: 45 | V68: 0.24 | W68: 0.01 | X68: =L68*W68 -> 22.79 | Y68: =S68*L68 -> 1777.62 | Z68: =L68-(X68+Y68) -> 478.59 | AI68: 0 | AJ68: 287
A69: 44629 | B69: 9 | C69: 68 | D69: 4 | E69: Wednesday | F69: 10 | G69: 3 | H69: March | I69: 1 | J69: 20 | K69: 54 | L69: 1108 | M69: 0.66 | N69: 729 | O69: 379 | P69: 1.36 | Q69: 0.63 | R69: 0.94 | S69: 0.54 | T69: 0.01 | U69: 38 | V69: 0.3 | W69: 0.05 | X69: =L69*W69 -> 55.4 | Y69: =S69*L69 -> 598.32 | Z69: =L69-(X69+Y69) -> 454.28 | AI69: 0 | AJ69: 379
A70: 44630 | B70: 10 | C70: 69 | D70: 5 | E70: Thursday | F70: 10 | G70: 3 | H70: March | I70: 1 | J70: 15 | K70: 102 | L70: 1532 | M70: 0.67 | N70: 1028 | O70: 504 | P70: 0.49 | Q70: 0.44 | R70: 0.96 | S70: 0.21 | T70: 0.01 | U70: 71 | V70: 0.09 | W70: 0.02 | X70: =L70*W70 -> 30.64 | Y70: =S70*L70 -> 321.72 | Z70: =L70-(X70+Y70) -> 1179.64 | AD70: 300 | AI70: 300 | AJ70: 204
A71: 44631 | B71: 11 | C71: 70 | D71: 6 | E71: Friday | F71: 10 | G71: 3 | H71: March | I71: 1 | J71: 26 | K71: 66 | L71: 1719 | M71: 0.76 | N71: 1305 | O71: 414 | P71: 0.59 | Q71: 1.13 | R71: 1.08 | S71: 0.56 | T71: 0.01 | U71: 46 | V71: 0.22 | W71: 0.02 | X71: =L71*W71 -> 34.38 | Y71: =S71*L71 -> 962.64 | Z71: =L71-(X71+Y71) -> 721.98 | AI71: 0 | AJ71: 414
A72: 44632 | B72: 12 | C72: 71 | D72: 7 | E72: Saturday | F72: 10 | G72: 3 | H72: March | I72: 1 | J72: 5 | K72: 8 | L72: 36 | M72: 0.6 | N72: 22 | O72: 14 | P72: 5.28 | Q72: 0.16 | R72: 0.86 | S72: 0.9 | T72: 0.36 | U72: 5 | V72: 2.33 | W72: 0.78 | X72: =L72*W72 -> 28.08 | Y72: =S72*L72 -> 32.4 | Z72: =L72-(X72+Y72) -> -24.48 | AF72: 480 | AI72: 480 | AJ72: -466
A73: 44633 | B73: 13 | C73: 72 | D73: 1 | E73: Sunday | F73: 11 | G73: 3 | H73: March | I73: 1 | J73: 10 | K73: 35 | L73: 345 | M73: 0.23 | N73: 78 | O73: 267 | P73: 0.32 | Q73: 0.74 | R73: 0.32 | S73: 0.41 | T73: 0.08 | U73: 24 | V73: 0.19 | W73: 0.02 | X73: =L73*W73 -> 6.9 | Y73: =S73*L73 -> 141.45 | Z73: =L73-(X73+Y73) -> 196.65 | AB73: 1000 | AI73: 1000 | AJ73: -733
A74: 44634 | B74: 14 | C74: 73 | D74: 2 | E74: Monday | F74: 11 | G74: 3 | H74: March | I74: 1 | J74: 16 | K74: 72 | L74: 1134 | M74: 0.53 | N74: 597 | O74: 538 | P74: 0.8 | Q74: 0.51 | R74: 0.75 | S74: 0.31 | T74: 0.01 | U74: 50 | V74: 0.17 | W74: 0.04 | X74: =L74*W74 -> 45.36 | Y74: =S74*L74 -> 351.54 | Z74: =L74-(X74+Y74) -> 737.1 | AI74: 0 | AJ74: 538
A75: 44635 | B75: 15 | C75: 74 | D75: 3 | E75: Tuesday | F75: 11 | G75: 3 | H75: March | I75: 1 | J75: 22 | K75: 111 | L75: 2462 | M75: 0.4 | N75: 982 | O75: 1481 | P75: 0.41 | Q75: 0.65 | R75: 0.57 | S75: 0.28 | T75: 0.01 | U75: 78 | V75: 0.14 | W75: 0.01 | X75: =L75*W75 -> 24.62 | Y75: =S75*L75 -> 689.36 | Z75: =L75-(X75+Y75) -> 1748.02 | AC75: 300 | AI75: 300 | AJ75: 1181
A76: 44636 | B76: 16 | C76: 75 | D76: 4 | E76: Wednesday | F76: 11 | G76: 3 | H76: March | I76: 1 | J76: 13 | K76: 50 | L76: 635 | M76: 0.79 | N76: 501 | O76: 135 | P76: 0.85 | Q76: 0.43 | R76: 1.13 | S76: 0.36 | T76: 0.02 | U76: 35 | V76: 0.2 | W76: 0.05 | X76: =L76*W76 -> 31.75 | Y76: =S76*L76 -> 228.6 | Z76: =L76-(X76+Y76) -> 374.65 | AI76: 0 | AJ76: 135
A77: 44637 | B77: 17 | C77: 76 | D77: 5 | E77: Thursday | F77: 11 | G77: 3 | H77: March | I77: 1 | J77: 17 | K77: 95 | L77: 1609 | M77: 0.76 | N77: 1216 | O77: 393 | P77: 0.48 | Q77: 0.7 | R77: 1.08 | S77: 0.26 | T77: 0.01 | U77: 66 | V77: 0.09 | W77: 0.02 | X77: =L77*W77 -> 32.18 | Y77: =S77*L77 -> 418.34 | Z77: =L77-(X77+Y77) -> 1158.48 | AI77: 0 | AJ77: 393
A78: 44638 | B78: 18 | C78: 77 | D78: 6 | E78: Friday | F78: 11 | G78: 3 | H78: March | I78: 1 | J78: 18 | K78: 26 | L78: 469 | M78: 0.58 | N78: 270 | O78: 199 | P78: 2.1 | Q78: 0.79 | R78: 0.82 | S78: 1.01 | T78: 0.03 | U78: 18 | V78: 0.52 | W78: 0.08 | X78: =L78*W78 -> 37.52 | Y78: =S78*L78 -> 473.69 | Z78: =L78-(X78+Y78) -> -42.21 | AI78: 0 | AJ78: 199
A79: 44639 | B79: 19 | C79: 78 | D79: 7 | E79: Saturday | F79: 11 | G79: 3 | H79: March | I79: 1 | J79: 3 | K79: 48 | L79: 131 | M79: 0.84 | N79: 110 | O79: 21 | P79: 1.38 | Q79: 0.13 | R79: 1.2 | S79: 0.08 | T79: 0.1 | U79: 34 | V79: 0.14 | W79: 0.35 | X79: =L79*W79 -> 45.85 | Y79: =S79*L79 -> 10.48 | Z79: =L79-(X79+Y79) -> 74.67 | AI79: 0 | AJ79: 21
A80: 44640 | B80: 20 | C80: 79 | D80: 1 | E80: Sunday | F80: 12 | G80: 3 | H80: March | I80: 1 | J80: 6 | K80: 43 | L80: 248 | M80: 0.31 | N80: 77 | O80: 171 | P80: 0.41 | Q80: 0.47 | R80: 0.44 | S80: 0.19 | T80: 0.12 | U80: 30 | V80: 0.03 | W80: 0.05 | X80: =L80*W80 -> 12.4 | Y80: =S80*L80 -> 47.12 | Z80: =L80-(X80+Y80) -> 188.48 | AB80: 1000 | AE80: 100 | AI80: 1100 | AJ80: -929
A81: 44641 | B81: 21 | C81: 80 | D81: 2 | E81: Monday | F81: 12 | G81: 3 | H81: March | I81: 1 | J81: 17 | K81: 93 | L81: 1564 | M81: 0.69 | N81: 1075 | O81: 488 | P81: 0.38 | Q81: 0.52 | R81: 0.98 | S81: 0.26 | T81: 0.01 | U81: 65 | V81: 0.12 | W81: 0.02 | X81: =L81*W81 -> 31.28 | Y81: =S81*L81 -> 406.64 | Z81: =L81-(X81+Y81) -> 1126.08 | AI81: 0 | AJ81: 488
A82: 44642 | B82: 22 | C82: 81 | D82: 3 | E82: Tuesday | F82: 12 | G82: 3 | H82: March | I82: 1 | J82: 13 | K82: 74 | L82: 947 | M82: 0.92 | N82: 872 | O82: 76 | P82: 0.8 | Q82: 0.38 | R82: 1.31 | S82: 0.25 | T82: 0.01 | U82: 51 | V82: 0.13 | W82: 0.04 | X82: =L82*W82 -> 37.88 | Y82: =S82*L82 -> 236.75 | Z82: =L82-(X82+Y82) -> 672.37 | AI82: 0 | AJ82: 76
A83: 44643 | B83: 23 | C83: 82 | D83: 4 | E83: Wednesday | F83: 12 | G83: 3 | H83: March | I83: 1 | J83: 4 | K83: 49 | L83: 211 | M83: 0.28 | N83: 59 | O83: 152 | P83: 1.23 | Q83: 0.16 | R83: 0.4 | S83: 0.13 | T83: 0.06 | U83: 34 | V83: 0.3 | W83: 0.2 | X83: =L83*W83 -> 42.2 | Y83: =S83*L83 -> 27.43 | Z83: =L83-(X83+Y83) -> 141.37 | AI83: 0 | AJ83: 152
A84: 44644 | B84: 24 | C84: 83 | D84: 5 | E84: Thursday | F84: 12 | G84: 3 | H84: March | I84: 1 | J84: 22 | K84: 19 | L84: 424 | M84: 0.47 | N84: 201 | O84: 223 | P84: 3.09 | Q84: 0.7 | R84: 0.68 | S84: 1.59 | T84: 0.03 | U84: 14 | V84: 1.05 | W84: 0.1 | X84: =L84*W84 -> 42.4 | Y84: =S84*L84 -> 674.16 | Z84: =L84-(X84+Y84) -> -292.56 | AI84: 0 | AJ84: 223
A85: 44645 | B85: 25 | C85: 84 | D85: 6 | E85: Friday | F85: 12 | G85: 3 | H85: March | I85: 1 | J85: 22 | K85: 50 | L85: 1097 | M85: 0.72 | N85: 789 | O85: 308 | P85: 1.48 | Q85: 0.79 | R85: 1.03 | S85: 0.64 | T85: 0.01 | U85: 35 | V85: 0.19 | W85: 0.05 | X85: =L85*W85 -> 54.85 | Y85: =S85*L85 -> 702.08 | Z85: =L85-(X85+Y85) -> 340.07 | AG85: 83 | AI85: 83 | AJ85: 225
A86: 44646 | B86: 26 | C86: 85 | D86: 7 | E86: Saturday | F86: 12 | G86: 3 | H86: March | I86: 1 | J86: 18 | K86: 45 | L86: 805 | M86: 0.65 | N86: 521 | O86: 284 | P86: 0.86 | Q86: 0.55 | R86: 0.92 | S86: 0.58 | T86: 0.02 | U86: 31 | V86: 0.23 | W86: 0.03 | X86: =L86*W86 -> 24.15 | Y86: =S86*L86 -> 466.9 | Z86: =L86-(X86+Y86) -> 313.95 | AI86: 0 | AJ86: 284
A87: 44647 | B87: 27 | C87: 86 | D87: 1 | E87: Sunday | F87: 13 | G87: 3 | H87: March | I87: 1 | J87: 3 | K87: 12 | L87: 34 | M87: 0.26 | N87: 9 | O87: 25 | P87: 2.03 | Q87: 0.22 | R87: 0.37 | S87: 0.32 | T87: 0.85 | U87: 9 | V87: 0.29 | W87: 0.51 | X87: =L87*W87 -> 17.34 | Y87: =S87*L87 -> 10.88 | Z87: =L87-(X87+Y87) -> 5.78 | AB87: 1000 | AI87: 1000 | AJ87: -975
A88: 44648 | B88: 28 | C88: 87 | D88: 2 | E88: Monday | F88: 13 | G88: 3 | H88: March | I88: 1 | J88: 19 | K88: 40 | L88: 754 | M88: 0.58 | N88: 441 | O88: 313 | P88: 1.96 | Q88: 0.62 | R88: 0.83 | S88: 0.68 | T88: 0.02 | U88: 28 | V88: 0.32 | W88: 0.07 | X88: =L88*W88 -> 52.78 | Y88: =S88*L88 -> 512.72 | Z88: =L88-(X88+Y88) -> 188.5 | AI88: 0 | AJ88: 313
A89: 44649 | B89: 29 | C89: 88 | D89: 3 | E89: Tuesday | F89: 13 | G89: 3 | H89: March | I89: 1 | J89: 18 | K89: 46 | L89: 823 | M89: 0.8 | N89: 657 | O89: 167 | P89: 1.18 | Q89: 0.55 | R89: 1.14 | S89: 0.56 | T89: 0.02 | U89: 32 | V89: 0.08 | W89: 0.05 | X89: =L89*W89 -> 41.15 | Y89: =S89*L89 -> 460.88 | Z89: =L89-(X89+Y89) -> 320.97 | AI89: 0 | AJ89: 167
A90: 44650 | B90: 30 | C90: 89 | D90: 4 | E90: Wednesday | F90: 13 | G90: 3 | H90: March | I90: 1 | J90: 20 | K90: 14 | L90: 283 | M90: 0.56 | N90: 159 | O90: 123 | P90: 3.5 | Q90: 0.55 | R90: 0.8 | S90: 2.03 | T90: 0.05 | U90: 10 | V90: 1.01 | W90: 0.12 | X90: =L90*W90 -> 33.96 | Y90: =S90*L90 -> 574.49 | Z90: =L90-(X90+Y90) -> -325.45 | AI90: 0 | AJ90: 123
A91: 44651 | B91: 31 | C91: 90 | D91: 5 | E91: Thursday | F91: 13 | G91: 3 | H91: March | I91: 1 | J91: 1 | K91: 84 | L91: 105 | M91: 0.41 | N91: 43 | O91: 61 | P91: 0.59 | Q91: 0.04 | R91: 0.59 | S91: 0.02 | T91: 0.12 | U91: 59 | V91: 0.17 | W91: 0.33 | X91: =L91*W91 -> 34.65 | Y91: =S91*L91 -> 2.1 | Z91: =L91-(X91+Y91) -> 68.25 | AI91: 0 | AJ91: 61
A92: 44652 | B92: 1 | C92: 91 | D92: 6 | E92: Friday | F92: 13 | G92: 4 | H92: April | I92: 2 | J92: 14 | K92: 106 | L92: 1433 | M92: 0.64 | N92: 922 | O92: 510 | P92: 0.53 | Q92: 0.41 | R92: 0.92 | S92: 0.18 | T92: 0.01 | U92: 74 | V92: 0.03 | W92: 0.03 | X92: =L92*W92 -> 42.99 | Y92: =S92*L92 -> 257.94 | Z92: =L92-(X92+Y92) -> 1132.07 | AA92: 3000 | AI92: 3000 | AJ92: -2490
A93: 44653 | B93: 2 | C93: 92 | D93: 7 | E93: Saturday | F93: 13 | G93: 4 | H93: April | I93: 2 | J93: 16 | K93: 108 | L93: 1775 | M93: 0.49 | N93: 876 | O93: 898 | P93: 0.32 | Q93: 0.68 | R93: 0.71 | S93: 0.22 | T93: 0.01 | U93: 76 | V93: 0.02 | W93: 0.01 | X93: =L93*W93 -> 17.75 | Y93: =S93*L93 -> 390.5 | Z93: =L93-(X93+Y93) -> 1366.75 | AI93: 0 | AJ93: 898
A94: 44654 | B94: 3 | C94: 93 | D94: 1 | E94: Sunday | F94: 14 | G94: 4 | H94: April | I94: 2 | J94: 13 | K94: 18 | L94: 231 | M94: 0.25 | N94: 57 | O94: 174 | P94: 0.96 | Q94: 0.98 | R94: 0.35 | S94: 1.01 | T94: 0.12 | U94: 13 | V94: 0.37 | W94: 0.05 | X94: =L94*W94 -> 11.55 | Y94: =S94*L94 -> 233.31 | Z94: =L94-(X94+Y94) -> -13.86 | AB94: 1000 | AI94: 1000 | AJ94: -826
A95: 44655 | B95: 4 | C95: 94 | D95: 2 | E95: Monday | F95: 14 | G95: 4 | H95: April | I95: 2 | J95: 19 | K95: 66 | L95: 1262 | M95: 0.34 | N95: 423 | O95: 839 | P95: 0.94 | Q95: 0.52 | R95: 0.48 | S95: 0.41 | T95: 0.01 | U95: 46 | V95: 0.27 | W95: 0.03 | X95: =L95*W95 -> 37.86 | Y95: =S95*L95 -> 517.42 | Z95: =L95-(X95+Y95) -> 706.72 | AI95: 0 | AJ95: 839
A96: 44656 | B96: 5 | C96: 95 | D96: 3 | E96: Tuesday | F96: 14 | G96: 4 | H96: April | I96: 2 | J96: 18 | K96: 108 | L96: 1910 | M96: 0.33 | N96: 621 | O96: 1289 | P96: 0.32 | Q96: 0.61 | R96: 0.46 | S96: 0.23 | T96: 0.01 | U96: 76 | V96: 0.06 | W96: 0.01 | X96: =L96*W96 -> 19.1 | Y96: =S96*L96 -> 439.3 | Z96: =L96-(X96+Y96) -> 1451.6 | AH96: 1000 | AI96: 1000 | AJ96: 289
A97: 44657 | B97: 6 | C97: 96 | D97: 4 | E97: Wednesday | F97: 14 | G97: 4 | H97: April | I97: 2 | J97: 14 | K97: 37 | L97: 517 | M97: 0.71 | N97: 366 | O97: 150 | P97: 1.66 | Q97: 0.51 | R97: 1.01 | S97: 0.55 | T97: 0.03 | U97: 26 | V97: 0.35 | W97: 0.08 | X97: =L97*W97 -> 41.36 | Y97: =S97*L97 -> 284.35 | Z97: =L97-(X97+Y97) -> 191.29 | AI97: 0 | AJ97: 150
A98: 44658 | B98: 7 | C98: 97 | D98: 5 | E98: Thursday | F98: 14 | G98: 4 | H98: April | I98: 2 | J98: 20 | K98: 71 | L98: 1397 | M98: 0.75 | N98: 1046 | O98: 350 | P98: 0.82 | Q98: 0.78 | R98: 1.07 | S98: 0.4 | T98: 0.01 | U98: 50 | V98: 0.17 | W98: 0.03 | X98: =L98*W98 -> 41.91 | Y98: =S98*L98 -> 558.8 | Z98: =L98-(X98+Y98) -> 796.29 | AI98: 0 | AJ98: 350
A99: 44659 | B99: 8 | C99: 98 | D99: 6 | E99: Friday | F99: 14 | G99: 4 | H99: April | I99: 2 | J99: 26 | K99: 71 | L99: 1838 | M99: 0.43 | N99: 786 | O99: 1052 | P99: 0.67 | Q99: 0.86 | R99: 0.61 | S99: 0.52 | T99: 0.01 | U99: 50 | V99: 0.18 | W99: 0.02 | X99: =L99*W99 -> 36.76 | Y99: =S99*L99 -> 955.76 | Z99: =L99-(X99+Y99) -> 845.48 | AI99: 0 | AJ99: 1052
A100: 44660 | B100: 9 | C100: 99 | D100: 7 | E100: Saturday | F100: 14 | G100: 4 | H100: April | I100: 2 | J100: 13 | K100: 23 | L100: 302 | M100: 0.76 | N100: 228 | O100: 73 | P100: 2.18 | Q100: 0.36 | R100: 1.08 | S100: 0.83 | T100: 0.04 | U100: 16 | V100: 0.44 | W100: 0.12 | X100: =L100*W100 -> 36.24 | Y100: =S100*L100 -> 250.66 | Z100: =L100-(X100+Y100) -> 15.1 | AI100: 0 | AJ100: 73
...

Sheet Chance
A1: YOUR COMPANY NAME | D1: Flowerama
S2: =AG9/7 -> 142.85714
AG4: =AG5+200 -> 1200
AF5: 3000 | AG5: 1000 | AH5: 300 | AI5: 300 | AJ5: 100 | AK5: 480 | AL5: 83 | AM5: 1000
W6: KPI | AF6: 1 | AG6: Sunday | AH6: 15 | AI6: 10 | AJ6: 20 | AK6: 12 | AL6: 25 | AM6: 5
A7: Date | B7: Dayo Month | C7: Dayo Year | D7: Dayo Week # | E7: Dayo Week Name | F7: Weeko Year | G7: Month # | H7: Month Name | I7: Quarter | J7: Foot Traffic (customers per day) | K7: Chance Foot Traffic | L7: Spend per Customer | M7: Total Revenue | N7: Daily COGS | O7: COGS | P7: Gross Margin | Q7: buy online | R7: Stems discard | S7: Wages paied by day | T7: Online Orders | U7: Delvery Total rev | V7: Delevry orders | W7: Peps in door | X7: Online delevery | Y7: Conversion Rate | Z7: Avg Delevry cost % | AA7: Delevery percentage | AB7: percent of wage per hr | AC7: Average Delevery value per Order | AD7: Dollar wasted oer stem discarded | AE7: online order % | AF7: Rent / Lease | AG7: Wages and Salaries | AH7: Insurance | AI7: Electric | AJ7: Water | AK7: Phone | AL7: Internet | AM7: Delivery | AN7: Total Expenses | AO7: Profit
A8: 44562 | B8: 1 | C8: 1 | D8: 7 | E8: Saturday | F8: 1 | G8: 1 | H8: January | I8: 1 | J8: 18.248423 | K8: =J8 -> 18.248423 | L8: 63.210073 | M8: =K8*L8 -> 1153.4842 | N8: 0.38876823 | O8: =M8*N8 -> 448.43799 | P8: =M8-O8 -> 705.04617 | Q8: 43.748147 | R8: 6.6793627 | S8: =IF(E8=$AG$6,$S$2/5,$S$2/11) -> 12.987013 | T8: 28.155118 | U8: =M8*0.7 -> 807.43891 | V8: =U8/K8 -> 44.247051 | W8: 26.334351 | X8: =Q8/V8 -> 0.98872459 | Y8: =J8/W8 -> 0.69295131 | Z8: =O8/U8 -> 0.55538318 | AA8: =K8/V8 -> 0.41242123 | AB8: =S8/M8 -> 0.011258944 | AC8: =U8/J8 -> 44.247051 | AD8: =R8/L8 -> 0.10566928 | AE8: =Q8/M8 -> 0.03792696 | AF8: =IF(B8=$AF$6,$AF$5, ) -> 3000 | AG8: =IF(E8=$AG$6,$AG$5,"") | AH8: =IF(B8=$AH$6,$AH$5,"") | AI8: =IF($B$8=AI6,AI5,"") | AJ8: =IF($B8=$AJ$6,$AJ$5,"") | AK8: =IF($B8=$AK$6,$AK$5,"") | AL8: =IF($B8=$AL$6,$AL$5,"") | AM8: =IF($B8=$AM$6,$AM$5,"") | AN8: =SUM(AF8:AM8) -> 3000 | AO8: =P8-AN8 -> -2294.9538
A9: 44563 | B9: 2 | C9: 2 | D9: 1 | E9: Sunday | F9: 1 | G9: 1 | H9: January | I9: 1 | J9: 5.6481892 | K9: =J9 -> 5.6481892 | L9: 37.00637 | M9: =K9*L9 -> 209.01898 | N9: 0.21121235 | O9: =M9*N9 -> 44.14739 | P9: =M9-O9 -> 164.87159 | Q9: 15.607485 | R9: 7.0101524 | S9: =IF(E9=$AG$6,$S$2/5,$S$2/11) -> 28.571429 | T9: 13.589794 | U9: =M9*0.7 -> 146.31329 | V9: =U9/K9 -> 25.904459 | W9: 13.883588 | X9: =Q9/V9 -> 0.60250188 | Y9: =K9/W9 -> 0.40682489 | Z9: =O9/U9 -> 0.30173193 | AA9: =K9/V9 -> 0.21803926 | AB9: =S9/M9 -> 0.13669299 | AC9: =U9/K9 -> 25.904459 | AD9: =R9/L9 -> 0.18943096 | AE9: =Q9/M9 -> 0.074670182 | AF9: =IF(B9=$AF$6,$AF$5, "") | AG9: =IF(E9=$AG$6,$AG$5,"") -> 1000 | AH9: =IF(B9=$AH$6,$AH$5,"") | AI9: =IF(B9=$AI$6,$AI$5,"") | AJ9: =IF($B9=$AJ$6,$AJ$5,"") | AK9: =IF($B9=$AK$6,$AK$5,"") | AL9: =IF($B9=$AL$6,$AL$5,"") | AM9: =IF($B9=$AM$6,$AM$5,"") | AN9: =SUM(AF9:AM9) -> 1000 | AO9: =P9-AN9 -> -835.12841
A10: 44564 | B10: 3 | C10: 3 | D10: 2 | E10: Monday | F10: 1 | G10: 1 | H10: January | I10: 1 | J10: 10.949241 | K10: =J10 -> 10.949241 | L10: 8.9188617 | M10: =K10*L10 -> 97.654762 | N10: 0.50933335 | O10: =M10*N10 -> 49.738827 | P10: =M10-O10 -> 47.915935 | Q10: 36.952446 | R10: 7.7018362 | S10: =IF(E10=$AG$6,$S$2/5,$S$2/11) -> 12.987013 | T10: 30.385295 | U10: =M10*0.7 -> 68.358333 | V10: =U10/K10 -> 6.2432032 | W10: 25.259286 | X10: =Q10/V10 -> 5.918828 | Y10: =K10/W10 -> 0.43347387 | Z10: =O10/U10 -> 0.72761907 | AA10: =K10/V10 -> 1.7537857 | AB10: =S10/M10 -> 0.13298904 | AC10: =U10/K10 -> 6.2432032 | AD10: =R10/L10 -> 0.86354475 | AE10: =Q10/M10 -> 0.37839881 | AF10: =IF(B10=$AF$6,$AF$5, "") | AG10: =IF(E10=$AG$6,$AG$5,"") | AH10: =IF(B10=$AH$6,$AH$5,"") | AI10: =IF(B10=$AI$6,$AI$5,"") | AJ10: =IF($B10=$AJ$6,$AJ$5,"") | AK10: =IF($B10=$AK$6,$AK$5,"") | AL10: =IF($B10=$AL$6,$AL$5,"") | AM10: =IF($B10=$AM$6,$AM$5,"") | AN10: =SUM(AF10:AM10) -> 0 | AO10: =P10-AN10 -> 47.915935
A11: 44565 | B11: 4 | C11: 4 | D11: 3 | E11: Tuesday | F11: 1 | G11: 1 | H11: January | I11: 1 | J11: 12.174664 | K11: =J11 -> 12.174664 | L11: 27.250856 | M11: =K11*L11 -> 331.77002 | N11: 0.36085715 | O11: =M11*N11 -> 119.72158 | P11: =M11-O11 -> 212.04843 | Q11: 26.314823 | R11: 5.9731019 | S11: =IF(E11=$AG$6,$S$2/5,$S$2/11) -> 12.987013 | T11: 25.204278 | U11: =M11*0.7 -> 232.23901 | V11: =U11/K11 -> 19.075599 | W11: 35.670771 | X11: =Q11/V11 -> 1.3795018 | Y11: =K11/W11 -> 0.34130645 | Z11: =O11/U11 -> 0.51551022 | AA11: =K11/V11 -> 0.63823233 | AB11: =S11/M11 -> 0.039144625 | AC11: =U11/K11 -> 19.075599 | AD11: =R11/L11 -> 0.21918952 | AE11: =Q11/M11 -> 0.07931646 | AF11: =IF(B11=$AF$6,$AF$5, "") | AG11: =IF(E11=$AG$6,$AG$5,"") | AH11: =IF(B11=$AH$6,$AH$5,"") | AI11: =IF(B11=$AI$6,$AI$5,"") | AJ11: =IF($B11=$AJ$6,$AJ$5,"") | AK11: =IF($B11=$AK$6,$AK$5,"") | AL11: =IF($B11=$AL$6,$AL$5,"") | AM11: =IF($B11=$AM$6,$AM$5,"") | AN11: =SUM(AF11:AM11) -> 0 | AO11: =P11-AN11 -> 212.04843
A12: 44566 | B12: 5 | C12: 5 | D12: 4 | E12: Wednesday | F12: 1 | G12: 1 | H12: January | I12: 1 | J12: 7.8061021 | K12: =J12 -> 7.8061021 | L12: 38.12985 | M12: =K12*L12 -> 297.64551 | N12: 0.34623885 | O12: =M12*N12 -> 103.05644 | P12: =M12-O12 -> 194.58907 | Q12: 32.519419 | R12: 1.4195718 | S12: =IF(E12=$AG$6,$S$2/5,$S$2/11) -> 12.987013 | T12: 27.172086 | U12: =M12*0.7 -> 208.35185 | V12: =U12/K12 -> 26.690895 | W12: 24.852601 | X12: =Q12/V12 -> 1.2183712 | Y12: =K12/W12 -> 0.31409598 | Z12: =O12/U12 -> 0.49462693 | AA12: =K12/V12 -> 0.29246311 | AB12: =S12/M12 -> 0.043632485 | AC12: =U12/K12 -> 26.690895 | AD12: =R12/L12 -> 0.037229934 | AE12: =Q12/M12 -> 0.10925553 | AF12: =IF(B12=$AF$6,$AF$5, "") | AG12: =IF(E12=$AG$6,$AG$5,"") | AH12: =IF(B12=$AH$6,$AH$5,"") | AI12: =IF(B12=$AI$6,$AI$5,"") | AJ12: =IF($B12=$AJ$6,$AJ$5,"") | AK12: =IF($B12=$AK$6,$AK$5,"") | AL12: =IF($B12=$AL$6,$AL$5,"") | AM12: =IF($B12=$AM$6,$AM$5,"") -> 1000 | AN12: =SUM(AF12:AM12) -> 1000 | AO12: =P12-AN12 -> -805.41093
A13: 44567 | B13: 6 | C13: 6 | D13: 5 | E13: Thursday | F13: 1 | G13: 1 | H13: January | I13: 1 | J13: 9.2683237 | K13: =J13 -> 9.2683237 | L13: 29.780468 | M13: =K13*L13 -> 276.01501 | N13: 0.40558507 | O13: =M13*N13 -> 111.94757 | P13: =M13-O13 -> 164.06745 | Q13: 38.666184 | R13: 8.9853593 | S13: =IF(E13=$AG$6,$S$2/5,$S$2/11) -> 12.987013 | T13: 34.524216 | U13: =M13*0.7 -> 193.21051 | V13: =U13/K13 -> 20.846327 | W13: 34.428736 | X13: =Q13/V13 -> 1.85482 | Y13: =K13/W13 -> 0.26920314 | Z13: =O13/U13 -> 0.57940724 | AA13: =K13/V13 -> 0.44460223 | AB13: =S13/M13 -> 0.047051835 | AC13: =U13/K13 -> 20.846327 | AD13: =R13/L13 -> 0.30171989 | AE13: =Q13/M13 -> 0.14008725 | AF13: =IF(B13=$AF$6,$AF$5, "") | AG13: =IF(E13=$AG$6,$AG$5,"") | AH13: =IF(B13=$AH$6,$AH$5,"") | AI13: =IF(B13=$AI$6,$AI$5,"") | AJ13: =IF($B13=$AJ$6,$AJ$5,"") | AK13: =IF($B13=$AK$6,$AK$5,"") | AL13: =IF($B13=$AL$6,$AL$5,"") | AM13: =IF($B13=$AM$6,$AM$5,"") | AN13: =SUM(AF13:AM13) -> 0 | AO13: =P13-AN13 -> 164.06745
A14: 44568 | B14: 7 | C14: 7 | D14: 6 | E14: Friday | F14: 1 | G14: 1 | H14: January | I14: 1 | J14: 5.7375578 | K14: =J14 -> 5.7375578 | L14: 43.485501 | M14: =K14*L14 -> 249.50058 | N14: 0.39389748 | O14: =M14*N14 -> 98.277649 | P14: =M14-O14 -> 151.22293 | Q14: 29.232184 | R14: 7.0897059 | S14: =IF(E14=$AG$6,$S$2/5,$S$2/11) -> 12.987013 | T14: 31.126457 | U14: =M14*0.7 -> 174.6504 | V14: =U14/K14 -> 30.439851 | W14: 35.188495 | X14: =Q14/V14 -> 0.96032612 | Y14: =K14/W14 -> 0.16305209 | Z14: =O14/U14 -> 0.56271069 | AA14: =K14/V14 -> 0.18848837 | AB14: =S14/M14 -> 0.052052036 | AC14: =U14/K14 -> 30.439851 | AD14: =R14/L14 -> 0.16303609 | AE14: =Q14/M14 -> 0.11716279 | AF14: =IF(B14=$AF$6,$AF$5, "") | AG14: =IF(E14=$AG$6,$AG$5,"") | AH14: =IF(B14=$AH$6,$AH$5,"") | AI14: =IF(B14=$AI$6,$AI$5,"") | AJ14: =IF($B14=$AJ$6,$AJ$5,"") | AK14: =IF($B14=$AK$6,$AK$5,"") | AL14: =IF($B14=$AL$6,$AL$5,"") | AM14: =IF($B14=$AM$6,$AM$5,"") | AN14: =SUM(AF14:AM14) -> 0 | AO14: =P14-AN14 -> 151.22293
A15: 44569 | B15: 8 | C15: 8 | D15: 7 | E15: Saturday | F15: 1 | G15: 1 | H15: January | I15: 1 | J15: 9.6976877 | K15: =J15 -> 9.6976877 | L15: 30.347755 | M15: =K15*L15 -> 294.30305 | N15: 0.33384866 | O15: =M15*N15 -> 98.252679 | P15: =M15-O15 -> 196.05037 | Q15: 23.267168 | R15: 2.1453246 | S15: =IF(E15=$AG$6,$S$2/5,$S$2/11) -> 12.987013 | T15: 30.204552 | U15: =M15*0.7 -> 206.01213 | V15: =U15/K15 -> 21.243428 | W15: 28.435653 | X15: =Q15/V15 -> 1.0952643 | Y15: =K15/W15 -> 0.34103973 | Z15: =O15/U15 -> 0.47692666 | AA15: =K15/V15 -> 0.45650295 | AB15: =S15/M15 -> 0.044128027 | AC15: =U15/K15 -> 21.243428 | AD15: =R15/L15 -> 0.070691378 | AE15: =Q15/M15 -> 0.079058535 | AF15: =IF(B15=$AF$6,$AF$5, "") | AG15: =IF(E15=$AG$6,$AG$5,"") | AH15: =IF(B15=$AH$6,$AH$5,"") | AI15: =IF(B15=$AI$6,$AI$5,"") | AJ15: =IF($B15=$AJ$6,$AJ$5,"") | AK15: =IF($B15=$AK$6,$AK$5,"") | AL15: =IF($B15=$AL$6,$AL$5,"") | AM15: =IF($B15=$AM$6,$AM$5,"") | AN15: =SUM(AF15:AM15) -> 0 | AO15: =P15-AN15 -> 196.05037
A16: 44570 | B16: 9 | C16: 9 | D16: 1 | E16: Sunday | F16: 2 | G16: 1 | H16: January | I16: 1 | J16: 5.5871449 | K16: =J16 -> 5.5871449 | L16: 21.60263 | M16: =K16*L16 -> 120.69702 | N16: 0.27132475 | O16: =M16*N16 -> 32.748089 | P16: =M16-O16 -> 87.948933 | Q16: 16.590911 | R16: 3.6238352 | S16: =IF(E16=$AG$6,$S$2/5,$S$2/11) -> 28.571429 | T16: 14.680302 | U16: =M16*0.7 -> 84.487915 | V16: =U16/K16 -> 15.121841 | W16: 12.701462 | X16: =Q16/V16 -> 1.0971489 | Y16: =K16/W16 -> 0.43988203 | Z16: =O16/U16 -> 0.38760678 | AA16: =K16/V16 -> 0.36947519 | AB16: =S16/M16 -> 0.23672025 | AC16: =U16/K16 -> 15.121841 | AD16: =R16/L16 -> 0.16774973 | AE16: =Q16/M16 -> 0.13745916 | AF16: =IF(B16=$AF$6,$AF$5, "") | AG16: =IF(E16=$AG$6,$AG$5,"") -> 1000 | AH16: =IF(B16=$AH$6,$AH$5,"") | AI16: =IF(B16=$AI$6,$AI$5,"") | AJ16: =IF($B16=$AJ$6,$AJ$5,"") | AK16: =IF($B16=$AK$6,$AK$5,"") | AL16: =IF($B16=$AL$6,$AL$5,"") | AM16: =IF($B16=$AM$6,$AM$5,"") | AN16: =SUM(AF16:AM16) -> 1000 | AO16: =P16-AN16 -> -912.05107
A17: 44571 | B17: 10 | C17: 10 | D17: 2 | E17: Monday | F17: 2 | G17: 1 | H17: January | I17: 1 | J17: 8.7214496 | K17: =J17 -> 8.7214496 | L17: 50.462988 | M17: =K17*L17 -> 440.11041 | N17: 0.29690507 | O17: =M17*N17 -> 130.67101 | P17: =M17-O17 -> 309.4394 | Q17: 37.40443 | R17: 7.6271942 | S17: =IF(E17=$AG$6,$S$2/5,$S$2/11) -> 12.987013 | T17: 25.73566 | U17: =M17*0.7 -> 308.07729 | V17: =U17/K17 -> 35.324092 | W17: 34.111474 | X17: =Q17/V17 -> 1.0588929 | Y17: =K17/W17 -> 0.25567496 | Z17: =O17/U17 -> 0.4241501 | AA17: =K17/V17 -> 0.24689806 | AB17: =S17/M17 -> 0.029508534 | AC17: =U17/K17 -> 35.324092 | AD17: =R17/L17 -> 0.15114432 | AE17: =Q17/M17 -> 0.084988743 | AF17: =IF(B17=$AF$6,$AF$5, "") | AG17: =IF(E17=$AG$6,$AG$5,"") | AH17: =IF(B17=$AH$6,$AH$5,"") | AI17: =IF(B17=$AI$6,$AI$5,"") -> 300 | AJ17: =IF($B17=$AJ$6,$AJ$5,"") | AK17: =IF($B17=$AK$6,$AK$5,"") | AL17: =IF($B17=$AL$6,$AL$5,"") | AM17: =IF($B17=$AM$6,$AM$5,"") | AN17: =SUM(AF17:AM17) -> 300 | AO17: =P17-AN17 -> 9.4393969
A18: 44572 | B18: 11 | C18: 11 | D18: 3 | E18: Tuesday | F18: 2 | G18: 1 | H18: January | I18: 1 | J18: 18.144643 | K18: =J18 -> 18.144643 | L18: 43.016572 | M18: =K18*L18 -> 780.52036 | N18: 0.52230161 | O18: =M18*N18 -> 407.66703 | P18: =M18-O18 -> 372.85332 | Q18: 46.794366 | R18: 9.3260607 | S18: =IF(E18=$AG$6,$S$2/5,$S$2/11) -> 12.987013 | T18: 31.99161 | U18: =M18*0.7 -> 546.36425 | V18: =U18/K18 -> 30.1116 | W18: 30.81582 | X18: =Q18/V18 -> 1.5540312 | Y18: =K18/W18 -> 0.58880936 | Z18: =O18/U18 -> 0.74614515 | AA18: =K18/V18 -> 0.60257984 | AB18: =S18/M18 -> 0.016638916 | AC18: =U18/K18 -> 30.1116 | AD18: =R18/L18 -> 0.21680158 | AE18: =Q18/M18 -> 0.059952782 | AF18: =IF(B18=$AF$6,$AF$5, "") | AG18: =IF(E18=$AG$6,$AG$5,"") | AH18: =IF(B18=$AH$6,$AH$5,"") | AI18: =IF(B18=$AI$6,$AI$5,"") | AJ18: =IF($B18=$AJ$6,$AJ$5,"") | AK18: =IF($B18=$AK$6,$AK$5,"") | AL18: =IF($B18=$AL$6,$AL$5,"") | AM18: =IF($B18=$AM$6,$AM$5,"") | AN18: =SUM(AF18:AM18) -> 0 | AO18: =P18-AN18 -> 372.85332
A19: 44573 | B19: 12 | C19: 12 | D19: 4 | E19: Wednesday | F19: 2 | G19: 1 | H19: January | I19: 1 | J19: 2.6356184 | K19: =J19 -> 2.6356184 | L19: 23.051269 | M19: =K19*L19 -> 60.754349 | N19: 0.52234832 | O19: =M19*N19 -> 31.734932 | P19: =M19-O19 -> 29.019417 | Q19: 29.957514 | R19: 3.9756458 | S19: =IF(E19=$AG$6,$S$2/5,$S$2/11) -> 12.987013 | T19: 28.772989 | U19: =M19*0.7 -> 42.528045 | V19: =U19/K19 -> 16.135889 | W19: 27.099146 | X19: =Q19/V19 -> 1.8565766 | Y19: =K19/W19 -> 0.097258354 | Z19: =O19/U19 -> 0.74621188 | AA19: =K19/V19 -> 0.1633389 | AB19: =S19/M19 -> 0.21376269 | AC19: =U19/K19 -> 16.135889 | AD19: =R19/L19 -> 0.17246971 | AE19: =Q19/M19 -> 0.4930925 | AF19: =IF(B19=$AF$6,$AF$5, "") | AG19: =IF(E19=$AG$6,$AG$5,"") | AH19: =IF(B19=$AH$6,$AH$5,"") | AI19: =IF(B19=$AI$6,$AI$5,"") | AJ19: =IF($B19=$AJ$6,$AJ$5,"") | AK19: =IF($B19=$AK$6,$AK$5,"") -> 480 | AL19: =IF($B19=$AL$6,$AL$5,"") | AM19: =IF($B19=$AM$6,$AM$5,"") | AN19: =SUM(AF19:AM19) -> 480 | AO19: =P19-AN19 -> -450.98058
A20: 44574 | B20: 13 | C20: 13 | D20: 5 | E20: Thursday | F20: 2 | G20: 1 | H20: January | I20: 1 | J20: 13.689948 | K20: =J20 -> 13.689948 | L20: 52.886584 | M20: =K20*L20 -> 724.0146 | N20: 0.45813765 | O20: =M20*N20 -> 331.69835 | P20: =M20-O20 -> 392.31625 | Q20: 30.053337 | R20: 9.9404558 | S20: =IF(E20=$AG$6,$S$2/5,$S$2/11) -> 12.987013 | T20: 25.193107 | U20: =M20*0.7 -> 506.81022 | V20: =U20/K20 -> 37.020609 | W20: 26.834492 | X20: =Q20/V20 -> 0.81180018 | Y20: =K20/W20 -> 0.51016239 | Z20: =O20/U20 -> 0.65448236 | AA20: =K20/V20 -> 0.36979263 | AB20: =S20/M20 -> 0.017937501 | AC20: =U20/K20 -> 37.020609 | AD20: =R20/L20 -> 0.18795799 | AE20: =Q20/M20 -> 0.041509297 | AF20: =IF(B20=$AF$6,$AF$5, "") | AG20: =IF(E20=$AG$6,$AG$5,"") | AH20: =IF(B20=$AH$6,$AH$5,"") | AI20: =IF(B20=$AI$6,$AI$5,"") | AJ20: =IF($B20=$AJ$6,$AJ$5,"") | AK20: =IF($B20=$AK$6,$AK$5,"") | AL20: =IF($B20=$AL$6,$AL$5,"") | AM20: =IF($B20=$AM$6,$AM$5,"") | AN20: =SUM(AF20:AM20) -> 0 | AO20: =P20-AN20 -> 392.31625
... A188: 44742 | B188: 30 | C188: 181 | D188: 5 | E188: Thursday | F188: 26 | G188: 6 | H188: June | I188: 2 | J188: 0.044856799 | K188: =J188 -> 0.044856799 | L188: 65.50402 | M188: =K188*L188 -> 2.9383007 | N188: 0.60744286 | O188: =M188*N188 -> 1.7848498 | P188: =M188-O188 -> 1.1534509 | Q188: 48.21422 | R188: 11.394534 | S188: =IF(E188=$AG$6,$S$2/5,$S$2/11) -> 12.987013 | T188: 30.836836 | U188: =M188*0.7 -> 2.0568105 | V188: =U188/K188 -> 45.852814 | W188: 31.055898 | X188: =Q188/V188 -> 1.0514997 | Y188: =K188/W188 -> 0.0014443891 | Z188: =O188/U188 -> 0.86777552 | AA188: =K188/V188 -> 0.00097827801 | AB188: =S188/M188 -> 4.4199061 | AC188: =U188/K188 -> 45.852814 | AD188: =R188/L188 -> 0.17395168 | AE188: =Q188/M188 -> 16.408879 | AF188: =IF(B188=$AF$6,$AF$5, "") | AG188: =IF(E188=$AG$6,$AG$5,"") | AH188: =IF(B188=$AH$6,$AH$5,"") | AI188: =IF(B188=$AI$6,$AI$5,"") | AJ188: =IF($B188=$AJ$6,$AJ$5,"") | AK188: =IF($B188=$AK$6,$AK$5,"") | AL188: =IF($B188=$AL$6,$AL$5,"") | AM188: =IF($B188=$AM$6,$AM$5,"") | AN188: =SUM(AF188:AM188) -> 0 | AO188: =P188-AN188 -> 1.1534509
A189: 44743 | B189: 1 | C189: 182 | D189: 6 | E189: Friday | F189: 26 | G189: 7 | H189: July | I189: 3 | J189: 4.0545139 | K189: =J189-(J189*0.4) -> 2.4327083 | L189: 105.67501 | M189: =K189*L189 -> 257.07647 | N189: 0.80253747 | O189: =M189*N189 -> 206.3135 | P189: =M189-O189 -> 50.762971 | Q189: 40.641381 | R189: 9.2642994 | S189: =IF(E189=$AG$6,$S$2/5,$S$2/11) -> 12.987013 | T189: 34.414125 | U189: =M189*0.7 -> 179.95353 | V189: =U189/K189 -> 73.972505 | W189: 33.975664 | X189: =Q189/V189 -> 0.549412 | Y189: =K189/W189 -> 0.071601495 | Z189: =O189/U189 -> 1.1464821 | AA189: =K189/V189 -> 0.032886657 | AB189: =S189/M189 -> 0.050518093 | AC189: =U189/K189 -> 73.972505 | AD189: =R189/L189 -> 0.087667838 | AE189: =Q189/M189 -> 0.15809063 | AF189: =IF(B189=$AF$6,$AF$5, "") -> 3000 | AG189: =IF(E189=$AG$6,$AG$4,"") | AH189: =IF(B189=$AH$6,$AH$5,"") | AI189: =IF(B189=$AI$6,$AI$5,"") | AJ189: =IF($B189=$AJ$6,$AJ$5,"") | AK189: =IF($B189=$AK$6,$AK$5,"") | AL189: =IF($B189=$AL$6,$AL$5,"") | AM189: =IF($B189=$AM$6,$AM$5,"") | AN189: =SUM(AF189:AM189) -> 3000 | AO189: =P189-AN189 -> -2949.237
A190: 44744 | B190: 2 | C190: 183 | D190: 7 | E190: Saturday | F190: 26 | G190: 7 | H190: July | I190: 3 | J190: 18.976672 | K190: =J190-(J190*0.4) -> 11.386003 | L190: 35.421114 | M190: =K190*L190 -> 403.30491 | N190: 0.76216217 | O190: =M190*N190 -> 307.38374 | P190: =M190-O190 -> 95.921165 | Q190: 25.683565 | R190: 16.448877 | S190: =IF(E190=$AG$6,$S$2/5,$S$2/11) -> 12.987013 | T190: 27.934224 | U190: =M190*0.7 -> 282.31344 | V190: =U190/K190 -> 24.79478 | W190: 34.638369 | X190: =Q190/V190 -> 1.0358457 | Y190: =K190/W190 -> 0.32871071 | Z190: =O190/U190 -> 1.0888031 | AA190: =K190/V190 -> 0.45920968 | AB190: =S190/M190 -> 0.032201475 | AC190: =U190/K190 -> 24.79478 | AD190: =R190/L190 -> 0.46438057 | AE190: =Q190/M190 -> 0.063682748 | AF190: =IF(B190=$AF$6,$AF$5, "") | AG190: =IF(E190=$AG$6,$AG$4,"") | AH190: =IF(B190=$AH$6,$AH$5,"") | AI190: =IF(B190=$AI$6,$AI$5,"") | AJ190: =IF($B190=$AJ$6,$AJ$5,"") | AK190: =IF($B190=$AK$6,$AK$5,"") | AL190: =IF($B190=$AL$6,$AL$5,"") | AM190: =IF($B190=$AM$6,$AM$5,"") | AN190: =SUM(AF190:AM190) -> 0 | AO190: =P190-AN190 -> 95.921165
A191: 44745 | B191: 3 | C191: 184 | D191: 1 | E191: Sunday | F191: 27 | G191: 7 | H191: July | I191: 3 | J191: 9.9977479 | K191: =J191-(J191*0.4) -> 5.9986487 | L191: 17.13847 | M191: =K191*L191 -> 102.80766 | N191: 0.23340149 | O191: =M191*N191 -> 23.995462 | P191: =M191-O191 -> 78.812201 | Q191: 20.541508 | R191: 4.7142395 | S191: =IF(E191=$AG$6,$S$2/5,$S$2/11) -> 28.571429 | T191: 15.42969 | U191: =M191*0.7 -> 71.965364 | V191: =U191/K191 -> 11.996929 | W191: 14.810839 | X191: =Q191/V191 -> 1.7122305 | Y191: =K191/W191 -> 0.40501748 | Z191: =O191/U191 -> 0.3334307 | AA191: =K191/V191 -> 0.50001535 | AB191: =S191/M191 -> 0.27791147 | AC191: =U191/K191 -> 11.996929 | AD191: =R191/L191 -> 0.2750677 | AE191: =Q191/M191 -> 0.19980522 | AF191: =IF(B191=$AF$6,$AF$5, "") | AG191: =IF(E191=$AG$6,$AG$4,"") -> 1200 | AH191: =IF(B191=$AH$6,$AH$5,"") | AI191: =IF(B191=$AI$6,$AI$5,"") | AJ191: =IF($B191=$AJ$6,$AJ$5,"") | AK191: =IF($B191=$AK$6,$AK$5,"") | AL191: =IF($B191=$AL$6,$AL$5,"") | AM191: =IF($B191=$AM$6,$AM$5,"") | AN191: =SUM(AF191:AM191) -> 1200 | AO191: =P191-AN191 -> -1121.1878
A192: 44746 | B192: 4 | C192: 185 | D192: 2 | E192: Monday | F192: 27 | G192: 7 | H192: July | I192: 3 | J192: 19.944189 | K192: =J192-(J192*0.4) -> 11.966513 | L192: 21.852919 | M192: =K192*L192 -> 261.50324 | N192: 0.48034182 | O192: =M192*N192 -> 125.61094 | P192: =M192-O192 -> 135.8923 | Q192: 32.155195 | R192: 17.240358 | S192: =IF(E192=$AG$6,$S$2/5,$S$2/11) -> 12.987013 | T192: 37.164164 | U192: =M192*0.7 -> 183.05227 | V192: =U192/K192 -> 15.297043 | W192: 30.627341 | X192: =Q192/V192 -> 2.102053 | Y192: =K192/W192 -> 0.39071343 | Z192: =O192/U192 -> 0.68620261 | AA192: =K192/V192 -> 0.78227624 | AB192: =S192/M192 -> 0.049662914 | AC192: =U192/K192 -> 15.297043 | AD192: =R192/L192 -> 0.78892702 | AE192: =Q192/M192 -> 0.12296289 | AF192: =IF(B192=$AF$6,$AF$5, "") | AG192: =IF(E192=$AG$6,$AG$4,"") | AH192: =IF(B192=$AH$6,$AH$5,"") | AI192: =IF(B192=$AI$6,$AI$5,"") | AJ192: =IF($B192=$AJ$6,$AJ$5,"") | AK192: =IF($B192=$AK$6,$AK$5,"") | AL192: =IF($B192=$AL$6,$AL$5,"") | AM192: =IF($B192=$AM$6,$AM$5,"") | AN192: =SUM(AF192:AM192) -> 0 | AO192: =P192-AN192 -> 135.8923
A193: 44747 | B193: 5 | C193: 186 | D193: 3 | E193: Tuesday | F193: 27 | G193: 7 | H193: July | I193: 3 | J193: 16.828051 | K193: =J193-(J193*0.4) -> 10.096831 | L193: 20.648431 | M193: =K193*L193 -> 208.48371 | N193: 0.58906921 | O193: =M193*N193 -> 122.81133 | P193: =M193-O193 -> 85.672377 | Q193: 37.107004 | R193: 9.9962125 | S193: =IF(E193=$AG$6,$S$2/5,$S$2/11) -> 12.987013 | T193: 33.724673 | U193: =M193*0.7 -> 145.9386 | V193: =U193/K193 -> 14.453902 | W193: 31.465115 | X193: =Q193/V193 -> 2.5672655 | Y193: =K193/W193 -> 0.32088967 | Z193: =O193/U193 -> 0.84152744 | AA193: =K193/V193 -> 0.69855397 | AB193: =S193/M193 -> 0.062292699 | AC193: =U193/K193 -> 14.453902 | AD193: =R193/L193 -> 0.48411486 | AE193: =Q193/M193 -> 0.17798515 | AF193: =IF(B193=$AF$6,$AF$5, "") | AG193: =IF(E193=$AG$6,$AG$4,"") | AH193: =IF(B193=$AH$6,$AH$5,"") | AI193: =IF(B193=$AI$6,$AI$5,"") | AJ193: =IF($B193=$AJ$6,$AJ$5,"") | AK193: =IF($B193=$AK$6,$AK$5,"") | AL193: =IF($B193=$AL$6,$AL$5,"") | AM193: =IF($B193=$AM$6,$AM$5,"") -> 1000 | AN193: =SUM(AF193:AM193) -> 1000 | AO193: =P193-AN193 -> -914.32762
A194: 44748 | B194: 6 | C194: 187 | D194: 4 | E194: Wednesday | F194: 27 | G194: 7 | H194: July | I194: 3 | J194: 19.05299 | K194: =J194-(J194*0.4) -> 11.431794 | L194: 44.407097 | M194: =K194*L194 -> 507.65278 | N194: 0.42174276 | O194: =M194*N194 -> 214.09888 | P194: =M194-O194 -> 293.55389 | Q194: 25.783515 | R194: 16.629988 | S194: =IF(E194=$AG$6,$S$2/5,$S$2/11) -> 12.987013 | T194: 34.088937 | U194: =M194*0.7 -> 355.35694 | V194: =U194/K194 -> 31.084968 | W194: 32.140353 | X194: =Q194/V194 -> 0.82945283 | Y194: =K194/W194 -> 0.35568351 | Z194: =O194/U194 -> 0.60248966 | AA194: =K194/V194 -> 0.36775954 | AB194: =S194/M194 -> 0.025582472 | AC194: =U194/K194 -> 31.084968 | AD194: =R194/L194 -> 0.37448941 | AE194: =Q194/M194 -> 0.050789666 | AF194: =IF(B194=$AF$6,$AF$5, "") | AG194: =IF(E194=$AG$6,$AG$4,"") | AH194: =IF(B194=$AH$6,$AH$5,"") | AI194: =IF(B194=$AI$6,$AI$5,"") | AJ194: =IF($B194=$AJ$6,$AJ$5,"") | AK194: =IF($B194=$AK$6,$AK$5,"") | AL194: =IF($B194=$AL$6,$AL$5,"") | AM194: =IF($B194=$AM$6,$AM$5,"") | AN194: =SUM(AF194:AM194) -> 0 | AO194: =P194-AN194 -> 293.55389
A195: 44749 | B195: 7 | C195: 188 | D195: 5 | E195: Thursday | F195: 27 | G195: 7 | H195: July | I195: 3 | J195: 12.477833 | K195: =J195-(J195*0.4) -> 7.4866996 | L195: 93.007825 | M195: =K195*L195 -> 696.32165 | N195: 0.42049524 | O195: =M195*N195 -> 292.79994 | P195: =M195-O195 -> 403.52171 | Q195: 21.694575 | R195: 9.4975664 | S195: =IF(E195=$AG$6,$S$2/5,$S$2/11) -> 12.987013 | T195: 30.181285 | U195: =M195*0.7 -> 487.42516 | V195: =U195/K195 -> 65.105478 | W195: 30.62018 | X195: =Q195/V195 -> 0.33322197 | Y195: =K195/W195 -> 0.24450214 | Z195: =O195/U195 -> 0.60070748 | AA195: =K195/V195 -> 0.11499339 | AB195: =S195/M195 -> 0.018650882 | AC195: =U195/K195 -> 65.105478 | AD195: =R195/L195 -> 0.10211578 | AE195: =Q195/M195 -> 0.031155968 | AF195: =IF(B195=$AF$6,$AF$5, "") | AG195: =IF(E195=$AG$6,$AG$4,"") | AH195: =IF(B195=$AH$6,$AH$5,"") | AI195: =IF(B195=$AI$6,$AI$5,"") | AJ195: =IF($B195=$AJ$6,$AJ$5,"") | AK195: =IF($B195=$AK$6,$AK$5,"") | AL195: =IF($B195=$AL$6,$AL$5,"") | AM195: =IF($B195=$AM$6,$AM$5,"") | AN195: =SUM(AF195:AM195) -> 0 | AO195: =P195-AN195 -> 403.52171
A196: 44750 | B196: 8 | C196: 189 | D196: 6 | E196: Friday | F196: 27 | G196: 7 | H196: July | I196: 3 | J196: 16.551072 | K196: =J196-(J196*0.4) -> 9.9306432 | L196: 41.39372 | M196: =K196*L196 -> 411.06626 | N196: 0.47791669 | O196: =M196*N196 -> 196.45543 | P196: =M196-O196 -> 214.61084 | Q196: 38.125293 | R196: 7.8890089 | S196: =IF(E196=$AG$6,$S$2/5,$S$2/11) -> 12.987013 | T196: 31.344059 | U196: =M196*0.7 -> 287.74638 | V196: =U196/K196 -> 28.975604 | W196: 31.472026 | X196: =Q196/V196 -> 1.3157722 | Y196: =K196/W196 -> 0.31553873 | Z196: =O196/U196 -> 0.68273813 | AA196: =K196/V196 -> 0.34272428 | AB196: =S196/M196 -> 0.031593478 | AC196: =U196/K196 -> 28.975604 | AD196: =R196/L196 -> 0.19058468 | AE196: =Q196/M196 -> 0.092747318 | AF196: =IF(B196=$AF$6,$AF$5, "") | AG196: =IF(E196=$AG$6,$AG$4,"") | AH196: =IF(B196=$AH$6,$AH$5,"") | AI196: =IF(B196=$AI$6,$AI$5,"") | AJ196: =IF($B196=$AJ$6,$AJ$5,"") | AK196: =IF($B196=$AK$6,$AK$5,"") | AL196: =IF($B196=$AL$6,$AL$5,"") | AM196: =IF($B196=$AM$6,$AM$5,"") | AN196: =SUM(AF196:AM196) -> 0 | AO196: =P196-AN196 -> 214.61084
A197: 44751 | B197: 9 | C197: 190 | D197: 7 | E197: Saturday | F197: 27 | G197: 7 | H197: July | I197: 3 | J197: 21.793727 | K197: =J197-(J197*0.4) -> 13.076236 | L197: 71.879688 | M197: =K197*L197 -> 939.9158 | N197: 0.46445394 | O197: =M197*N197 -> 436.5476 | P197: =M197-O197 -> 503.3682 | Q197: 34.234204 | R197: 13.573979 | S197: =IF(E197=$AG$6,$S$2/5,$S$2/11) -> 12.987013 | T197: 39.096523 | U197: =M197*0.7 -> 657.94106 | V197: =U197/K197 -> 50.315782 | W197: 35.465706 | X197: =Q197/V197 -> 0.68038701 | Y197: =K197/W197 -> 0.36870087 | Z197: =O197/U197 -> 0.66350563 | AA197: =K197/V197 -> 0.2598834 | AB197: =S197/M197 -> 0.013817209 | AC197: =U197/K197 -> 50.315782 | AD197: =R197/L197 -> 0.18884304 | AE197: =Q197/M197 -> 0.036422629 | AF197: =IF(B197=$AF$6,$AF$5, "") | AG197: =IF(E197=$AG$6,$AG$4,"") | AH197: =IF(B197=$AH$6,$AH$5,"") | AI197: =IF(B197=$AI$6,$AI$5,"") | AJ197: =IF($B197=$AJ$6,$AJ$5,"") | AK197: =IF($B197=$AK$6,$AK$5,"") | AL197: =IF($B197=$AL$6,$AL$5,"") | AM197: =IF($B197=$AM$6,$AM$5,"") | AN197: =SUM(AF197:AM197) -> 0 | AO197: =P197-AN197 -> 503.3682
A198: 44752 | B198: 10 | C198: 191 | D198: 1 | E198: Sunday | F198: 28 | G198: 7 | H198: July | I198: 3 | J198: 5.1235334 | K198: =J198-(J198*0.4) -> 3.07412 | L198: 32.947513 | M198: =K198*L198 -> 101.28461 | N198: 0.20584913 | O198: =M198*N198 -> 20.849348 | P198: =M198-O198 -> 80.435261 | Q198: 11.116791 | R198: 7.0516951 | S198: =IF(E198=$AG$6,$S$2/5,$S$2/11) -> 28.571429 | T198: 17.950794 | U198: =M198*0.7 -> 70.899226 | V198: =U198/K198 -> 23.063259 | W198: 14.501499 | X198: =Q198/V198 -> 0.48201301 | Y198: =K198/W198 -> 0.21198637 | Z198: =O198/U198 -> 0.29407018 | AA198: =K198/V198 -> 0.13329079 | AB198: =S198/M198 -> 0.28209053 | AC198: =U198/K198 -> 23.063259 | AD198: =R198/L198 -> 0.21402815 | AE198: =Q198/M198 -> 0.10975795 | AF198: =IF(B198=$AF$6,$AF$5, "") | AG198: =IF(E198=$AG$6,$AG$4,"") -> 1200 | AH198: =IF(B198=$AH$6,$AH$5,"") | AI198: =IF(B198=$AI$6,$AI$5,"") -> 300 | AJ198: =IF($B198=$AJ$6,$AJ$5,"") | AK198: =IF($B198=$AK$6,$AK$5,"") | AL198: =IF($B198=$AL$6,$AL$5,"") | AM198: =IF($B198=$AM$6,$AM$5,"") | AN198: =SUM(AF198:AM198) -> 1500 | AO198: =P198-AN198 -> -1419.5647
A199: 44753 | B199: 11 | C199: 192 | D199: 2 | E199: Monday | F199: 28 | G199: 7 | H199: July | I199: 3 | J199: 8.7242608 | K199: =J199-(J199*0.4) -> 5.2345565 | L199: 55.679012 | M199: =K199*L199 -> 291.45493 | N199: 0.32551442 | O199: =M199*N199 -> 94.872782 | P199: =M199-O199 -> 196.58215 | Q199: 27.145632 | R199: 9.9499067 | S199: =IF(E199=$AG$6,$S$2/5,$S$2/11) -> 12.987013 | T199: 37.995393 | U199: =M199*0.7 -> 204.01845 | V199: =U199/K199 -> 38.975308 | W199: 34.012136 | X199: =Q199/V199 -> 0.6964828 | Y199: =K199/W199 -> 0.15390261 | Z199: =O199/U199 -> 0.46502059 | AA199: =K199/V199 -> 0.13430443 | AB199: =S199/M199 -> 0.044559249 | AC199: =U199/K199 -> 38.975308 | AD199: =R199/L199 -> 0.17870121 | AE199: =Q199/M199 -> 0.093138351 | AF199: =IF(B199=$AF$6,$AF$5, "") | AG199: =IF(E199=$AG$6,$AG$4,"") | AH199: =IF(B199=$AH$6,$AH$5,"") | AI199: =IF(B199=$AI$6,$AI$5,"") | AJ199: =IF($B199=$AJ$6,$AJ$5,"") | AK199: =IF($B199=$AK$6,$AK$5,"") | AL199: =IF($B199=$AL$6,$AL$5,"") | AM199: =IF($B199=$AM$6,$AM$5,"") | AN199: =SUM(AF199:AM199) -> 0 | AO199: =P199-AN199 -> 196.58215
A200: 44754 | B200: 12 | C200: 193 | D200: 3 | E200: Tuesday | F200: 28 | G200: 7 | H200: July | I200: 3 | J200: 10.694837 | K200: =J200-(J200*0.4) -> 6.4169025 | L200: 45.707999 | M200: =K200*L200 -> 293.30377 | N200: 0.29130877 | O200: =M200*N200 -> 85.44196 | P200: =M200-O200 -> 207.86181 | Q200: 31.474616 | R200: 13.235238 | S200: =IF(E200=$AG$6,$S$2/5,$S$2/11) -> 12.987013 | T200: 34.803671 | U200: =M200*0.7 -> 205.31264 | V200: =U200/K200 -> 31.995599 | W200: 31.204391 | X200: =Q200/V200 -> 0.98371705 | Y200: =K200/W200 -> 0.20564101 | Z200: =O200/U200 -> 0.41615538 | AA200: =K200/V200 -> 0.20055578 | AB200: =S200/M200 -> 0.04427837 | AC200: =U200/K200 -> 31.995599 | AD200: =R200/L200 -> 0.28956066 | AE200: =Q200/M200 -> 0.10731064 | AF200: =IF(B200=$AF$6,$AF$5, "") | AG200: =IF(E200=$AG$6,$AG$4,"") | AH200: =IF(B200=$AH$6,$AH$5,"") | AI200: =IF(B200=$AI$6,$AI$5,"") | AJ200: =IF($B200=$AJ$6,$AJ$5,"") | AK200: =IF($B200=$AK$6,$AK$5,"") -> 480 | AL200: =IF($B200=$AL$6,$AL$5,"") | AM200: =IF($B200=$AM$6,$AM$5,"") | AN200: =SUM(AF200:AM200) -> 480 | AO200: =P200-AN200 -> -272.13819
... A311: 44865 | B311: 31 | C311: 304 | D311: 2 | E311: Monday | F311: 44 | G311: 10 | H311: October | I311: 4 | J311: 15.982317 | K311: =J311-(J311*0.4) -> 9.5893905 | L311: 11.460732 | M311: =K311*L311 -> 109.90143 | N311: 0.42645295 | O311: =M311*N311 -> 46.86779 | P311: =M311-O311 -> 63.033641 | Q311: 41.883827 | R311: 15.464948 | S311: =IF(E311=$AG$6,$S$2/5,$S$2/11) -> 12.987013 | T311: 38.385357 | U311: =M311*0.7 -> 76.931001 | V311: =U311/K311 -> 8.0225121 | W311: 30.334907 | X311: =Q311/V311 -> 5.220787 | Y311: =K311/W311 -> 0.31611736 | Z311: =O311/U311 -> 0.60921851 | AA311: =K311/V311 -> 1.1953102 | AB311: =S311/M311 -> 0.11816965 | AC311: =U311/K311 -> 8.0225121 | AD311: =R311/L311 -> 1.3493858 | AE311: =Q311/M311 -> 0.38110356 | AF311: =IF(B311=$AF$6,$AF$5, "") | AG311: =IF(E311=$AG$6,$AG$4,"") | AH311: =IF(B311=$AH$6,$AH$5,"") | AI311: =IF(B311=$AI$6,$AI$5,"") | AJ311: =IF($B311=$AJ$6,$AJ$5,"") | AK311: =IF($B311=$AK$6,$AK$5,"") | AL311: =IF($B311=$AL$6,$AL$5,"") | AM311: =IF($B311=$AM$6,$AM$5,"") | AN311: =SUM(AF311:AM311) -> 0 | AO311: =P311-AN311 -> 63.033641
A312: 44866 | B312: 1 | C312: 305 | D312: 3 | E312: Tuesday | F312: 44 | G312: 11 | H312: November | I312: 4 | J312: 6.1913023 | K312: =J312 -> 6.1913023 | L312: 16.547001 | M312: =K312*L312 -> 102.44749 | N312: 0.58002197 | O312: =M312*N312 -> 59.421794 | P312: =M312-O312 -> 43.025694 | Q312: 44.603086 | R312: 11.223545 | S312: =IF(E312=$AG$6,$S$2/5,$S$2/11) -> 12.987013 | T312: 42.477313 | U312: =M312*0.7 -> 71.713241 | V312: =U312/K312 -> 11.582901 | W312: 32.503545 | X312: =Q312/V312 -> 3.8507699 | Y312: =K312/W312 -> 0.19048083 | Z312: =O312/U312 -> 0.82860282 | AA312: =K312/V312 -> 0.53452088 | AB312: =S312/M312 -> 0.12676751 | AC312: =U312/K312 -> 11.582901 | AD312: =R312/L312 -> 0.67828271 | AE312: =Q312/M312 -> 0.43537511 | AF312: =IF(B312=$AF$6,$AF$5, "") -> 3000 | AG312: =IF(E312=$AG$6,$AG$5,"") | AH312: =IF(B312=$AH$6,$AH$5,"") | AI312: =IF(B312=$AI$6,$AI$5,"") | AJ312: =IF($B312=$AJ$6,$AJ$5,"") | AK312: =IF($B312=$AK$6,$AK$5,"") | AL312: =IF($B312=$AL$6,$AL$5,"") | AM312: =IF($B312=$AM$6,$AM$5,"") | AN312: =SUM(AF312:AM312) -> 3000 | AO312: =P312-AN312 -> -2956.9743
A313: 44867 | B313: 2 | C313: 306 | D313: 4 | E313: Wednesday | F313: 44 | G313: 11 | H313: November | I313: 4 | J313: 11.983626 | K313: =J313 -> 11.983626 | L313: 52.363679 | M313: =K313*L313 -> 627.50676 | N313: 0.35438747 | O313: =M313*N313 -> 222.38054 | P313: =M313-O313 -> 405.12623 | Q313: 33.183612 | R313: 14.393107 | S313: =IF(E313=$AG$6,$S$2/5,$S$2/11) -> 12.987013 | T313: 38.57731 | U313: =M313*0.7 -> 439.25473 | V313: =U313/K313 -> 36.654576 | W313: 34.800869 | X313: =Q313/V313 -> 0.90530614 | Y313: =K313/W313 -> 0.34434848 | Z313: =O313/U313 -> 0.50626782 | AA313: =K313/V313 -> 0.32693398 | AB313: =S313/M313 -> 0.020696212 | AC313: =U313/K313 -> 36.654576 | AD313: =R313/L313 -> 0.27486814 | AE313: =Q313/M313 -> 0.052881681 | AF313: =IF(B313=$AF$6,$AF$5, "") | AG313: =IF(E313=$AG$6,$AG$5,"") | AH313: =IF(B313=$AH$6,$AH$5,"") | AI313: =IF(B313=$AI$6,$AI$5,"") | AJ313: =IF($B313=$AJ$6,$AJ$5,"") | AK313: =IF($B313=$AK$6,$AK$5,"") | AL313: =IF($B313=$AL$6,$AL$5,"") | AM313: =IF($B313=$AM$6,$AM$5,"") | AN313: =SUM(AF313:AM313) -> 0 | AO313: =P313-AN313 -> 405.12623
A314: 44868 | B314: 3 | C314: 307 | D314: 5 | E314: Thursday | F314: 44 | G314: 11 | H314: November | I314: 4 | J314: 14.688992 | K314: =J314 -> 14.688992 | L314: 4.1646357 | M314: =K314*L314 -> 61.1743 | N314: 0.33357763 | O314: =M314*N314 -> 20.406378 | P314: =M314-O314 -> 40.767922 | Q314: 42.700667 | R314: 24.047043 | S314: =IF(E314=$AG$6,$S$2/5,$S$2/11) -> 12.987013 | T314: 33.909011 | U314: =M314*0.7 -> 42.82201 | V314: =U314/K314 -> 2.915245 | W314: 38.674198 | X314: =Q314/V314 -> 14.647368 | Y314: =K314/W314 -> 0.37981375 | Z314: =O314/U314 -> 0.47653947 | AA314: =K314/V314 -> 5.0386819 | AB314: =S314/M314 -> 0.21229524 | AC314: =U314/K314 -> 2.915245 | AD314: =R314/L314 -> 5.7741049 | AE314: =Q314/M314 -> 0.69801643 | AF314: =IF(B314=$AF$6,$AF$5, "") | AG314: =IF(E314=$AG$6,$AG$5,"") | AH314: =IF(B314=$AH$6,$AH$5,"") | AI314: =IF(B314=$AI$6,$AI$5,"") | AJ314: =IF($B314=$AJ$6,$AJ$5,"") | AK314: =IF($B314=$AK$6,$AK$5,"") | AL314: =IF($B314=$AL$6,$AL$5,"") | AM314: =IF($B314=$AM$6,$AM$5,"") | AN314: =SUM(AF314:AM314) -> 0 | AO314: =P314-AN314 -> 40.767922
A315: 44869 | B315: 4 | C315: 308 | D315: 6 | E315: Friday | F315: 44 | G315: 11 | H315: November | I315: 4 | J315: 7.8242128 | K315: =J315 -> 7.8242128 | L315: 58.471842 | M315: =K315*L315 -> 457.49613 | N315: 0.62937073 | O315: =M315*N315 -> 287.93468 | P315: =M315-O315 -> 169.56146 | Q315: 61.499204 | R315: 17.191403 | S315: =IF(E315=$AG$6,$S$2/5,$S$2/11) -> 12.987013 | T315: 33.422809 | U315: =M315*0.7 -> 320.24729 | V315: =U315/K315 -> 40.93029 | W315: 29.232855 | X315: =Q315/V315 -> 1.5025353 | Y315: =K315/W315 -> 0.26765134 | Z315: =O315/U315 -> 0.89910105 | AA315: =K315/V315 -> 0.19115948 | AB315: =S315/M315 -> 0.028387153 | AC315: =U315/K315 -> 40.93029 | AD315: =R315/L315 -> 0.29401165 | AE315: =Q315/M315 -> 0.13442563 | AF315: =IF(B315=$AF$6,$AF$5, "") | AG315: =IF(E315=$AG$6,$AG$5,"") | AH315: =IF(B315=$AH$6,$AH$5,"") | AI315: =IF(B315=$AI$6,$AI$5,"") | AJ315: =IF($B315=$AJ$6,$AJ$5,"") | AK315: =IF($B315=$AK$6,$AK$5,"") | AL315: =IF($B315=$AL$6,$AL$5,"") | AM315: =IF($B315=$AM$6,$AM$5,"") | AN315: =SUM(AF315:AM315) -> 0 | AO315: =P315-AN315 -> 169.56146
A316: 44870 | B316: 5 | C316: 309 | D316: 7 | E316: Saturday | F316: 44 | G316: 11 | H316: November | I316: 4 | J316: 20.930733 | K316: =J316 -> 20.930733 | L316: 78.712863 | M316: =K316*L316 -> 1647.5179 | N316: 0.21768976 | O316: =M316*N316 -> 358.64779 | P316: =M316-O316 -> 1288.8702 | Q316: 38.46991 | R316: 12.334262 | S316: =IF(E316=$AG$6,$S$2/5,$S$2/11) -> 12.987013 | T316: 30.088509 | U316: =M316*0.7 -> 1153.2626 | V316: =U316/K316 -> 55.099004 | W316: 38.647215 | X316: =Q316/V316 -> 0.69819611 | Y316: =K316/W316 -> 0.54158452 | Z316: =O316/U316 -> 0.31098538 | AA316: =K316/V316 -> 0.37987499 | AB316: =S316/M316 -> 0.0078827748 | AC316: =U316/K316 -> 55.099004 | AD316: =R316/L316 -> 0.15669945 | AE316: =Q316/M316 -> 0.023350222 | AF316: =IF(B316=$AF$6,$AF$5, "") | AG316: =IF(E316=$AG$6,$AG$5,"") | AH316: =IF(B316=$AH$6,$AH$5,"") | AI316: =IF(B316=$AI$6,$AI$5,"") | AJ316: =IF($B316=$AJ$6,$AJ$5,"") | AK316: =IF($B316=$AK$6,$AK$5,"") | AL316: =IF($B316=$AL$6,$AL$5,"") | AM316: =IF($B316=$AM$6,$AM$5,"") -> 1000 | AN316: =SUM(AF316:AM316) -> 1000 | AO316: =P316-AN316 -> 288.87016
A317: 44871 | B317: 6 | C317: 310 | D317: 1 | E317: Sunday | F317: 45 | G317: 11 | H317: November | I317: 4 | J317: 5.8985956 | K317: =J317 -> 5.8985956 | L317: 33.025235 | M317: =K317*L317 -> 194.8025 | N317: 0.18828496 | O317: =M317*N317 -> 36.678383 | P317: =M317-O317 -> 158.12412 | Q317: 17.189249 | R317: 6.1420344 | S317: =IF(E317=$AG$6,$S$2/5,$S$2/11) -> 28.571429 | T317: 16.356594 | U317: =M317*0.7 -> 136.36175 | V317: =U317/K317 -> 23.117664 | W317: 20.414774 | X317: =Q317/V317 -> 0.74355475 | Y317: =K317/W317 -> 0.28893758 | Z317: =O317/U317 -> 0.26897852 | AA317: =K317/V317 -> 0.25515534 | AB317: =S317/M317 -> 0.14666869 | AC317: =U317/K317 -> 23.117664 | AD317: =R317/L317 -> 0.18598004 | AE317: =Q317/M317 -> 0.088239364 | AF317: =IF(B317=$AF$6,$AF$5, "") | AG317: =IF(E317=$AG$6,$AG$5,"") -> 1000 | AH317: =IF(B317=$AH$6,$AH$5,"") | AI317: =IF(B317=$AI$6,$AI$5,"") | AJ317: =IF($B317=$AJ$6,$AJ$5,"") | AK317: =IF($B317=$AK$6,$AK$5,"") | AL317: =IF($B317=$AL$6,$AL$5,"") | AM317: =IF($B317=$AM$6,$AM$5,"") | AN317: =SUM(AF317:AM317) -> 1000 | AO317: =P317-AN317 -> -841.87588
A318: 44872 | B318: 7 | C318: 311 | D318: 2 | E318: Monday | F318: 45 | G318: 11 | H318: November | I318: 4 | J318: 12.041636 | K318: =J318 -> 12.041636 | L318: 38.770078 | M318: =K318*L318 -> 466.85517 | N318: 0.67973852 | O318: =M318*N318 -> 317.33944 | P318: =M318-O318 -> 149.51573 | Q318: 45.607349 | R318: 16.902003 | S318: =IF(E318=$AG$6,$S$2/5,$S$2/11) -> 12.987013 | T318: 35.654468 | U318: =M318*0.7 -> 326.79862 | V318: =U318/K318 -> 27.139054 | W318: 39.179893 | X318: =Q318/V318 -> 1.6805062 | Y318: =K318/W318 -> 0.30734224 | Z318: =O318/U318 -> 0.97105503 | AA318: =K318/V318 -> 0.44370139 | AB318: =S318/M318 -> 0.027818077 | AC318: =U318/K318 -> 27.139054 | AD318: =R318/L318 -> 0.43595485 | AE318: =Q318/M318 -> 0.097690573 | AF318: =IF(B318=$AF$6,$AF$5, "") | AG318: =IF(E318=$AG$6,$AG$5,"") | AH318: =IF(B318=$AH$6,$AH$5,"") | AI318: =IF(B318=$AI$6,$AI$5,"") | AJ318: =IF($B318=$AJ$6,$AJ$5,"") | AK318: =IF($B318=$AK$6,$AK$5,"") | AL318: =IF($B318=$AL$6,$AL$5,"") | AM318: =IF($B318=$AM$6,$AM$5,"") | AN318: =SUM(AF318:AM318) -> 0 | AO318: =P318-AN318 -> 149.51573
A319: 44873 | B319: 8 | C319: 312 | D319: 3 | E319: Tuesday | F319: 45 | G319: 11 | H319: November | I319: 4 | J319: 10.913286 | K319: =J319 -> 10.913286 | L319: 62.664642 | M319: =K319*L319 -> 683.87717 | N319: 0.45447725 | O319: =M319*N319 -> 310.80661 | P319: =M319-O319 -> 373.07055 | Q319: 43.248029 | R319: 14.424191 | S319: =IF(E319=$AG$6,$S$2/5,$S$2/11) -> 12.987013 | T319: 41.98235 | U319: =M319*0.7 -> 478.71402 | V319: =U319/K319 -> 43.86525 | W319: 30.870381 | X319: =Q319/V319 -> 0.98592916 | Y319: =K319/W319 -> 0.35351964 | Z319: =O319/U319 -> 0.64925321 | AA319: =K319/V319 -> 0.24879115 | AB319: =S319/M319 -> 0.018990271 | AC319: =U319/K319 -> 43.86525 | AD319: =R319/L319 -> 0.2301807 | AE319: =Q319/M319 -> 0.063239469 | AF319: =IF(B319=$AF$6,$AF$5, "") | AG319: =IF(E319=$AG$6,$AG$5,"") | AH319: =IF(B319=$AH$6,$AH$5,"") | AI319: =IF(B319=$AI$6,$AI$5,"") | AJ319: =IF($B319=$AJ$6,$AJ$5,"") | AK319: =IF($B319=$AK$6,$AK$5,"") | AL319: =IF($B319=$AL$6,$AL$5,"") | AM319: =IF($B319=$AM$6,$AM$5,"") | AN319: =SUM(AF319:AM319) -> 0 | AO319: =P319-AN319 -> 373.07055
A320: 44874 | B320: 9 | C320: 313 | D320: 4 | E320: Wednesday | F320: 45 | G320: 11 | H320: November | I320: 4 | J320: 17.706255 | K320: =J320 -> 17.706255 | L320: 10.097177 | M320: =K320*L320 -> 178.78318 | N320: 0.36098676 | O320: =M320*N320 -> 64.538361 | P320: =M320-O320 -> 114.24482 | Q320: 62.750197 | R320: 14.639252 | S320: =IF(E320=$AG$6,$S$2/5,$S$2/11) -> 12.987013 | T320: 37.254604 | U320: =M320*0.7 -> 125.14823 | V320: =U320/K320 -> 7.0680236 | W320: 34.152972 | X320: =Q320/V320 -> 8.8780402 | Y320: =K320/W320 -> 0.51843966 | Z320: =O320/U320 -> 0.51569536 | AA320: =K320/V320 -> 2.5051211 | AB320: =S320/M320 -> 0.072641133 | AC320: =U320/K320 -> 7.0680236 | AD320: =R320/L320 -> 1.4498362 | AE320: =Q320/M320 -> 0.3509849 | AF320: =IF(B320=$AF$6,$AF$5, "") | AG320: =IF(E320=$AG$6,$AG$5,"") | AH320: =IF(B320=$AH$6,$AH$5,"") | AI320: =IF(B320=$AI$6,$AI$5,"") | AJ320: =IF($B320=$AJ$6,$AJ$5,"") | AK320: =IF($B320=$AK$6,$AK$5,"") | AL320: =IF($B320=$AL$6,$AL$5,"") | AM320: =IF($B320=$AM$6,$AM$5,"") | AN320: =SUM(AF320:AM320) -> 0 | AO320: =P320-AN320 -> 114.24482
A321: 44875 | B321: 10 | C321: 314 | D321: 5 | E321: Thursday | F321: 45 | G321: 11 | H321: November | I321: 4 | J321: 20.12949 | K321: =J321 -> 20.12949 | L321: 61.738538 | M321: =K321*L321 -> 1242.7653 | N321: 0.36114061 | O321: =M321*N321 -> 448.81302 | P321: =M321-O321 -> 793.95229 | Q321: 57.580057 | R321: 13.535055 | S321: =IF(E321=$AG$6,$S$2/5,$S$2/11) -> 12.987013 | T321: 32.735471 | U321: =M321*0.7 -> 869.93572 | V321: =U321/K321 -> 43.216977 | W321: 36.632069 | X321: =Q321/V321 -> 1.3323481 | Y321: =K321/W321 -> 0.5495046 | Z321: =O321/U321 -> 0.51591515 | AA321: =K321/V321 -> 0.46577738 | AB321: =S321/M321 -> 0.010450093 | AC321: =U321/K321 -> 43.216977 | AD321: =R321/L321 -> 0.21923186 | AE321: =Q321/M321 -> 0.046332205 | AF321: =IF(B321=$AF$6,$AF$5, "") | AG321: =IF(E321=$AG$6,$AG$5,"") | AH321: =IF(B321=$AH$6,$AH$5,"") | AI321: =IF(B321=$AI$6,$AI$5,"") -> 300 | AJ321: =IF($B321=$AJ$6,$AJ$5,"") | AK321: =IF($B321=$AK$6,$AK$5,"") | AL321: =IF($B321=$AL$6,$AL$5,"") | AM321: =IF($B321=$AM$6,$AM$5,"") | AN321: =SUM(AF321:AM321) -> 300 | AO321: =P321-AN321 -> 493.95229
A322: 44876 | B322: 11 | C322: 315 | D322: 6 | E322: Friday | F322: 45 | G322: 11 | H322: November | I322: 4 | J322: 15.910808 | K322: =J322 -> 15.910808 | L322: 35.848952 | M322: =K322*L322 -> 570.38581 | N322: 0.73702376 | O322: =M322*N322 -> 420.38789 | P322: =M322-O322 -> 149.99792 | Q322: 40.05485 | R322: 16.102474 | S322: =IF(E322=$AG$6,$S$2/5,$S$2/11) -> 12.987013 | T322: 35.6585 | U322: =M322*0.7 -> 399.27007 | V322: =U322/K322 -> 25.094266 | W322: 38.941058 | X322: =Q322/V322 -> 1.5961754 | Y322: =K322/W322 -> 0.40858695 | Z322: =O322/U322 -> 1.0528911 | AA322: =K322/V322 -> 0.63404158 | AB322: =S322/M322 -> 0.022768822 | AC322: =U322/K322 -> 25.094266 | AD322: =R322/L322 -> 0.44917559 | AE322: =Q322/M322 -> 0.070224135 | AF322: =IF(B322=$AF$6,$AF$5, "") | AG322: =IF(E322=$AG$6,$AG$5,"") | AH322: =IF(B322=$AH$6,$AH$5,"") | AI322: =IF(B322=$AI$6,$AI$5,"") | AJ322: =IF($B322=$AJ$6,$AJ$5,"") | AK322: =IF($B322=$AK$6,$AK$5,"") | AL322: =IF($B322=$AL$6,$AL$5,"") | AM322: =IF($B322=$AM$6,$AM$5,"") | AN322: =SUM(AF322:AM322) -> 0 | AO322: =P322-AN322 -> 149.99792
A323: 44877 | B323: 12 | C323: 316 | D323: 7 | E323: Saturday | F323: 45 | G323: 11 | H323: November | I323: 4 | J323: 9.0040133 | K323: =J323 -> 9.0040133 | L323: 56.778052 | M323: =K323*L323 -> 511.23033 | N323: 0.44979652 | O323: =M323*N323 -> 229.94962 | P323: =M323-O323 -> 281.2807 | Q323: 36.921485 | R323: 14.758429 | S323: =IF(E323=$AG$6,$S$2/5,$S$2/11) -> 12.987013 | T323: 30.930552 | U323: =M323*0.7 -> 357.86123 | V323: =U323/K323 -> 39.744636 | W323: 33.062748 | X323: =Q323/V323 -> 0.92896775 | Y323: =K323/W323 -> 0.27233106 | Z323: =O323/U323 -> 0.64256646 | AA323: =K323/V323 -> 0.22654663 | AB323: =S323/M323 -> 0.025403448 | AC323: =U323/K323 -> 39.744636 | AD323: =R323/L323 -> 0.25993194 | AE323: =Q323/M323 -> 0.072220842 | AF323: =IF(B323=$AF$6,$AF$5, "") | AG323: =IF(E323=$AG$6,$AG$5,"") | AH323: =IF(B323=$AH$6,$AH$5,"") | AI323: =IF(B323=$AI$6,$AI$5,"") | AJ323: =IF($B323=$AJ$6,$AJ$5,"") | AK323: =IF($B323=$AK$6,$AK$5,"") -> 480 | AL323: =IF($B323=$AL$6,$AL$5,"") | AM323: =IF($B323=$AM$6,$AM$5,"") | AN323: =SUM(AF323:AM323) -> 480 | AO323: =P323-AN323 -> -198.7193
... A373: 44927 | B373: 1 | C373: 366 | D373: 1 | E373: Sunday | F373: 52 | G373: 1 | H373: January | I373: 4 | J373: 13.608697 | K373: =J373 -> 13.608697 | L373: 28.088597 | M373: =K373*L373 -> 382.24921 | N373: 0.17156509 | O373: =M373*N373 -> 65.58062 | P373: =M373-O373 -> 316.66859 | Q373: 28.984362 | R373: 5.6991993 | S373: =IF(E373=$AG$6,$S$2/5,$S$2/11) -> 28.571429 | T373: 15.912487 | U373: =M373*0.7 -> 267.57445 | V373: =U373/K373 -> 19.662018 | W373: 19.553897 | X373: =Q373/V373 -> 1.4741296 | Y373: =K373/W373 -> 0.69595831 | Z373: =O373/U373 -> 0.24509299 | AA373: =K373/V373 -> 0.69213126 | AB373: =S373/M373 -> 0.074745553 | AC373: =U373/K373 -> 19.662018 | AD373: =R373/L373 -> 0.20290082 | AE373: =Q373/M373 -> 0.075825825 | AF373: =IF(B373=$AF$6,$AF$5, "") -> 3000 | AG373: =IF(E373=$AG$6,$AG$5,"") -> 1000 | AH373: =IF(B373=$AH$6,$AH$5,"") | AI373: =IF(B373=$AI$6,$AI$5,"") | AJ373: =IF($B373=$AJ$6,$AJ$5,"") | AK373: =IF($B373=$AK$6,$AK$5,"") | AL373: =IF($B373=$AL$6,$AL$5,"") | AM373: =IF($B373=$AM$6,$AM$5,"") | AN373: =SUM(AF373:AM373) -> 4000 | AO373: =P373-AN373 -> -3683.3314

Sheet Assessment Sheet
B6: 1) What is the TOTAL ANNUAL REVENUE for YOUR company? | H6: =SUM('Landing Sheet'!L8:L373) -> 344165.43
B11: 2) Insert a PIVOT TABLE ON THE NEXT SHEET showing the Revenue (Rows), Months (Columns) with sum of revenue in each (Cell) for the FULL YEAR.
B12: hint: Start on landing sheet. Select all the data (A7:L373). Choose Insert, Pivot table. Select table on another sheet.
B18: 3) What are the Minimum and Maximum revenue days for the year? | H18: =MIN('Landing Sheet'!L8:L373) -> 2.9383007 | I18: Min
H19: =MAX('Landing Sheet'!L8:L373) -> 4486.4679 | I19: Max
B24: 4) Are these reasonable for this type of business? Why or Why not?
C25: (Do some research for comparable businesses) | G25: It is reasonable because big holidays like Valentine’s Day or Mother’s Day, or days with multiple weddings and deliveries, can create very high one-day sales even though this is rare.

Sheet Pivot Tabels
C2: Revenue | D2: COGS | E2: Expenses | F2: Profit
B3: 1 | C3: 89176.171 | D3: 62709.637 | E3: 28789 | F3: -2322.4657
B4: 2 | C4: 111070.91 | D4: 76825.003 | E4: 28789 | F4: 5456.9076
B5: 3 | C5: 70717.064 | D5: 39941.079 | E5: 28789 | F5: 1986.9854
B6: 4 | C6: 73201.284 | D6: 40776.311 | E6: 32789 | F6: -364.02706 | N6: 343.08564 | O6: 990.79813 | P6: 963.36134 | Q6: {=(O6+V12P6)-N6} -> #NAME?
N7: 516.5876 | O7: 1715.0874 | P7: 1655.7328 | Q7: =(O7+P7)-N7 -> 2854.2326
I8: Revenue | J8: COGS | K8: Expenses | L8: Profit | N8: 499.10944 | O8: 1115.2904 | P8: 1218.5043 | Q8: =(O8+P8)-N8 -> 1834.6853
H9: Sunday | I9: 11510.989 | J9: 3270.7092 | K9: 61846 | L9: -53605.72 | N9: 498.73459 | O9: 1316.8318 | P9: 1551.8399 | Q9: =(O9+P9)-N9 -> 2369.9372
H10: Monday | I10: 48750.96 | J10: 29615.429 | K10: 7126 | L10: 12009.531 | N10: 635.3752 | O10: 1883.9122 | P10: 1527.442 | Q10: =(O10+P10)-N10 -> 2775.979
H11: Tuesday | I11: 54117.248 | J11: 37733.905 | K11: 13526 | L11: 2857.3429 | N11: 399.82876 | O11: 927.34937 | P11: 1207.5764 | Q11: =(O11+P11)-N11 -> 1735.097 | T11: Sum of Online Orders | U11: Sum of Delevry orders | V11: In person
H12: Wednesday | I12: 58832.682 | J12: 37416.429 | K12: 6843 | L12: 14573.253 | N12: 400.89451 | O12: 972.20725 | P12: 1060.2492 | Q12: =(O12+P12)-N12 -> 1631.5619 | S12: January | T12: =O6+O6*0.2 -> 1188.9578 | U12: =P6+P6*0.4 -> 1348.7059 | V12: =((O6+P6)-N6) -> 1611.0738 | W12: =SUM(T12:V12) -> 4148.7375 | X12: =U12/W12 -> 0.32508827
H13: Thursday | I13: 56330.178 | J13: 36817.54 | K13: 9263 | L13: 10249.637 | N13: 492.83599 | O13: 992.76884 | P13: 1081.0229 | Q13: =(O13+P13)-N13 -> 1580.9558 | S13: February | T13: =O7+O7*2 -> 5145.2622 | U13: =P7+P7*4 -> 8278.6638 | V13: =((O7+P7)-N7) -> 2854.2326 | W13: =SUM(T13:V13) -> 16278.159 | X13: =U13/W13 -> 0.50857496
H14: Friday | I14: 60292.902 | J14: 43704.18 | K14: 8729 | L14: 7859.7222 | N14: 424.2872 | O14: 965.62184 | P14: 1173.8636 | Q14: =(O14+P14)-N14 -> 1715.1982 | S14: March | T14: =O8+O8*2 -> 3345.8713 | U14: =P8+P8*4 -> 6092.5214 | V14: =((O8+P8)-N8) -> 1834.6853 | W14: =SUM(T14:V14) -> 11273.078 | X14: =U14/W14 -> 0.54044879
H15: Saturday | I15: 54330.471 | J15: 31693.837 | K15: 11823 | L15: 10813.634 | N15: 394.54189 | O15: 1024.2256 | P15: 1038.6579 | Q15: =(O15+P15)-N15 -> 1668.3416 | S15: April | T15: =O9+O9*2 -> 3950.4955 | U15: =P9+P9*4 -> 7759.1995 | V15: =((O9+P9)-N9) -> 2369.9372 | W15: =SUM(T15:V15) -> 14079.632 | X15: =U15/W15 -> 0.55109391
N16: 431.16747 | O16: 1001.1211 | P16: 994.28155 | Q16: =(O16+P16)-N16 -> 1564.2352 | S16: May | T16: =O10+O10*2 -> 5651.7366 | U16: =P10+P10*4 -> 7637.2098 | V16: =((O10+P10)-N10) -> 2775.979 | W16: =SUM(T16:V16) -> 16064.925 | X16: =U16/W16 -> 0.47539653
N17: 471.11062 | O17: 1143.0161 | P17: 1366.4607 | Q17: =(O17+P17)-N17 -> 2038.3661 | S17: June | T17: =O11+O11*2 -> 2782.0481 | U17: =P11+P11*4 -> 6037.8821 | V17: =((O11+P11)-N11) -> 1735.097 | W17: =SUM(T17:V17) -> 10555.027 | X17: =U17/W17 -> 0.57203851
C18: Revenue | D18: COGS | E18: Expenses | F18: Profit | S18: July | T18: =O12+O12*2 -> 2916.6218 | U18: =P12+P12*4 -> 5301.2459 | V18: =((O12+P12)-N12) -> 1631.5619 | W18: =SUM(T18:V18) -> 9849.4296 | X18: =U18/W18 -> 0.53822872
B19: January | C19: 16247.761 | D19: 5948.9178 | E19: 14263 | F19: -3964.1563 | S19: August | T19: =O13+O13*2 -> 2978.3065 | U19: =P13+P13*4 -> 5405.1147 | V19: =((O13+P13)-N13) -> 1580.9558 | W19: =SUM(T19:V19) -> 9964.3771 | X19: =U19/W19 -> 0.54244382
B20: February | C20: 43837.899 | D20: 35489.505 | E20: 9263 | F20: -914.60605 | S20: September | T20: =O14+O14*2 -> 2896.8655 | U20: =P14+P14*4 -> 5869.3178 | V20: =((O14+P14)-N14) -> 1715.1982 | W20: =SUM(T20:V20) -> 10481.382 | X20: =U20/W20 -> 0.55997559
B21: March | C21: 29472.76 | D21: 21336.794 | E21: 9263 | F21: -1127.0348 | S21: October | T21: =O15+O15*2 -> 3072.6768 | U21: =P15+P15*4 -> 5193.2893 | V21: =((O15+P15)-N15) -> 1668.3416 | W21: =SUM(T21:V21) -> 9934.3076 | X21: =U21/W21 -> 0.52276309
B22: April | C22: 38584.252 | D22: 27425.11 | E22: 9263 | F22: 1896.1427 | S22: November | T22: =O16+O16*2 -> 3003.3634 | U22: =P16+P16*4 -> 4971.4077 | V22: =((O16+P16)-N16) -> 1564.2352 | W22: =SUM(T22:V22) -> 9539.0064 | X22: =U22/W22 -> 0.5211662
B23: May | C23: 48394.143 | D23: 34429.177 | E23: 10263 | F23: 3701.9662 | K23: Values | S23: December | T23: 1143.0161 | U23: 1366.4607 | V23: =((O17+P17)-N17) -> 2038.3661 | W23: =SUM(T23:V23) -> 4547.8429 | X23: =U23/W23 -> 0.30046348
B24: June | C24: 24092.516 | D24: 14970.717 | E24: 9263 | F24: -141.20126 | K24: Sum of Total Revenue | L24: 344165.43
B25: July | C25: 20031.092 | D25: 10047.918 | E25: 10263 | F25: -279.82559 | K25: Sum of COGS | L25: 220252.03 | O25: Row Labels | P25: Average of Total Expenses | Q25: Average of Total Revenue
B26: August | C26: 26613.425 | D26: 14972.999 | E26: 9263 | F26: 2377.426 | K26: Sum of Rent / Lease | L26: 39000 | O26: January | P26: 445.71875 | Q26: 507.74255 | X26: =AVERAGE(X12:X23) -> 0.49647349
B27: September | C27: 24072.547 | D27: 14920.162 | E27: 9263 | F27: -110.615 | K27: Sum of Wages and Salaries | L27: 53000 | O27: February | P27: 330.82143 | Q27: 1565.6393
B28: October | C28: 20471.916 | D28: 10508.265 | E28: 10263 | F28: -299.34935 | K28: Sum of Insurance | L28: 3600 | O28: March | P28: 298.80645 | Q28: 950.73418
B29: November | C29: 21162.034 | D29: 10722.433 | E29: 9263 | F29: 1176.6015 | K29: Sum of Water | L29: 1200 | O29: April | P29: 308.76667 | Q29: 1286.1417
B30: December | C30: 31185.085 | D30: 19480.033 | E30: 9263 | F30: 2442.0522 | K30: Sum of Phone | L30: 5760 | O30: May | P30: 331.06452 | Q30: 1561.1014
K31: Sum of Electric | L31: 3600 | O31: June | P31: 308.76667 | Q31: 803.08385
K32: Sum of Internet | L32: 996 | O32: July | P32: 331.06452 | Q32: 646.16426
K33: Sum of Delivery | L33: 12000 | O33: August | P33: 298.80645 | Q33: 858.49758 | T33: Revenue | U33: 344165.43
K34: Sum of Profit | L34: 4757.4002 | O34: September | P34: 308.76667 | Q34: 802.41824 | T34: COGS | U34: -220252.03
O35: October | P35: 331.06452 | Q35: 660.38438 | T35: Rent / Lease | U35: -39000
O36: November | P36: 308.76667 | Q36: 705.40114 | T36: Wages | U36: -53000
O37: December | P37: 298.80645 | Q37: 1005.9705 | T37: Insurance | U37: -3600
O38: Grand Total | P38: 325.56284 | Q38: 940.34271 | T38: Water | U38: -1200
T39: Phone | U39: -5760
T40: Electric | U40: -3600
T41: Internet | U41: -996
A42: Month | B42: Profit | C42: Loss | T42: Delivery | U42: -12000
A43: Jan | C43: -3964 | T43: Profit | U43: 4757.4002
A44: Feb | C44: -915
A45: Mar | C45: -1127
A46: Apr | B46: 1896
A47: May | B47: 3702 | I47: Stems Wasted per week | P47: Gross Margin | Q47: OverHead Cost
A48: Jun | C48: -141 | H48: Sunday | I48: 16.821969 | O48: January | P48: 10298.844 | Q48: 14263
A49: Jul | C49: -280 | H49: Monday | I49: 17.704307 | O49: February | P49: 8348.3939 | Q49: 9263
A50: Aug | B50: 2377 | H50: Tuesday | I50: 16.166173 | O50: March | P50: 8135.9652 | Q50: 9263
A51: Sep | C51: -111 | H51: Wednesday | I51: 17.539404 | O51: April | P51: 11159.143 | Q51: 9263
A52: Oct | C52: -299 | H52: Thursday | I52: 21.73776 | O52: May | P52: 13964.966 | Q52: 10263
A53: Nov | B53: 1177 | H53: Friday | I53: 32.377989 | O53: June | P53: 9121.7987 | Q53: 9263
A54: Dec | B54: 2442 | H54: Saturday | I54: 24.38147 | O54: July | P54: 9983.1744 | Q54: 10263
O55: August | P55: 11640.426 | Q55: 9263
O56: September | P56: 9152.385 | Q56: 9263
O57: October | P57: 9963.6507 | Q57: 10263
O58: November | P58: 10439.601 | Q58: 9263
O59: December | P59: 11705.052 | Q59: 9263

Sheet P&L
D4: Values | E4: January | F4: February | G4: March | H4: April | I4: May | J4: June | K4: July | L4: August | M4: September | N4: October | O4: November | P4: December | Q4: Year Total
D5: Total Revenue | E5: =SUMIF('Landing Sheet'!$H$8:$H$373, E$4, 'Landing Sheet'!$L$8:$L$373) -> 16247.761 | F5: =SUMIF('Landing Sheet'!$H$8:$H$373, F$4, 'Landing Sheet'!$L$8:$L$373) -> 43837.899 | G5: =SUMIF('Landing Sheet'!$H$8:$H$373, G$4, 'Landing Sheet'!$L$8:$L$373) -> 29472.76 | H5: =SUMIF('Landing Sheet'!$H$8:$H$373, H$4, 'Landing Sheet'!$L$8:$L$373) -> 38584.252 | I5: =SUMIF('Landing Sheet'!$H$8:$H$373, I$4, 'Landing Sheet'!$L$8:$L$373) -> 48394.143 | J5: =SUMIF('Landing Sheet'!$H$8:$H$373, J$4, 'Landing Sheet'!$L$8:$L$373) -> 24092.516 | K5: =SUMIF('Landing Sheet'!$H$8:$H$373, K$4, 'Landing Sheet'!$L$8:$L$373) -> 20031.092 | L5: =SUMIF('Landing Sheet'!$H$8:$H$373, L$4, 'Landing Sheet'!$L$8:$L$373) -> 26613.425 | ... P5: =SUMIF('Landing Sheet'!$H$8:$H$373, P$4, 'Landing Sheet'!$L$8:$L$373) -> 31185.085 | Q5: =SUM(E5:P5) -> 344165.43
D6: COGS | E6: =SUMIF('Landing Sheet'!$H$8:$H$373, E$4, 'Landing Sheet'!$N$8:$N$373) -> 5948.9178 | F6: =SUMIF('Landing Sheet'!$H$8:$H$373, F$4, 'Landing Sheet'!$N$8:$N$373) -> 35489.505 | G6: =SUMIF('Landing Sheet'!$H$8:$H$373, G$4, 'Landing Sheet'!$N$8:$N$373) -> 21336.794 | H6: =SUMIF('Landing Sheet'!$H$8:$H$373, H$4, 'Landing Sheet'!$N$8:$N$373) -> 27425.11 | I6: =SUMIF('Landing Sheet'!$H$8:$H$373, I$4, 'Landing Sheet'!$N$8:$N$373) -> 34429.177 | J6: =SUMIF('Landing Sheet'!$H$8:$H$373, J$4, 'Landing Sheet'!$N$8:$N$373) -> 14970.717 | K6: =SUMIF('Landing Sheet'!$H$8:$H$373, K$4, 'Landing Sheet'!$N$8:$N$373) -> 10047.918 | L6: =SUMIF('Landing Sheet'!$H$8:$H$373, L$4, 'Landing Sheet'!$N$8:$N$373) -> 14972.999 | ... P6: =SUMIF('Landing Sheet'!$H$8:$H$373, P$4, 'Landing Sheet'!$N$8:$N$373) -> 19480.033 | Q6: =SUM(E6:P6) -> 220252.03
D7: Gross Margin | E7: =E5-E6 -> 10298.844 | F7: =F5-F6 -> 8348.3939 | G7: =G5-G6 -> 8135.9652 | H7: =H5-H6 -> 11159.143 | I7: =I5-I6 -> 13964.966 | J7: =J5-J6 -> 9121.7987 | K7: =K5-K6 -> 9983.1744 | L7: =L5-L6 -> 11640.426 | ... P7: =P5-P6 -> 11705.052 | Q7: =SUM(E7:P7) -> 123913.4
D9: Rent/Lease | E9: =SUMIF('Landing Sheet'!$H$8:$H$373, E$4, 'Landing Sheet'!$AE$8:$AE$373) -> 6000 | F9: =SUMIF('Landing Sheet'!$H$8:$H$373, F$4, 'Landing Sheet'!$AE$8:$AE$373) -> 3000 | G9: =SUMIF('Landing Sheet'!$H$8:$H$373, G$4, 'Landing Sheet'!$AE$8:$AE$373) -> 3000 | H9: =SUMIF('Landing Sheet'!$H$8:$H$373, H$4, 'Landing Sheet'!$AE$8:$AE$373) -> 3000 | I9: =SUMIF('Landing Sheet'!$H$8:$H$373, I$4, 'Landing Sheet'!$AE$8:$AE$373) -> 3000 | J9: =SUMIF('Landing Sheet'!$H$8:$H$373, J$4, 'Landing Sheet'!$AE$8:$AE$373) -> 3000 | K9: =SUMIF('Landing Sheet'!$H$8:$H$373, K$4, 'Landing Sheet'!$AE$8:$AE$373) -> 3000 | L9: =SUMIF('Landing Sheet'!$H$8:$H$373, L$4, 'Landing Sheet'!$AE$8:$AE$373) -> 3000 | ... P9: =SUMIF('Landing Sheet'!$H$8:$H$373, P$4, 'Landing Sheet'!$AE$8:$AE$373) -> 3000 | Q9: =SUM(E9:P9) -> 39000
D10: Wages | E10: =SUMIF('Landing Sheet'!$H$8:$H$373, E$4, 'Landing Sheet'!$AF$8:$AF$373) -> 6000 | F10: =SUMIF('Landing Sheet'!$H$8:$H$373, F$4, 'Landing Sheet'!$AF$8:$AF$373) -> 4000 | G10: =SUMIF('Landing Sheet'!$H$8:$H$373, G$4, 'Landing Sheet'!$AF$8:$AF$373) -> 4000 | H10: =SUMIF('Landing Sheet'!$H$8:$H$373, H$4, 'Landing Sheet'!$AF$8:$AF$373) -> 4000 | I10: =SUMIF('Landing Sheet'!$H$8:$H$373, I$4, 'Landing Sheet'!$AF$8:$AF$373) -> 5000 | J10: =SUMIF('Landing Sheet'!$H$8:$H$373, J$4, 'Landing Sheet'!$AF$8:$AF$373) -> 4000 | K10: =SUMIF('Landing Sheet'!$H$8:$H$373, K$4, 'Landing Sheet'!$AF$8:$AF$373) -> 5000 | L10: =SUMIF('Landing Sheet'!$H$8:$H$373, L$4, 'Landing Sheet'!$AF$8:$AF$373) -> 4000 | ... P10: =SUMIF('Landing Sheet'!$H$8:$H$373, P$4, 'Landing Sheet'!$AF$8:$AF$373) -> 4000 | Q10: =SUM(E10:P10) -> 53000
D11: Insurance | E11: =SUMIF('Landing Sheet'!$H$8:$H$373, E$4, 'Landing Sheet'!$AG$8:$AG$373) -> 300 | F11: =SUMIF('Landing Sheet'!$H$8:$H$373, F$4, 'Landing Sheet'!$AG$8:$AG$373) -> 300 | G11: =SUMIF('Landing Sheet'!$H$8:$H$373, G$4, 'Landing Sheet'!$AG$8:$AG$373) -> 300 | H11: =SUMIF('Landing Sheet'!$H$8:$H$373, H$4, 'Landing Sheet'!$AG$8:$AG$373) -> 300 | I11: =SUMIF('Landing Sheet'!$H$8:$H$373, I$4, 'Landing Sheet'!$AG$8:$AG$373) -> 300 | J11: =SUMIF('Landing Sheet'!$H$8:$H$373, J$4, 'Landing Sheet'!$AG$8:$AG$373) -> 300 | K11: =SUMIF('Landing Sheet'!$H$8:$H$373, K$4, 'Landing Sheet'!$AG$8:$AG$373) -> 300 | L11: =SUMIF('Landing Sheet'!$H$8:$H$373, L$4, 'Landing Sheet'!$AG$8:$AG$373) -> 300 | ... P11: =SUMIF('Landing Sheet'!$H$8:$H$373, P$4, 'Landing Sheet'!$AG$8:$AG$373) -> 300 | Q11: =SUM(E11:P11) -> 3600
D12: Electric | E12: =SUMIF('Landing Sheet'!$H$8:$H$373, E$4, 'Landing Sheet'!$AH$8:$AH$373) -> 300 | F12: =SUMIF('Landing Sheet'!$H$8:$H$373, F$4, 'Landing Sheet'!$AH$8:$AH$373) -> 300 | G12: =SUMIF('Landing Sheet'!$H$8:$H$373, G$4, 'Landing Sheet'!$AH$8:$AH$373) -> 300 | H12: =SUMIF('Landing Sheet'!$H$8:$H$373, H$4, 'Landing Sheet'!$AH$8:$AH$373) -> 300 | I12: =SUMIF('Landing Sheet'!$H$8:$H$373, I$4, 'Landing Sheet'!$AH$8:$AH$373) -> 300 | J12: =SUMIF('Landing Sheet'!$H$8:$H$373, J$4, 'Landing Sheet'!$AH$8:$AH$373) -> 300 | K12: =SUMIF('Landing Sheet'!$H$8:$H$373, K$4, 'Landing Sheet'!$AH$8:$AH$373) -> 300 | L12: =SUMIF('Landing Sheet'!$H$8:$H$373, L$4, 'Landing Sheet'!$AH$8:$AH$373) -> 300 | ... P12: =SUMIF('Landing Sheet'!$H$8:$H$373, P$4, 'Landing Sheet'!$AH$8:$AH$373) -> 300 | Q12: =SUM(E12:P12) -> 3600
D13: Water | E13: =SUMIF('Landing Sheet'!$H$8:$H$373, E$4, 'Landing Sheet'!$AI$8:$AI$373) -> 100 | F13: =SUMIF('Landing Sheet'!$H$8:$H$373, F$4, 'Landing Sheet'!$AI$8:$AI$373) -> 100 | G13: =SUMIF('Landing Sheet'!$H$8:$H$373, G$4, 'Landing Sheet'!$AI$8:$AI$373) -> 100 | H13: =SUMIF('Landing Sheet'!$H$8:$H$373, H$4, 'Landing Sheet'!$AI$8:$AI$373) -> 100 | I13: =SUMIF('Landing Sheet'!$H$8:$H$373, I$4, 'Landing Sheet'!$AI$8:$AI$373) -> 100 | J13: =SUMIF('Landing Sheet'!$H$8:$H$373, J$4, 'Landing Sheet'!$AI$8:$AI$373) -> 100 | K13: =SUMIF('Landing Sheet'!$H$8:$H$373, K$4, 'Landing Sheet'!$AI$8:$AI$373) -> 100 | L13: =SUMIF('Landing Sheet'!$H$8:$H$373, L$4, 'Landing Sheet'!$AI$8:$AI$373) -> 100 | ... P13: =SUMIF('Landing Sheet'!$H$8:$H$373, P$4, 'Landing Sheet'!$AI$8:$AI$373) -> 100 | Q13: =SUM(E13:P13) -> 1200
D14: Gas | E14: =SUMIF('Landing Sheet'!$H$8:$H$373, E$4, 'Landing Sheet'!$AJ$8:$AJ$373) -> 480 | F14: =SUMIF('Landing Sheet'!$H$8:$H$373, F$4, 'Landing Sheet'!$AJ$8:$AJ$373) -> 480 | G14: =SUMIF('Landing Sheet'!$H$8:$H$373, G$4, 'Landing Sheet'!$AJ$8:$AJ$373) -> 480 | H14: =SUMIF('Landing Sheet'!$H$8:$H$373, H$4, 'Landing Sheet'!$AJ$8:$AJ$373) -> 480 | I14: =SUMIF('Landing Sheet'!$H$8:$H$373, I$4, 'Landing Sheet'!$AJ$8:$AJ$373) -> 480 | J14: =SUMIF('Landing Sheet'!$H$8:$H$373, J$4, 'Landing Sheet'!$AJ$8:$AJ$373) -> 480 | K14: =SUMIF('Landing Sheet'!$H$8:$H$373, K$4, 'Landing Sheet'!$AJ$8:$AJ$373) -> 480 | L14: =SUMIF('Landing Sheet'!$H$8:$H$373, L$4, 'Landing Sheet'!$AJ$8:$AJ$373) -> 480 | ... P14: =SUMIF('Landing Sheet'!$H$8:$H$373, P$4, 'Landing Sheet'!$AJ$8:$AJ$373) -> 480 | Q14: =SUM(E14:P14) -> 5760
D15: Internet | E15: =SUMIF('Landing Sheet'!$H$8:$H$373, E$4, 'Landing Sheet'!$AK$8:$AK$373) -> 83 | F15: =SUMIF('Landing Sheet'!$H$8:$H$373, F$4, 'Landing Sheet'!$AK$8:$AK$373) -> 83 | G15: =SUMIF('Landing Sheet'!$H$8:$H$373, G$4, 'Landing Sheet'!$AK$8:$AK$373) -> 83 | H15: =SUMIF('Landing Sheet'!$H$8:$H$373, H$4, 'Landing Sheet'!$AK$8:$AK$373) -> 83 | I15: =SUMIF('Landing Sheet'!$H$8:$H$373, I$4, 'Landing Sheet'!$AK$8:$AK$373) -> 83 | J15: =SUMIF('Landing Sheet'!$H$8:$H$373, J$4, 'Landing Sheet'!$AK$8:$AK$373) -> 83 | K15: =SUMIF('Landing Sheet'!$H$8:$H$373, K$4, 'Landing Sheet'!$AK$8:$AK$373) -> 83 | L15: =SUMIF('Landing Sheet'!$H$8:$H$373, L$4, 'Landing Sheet'!$AK$8:$AK$373) -> 83 | ... P15: =SUMIF('Landing Sheet'!$H$8:$H$373, P$4, 'Landing Sheet'!$AK$8:$AK$373) -> 83 | Q15: =SUM(E15:P15) -> 996
D16: Advertising | E16: =SUMIF('Landing Sheet'!$H$8:$H$373, E$4, 'Landing Sheet'!$AL$8:$AL$373) -> 1000 | F16: =SUMIF('Landing Sheet'!$H$8:$H$373, F$4, 'Landing Sheet'!$AL$8:$AL$373) -> 1000 | G16: =SUMIF('Landing Sheet'!$H$8:$H$373, G$4, 'Landing Sheet'!$AL$8:$AL$373) -> 1000 | H16: =SUMIF('Landing Sheet'!$H$8:$H$373, H$4, 'Landing Sheet'!$AL$8:$AL$373) -> 1000 | I16: =SUMIF('Landing Sheet'!$H$8:$H$373, I$4, 'Landing Sheet'!$AL$8:$AL$373) -> 1000 | J16: =SUMIF('Landing Sheet'!$H$8:$H$373, J$4, 'Landing Sheet'!$AL$8:$AL$373) -> 1000 | K16: =SUMIF('Landing Sheet'!$H$8:$H$373, K$4, 'Landing Sheet'!$AL$8:$AL$373) -> 1000 | L16: =SUMIF('Landing Sheet'!$H$8:$H$373, L$4, 'Landing Sheet'!$AL$8:$AL$373) -> 1000 | ... P16: =SUMIF('Landing Sheet'!$H$8:$H$373, P$4, 'Landing Sheet'!$AL$8:$AL$373) -> 1000 | Q16: =SUM(E16:P16) -> 12000
D18: Total Expenses | E18: =SUM(E9:E16) -> 14263 | F18: =SUM(F9:F16) -> 9263 | G18: =SUM(G9:G16) -> 9263 | H18: =SUM(H9:H16) -> 9263 | I18: =SUM(I9:I16) -> 10263 | J18: =SUM(J9:J16) -> 9263 | K18: =SUM(K9:K16) -> 10263 | L18: =SUM(L9:L16) -> 9263 | ... Q18: =SUM(Q9:Q16) -> 119156
D20: Net Proffit | E20: =E7-E18 -> -3964.1563 | F20: =F7-F18 -> -914.60605 | G20: =G7-G18 -> -1127.0348 | H20: =H7-H18 -> 1896.1427 | I20: =I7-I18 -> 3701.9662 | J20: =J7-J18 -> -141.20126 | K20: =K7-K18 -> -279.82559 | L20: =L7-L18 -> 2377.426 | ... Q20: =Q7-Q18 -> 4757.4002

Sheet Sheet1
B7: Values | C7: Jan | D7: Feb | E7: Mar | F7: Apr | G7: May | H7: Jun | I7: Jul | J7: Aug | K7: Sep | L7: Oct | M7: Nov | N7: Dec | O7: Total
B8: Total Revenue | C8: 16247.761 | D8: 49837.899 | E8: 29472.76 | F8: 38584.252 | G8: 48394.143 | H8: 24092.516 | I8: 20031.092 | J8: 26613.425 | K8: 24072.547 | L8: 20471.916 | M8: 21162.034 | N8: 31185.085 | O8: 344165.43
B9: COGS | C9: 5948.9178 | D9: 35489.505 | E9: 21336.794 | F9: 27425.11 | G9: 34429.177 | H9: 14970.717 | I9: 10047.918 | J9: 14972.999 | K9: 14920.162 | L9: 10508.265 | M9: 10722.433 | N9: 19480.033 | O9: 220252.03
B10: Gross Margin | C10: 10298.844 | D10: =D8-D9 -> 14348.394 | E10: 8135.9652 | F10: 11159.143 | G10: 13964.966 | H10: 9121.7987 | I10: 9983.1744 | J10: 11640.426 | K10: 9152.385 | L10: 9963.6507 | M10: 10439.601 | N10: 11705.052 | O10: 123913.4
B12: Rent/Lease | C12: 6000 | D12: 3000 | E12: 3000 | F12: 3000 | G12: 3000 | H12: 3000 | I12: 3000 | J12: 3000 | K12: 3000 | L12: 3000 | M12: 3000 | N12: 3000 | O12: 39000
B13: Wages | C13: 6000 | D13: 4000 | E13: 4000 | F13: 4000 | G13: 5000 | H13: 4000 | I13: 5000 | J13: 4000 | K13: 4000 | L13: 5000 | M13: 4000 | N13: 4000 | O13: 53000
B14: Insurance | C14: 300 | D14: 300 | E14: 300 | F14: 300 | G14: 300 | H14: 300 | I14: 300 | J14: 300 | K14: 300 | L14: 300 | M14: 300 | N14: 300 | O14: 3600
B15: Electric | C15: 300 | D15: 300 | E15: 300 | F15: 300 | G15: 300 | H15: 300 | I15: 300 | J15: 300 | K15: 300 | L15: 300 | M15: 300 | N15: 300 | O15: 3600
B16: Water | C16: 100 | D16: 100 | E16: 100 | F16: 100 | G16: 100 | H16: 100 | I16: 100 | J16: 100 | K16: 100 | L16: 100 | M16: 100 | N16: 100 | O16: 1200
B17: Gas | C17: 480 | D17: 480 | E17: 480 | F17: 480 | G17: 480 | H17: 480 | I17: 480 | J17: 480 | K17: 480 | L17: 480 | M17: 480 | N17: 480 | O17: 5760
B18: Internet | C18: 83 | D18: 83 | E18: 83 | F18: 83 | G18: 83 | H18: 83 | I18: 83 | J18: 83 | K18: 83 | L18: 83 | M18: 83 | N18: 83 | O18: 996
B19: Advertising | C19: 1000 | D19: 1000 | E19: 1000 | F19: 1000 | G19: 1000 | H19: 1000 | I19: 1000 | J19: 1000 | K19: 1000 | L19: 1000 | M19: 1000 | N19: 1000 | O19: 12000
B21: Total Expenses | C21: 14263 | D21: 9263 | E21: 9263 | F21: 9263 | G21: 10263 | H21: 9263 | I21: 10263 | J21: 9263 | K21: 9263 | L21: 10263 | M21: 9263 | N21: 9263 | O21: 119156
B23: Net Profit | C23: -3964.1563 | D23: =D10-D21 -> 5085.3939 | E23: -1127.0348 | F23: 1896.1427 | G23: 3701.9662 | H23: -141.20126 | I23: -279.82559 | J23: 2377.426 | K23: -110.615 | L23: -299.34935 | M23: 1176.6015 | N23: 2442.0522 | O23: 4757.4002
